Workbook
Name _b2: #REF!
Name _b2: #REF!
Name a: #REF!
Name a: #REF!
Name AccountList2007: #REF!
Name AccountList2007: #REF!
Name AccountList2008: #REF!
Name AccountList2008: #REF!
Name Agg_Marman_Claims: #REF!
Name Agg_Marman_Claims: #REF!
Name Agg_Marman_Summary: #REF!
Name Agg_Marman_Summary: #REF!
Name Aggregate_Summary: #REF!
Name Aggregate_Summary: #REF!
Name Avg_Delay: '[1]Frequency analysis'!$X$14
Name Binder_Table: [2]Console!$B$156:$C$172
Name binder_table_mid: [2]Console!$B$156:$G$172
Name biz_type_table: [2]Console!$B$70:$C$71
Name biz_type_table_mid: [2]Console!$B$70:$G$71
Name Claims_Inflation: '2. Claims data'!$D$6
Name cli_output2: #REF!
Name cli_output2: #REF!
Name COB_BT_Combo_Table: [2]Console!$B$176:$C$194
Name COB_BT_Combo_Table_mid: [2]Console!$B$176:$G$194
Name COB_table: [2]Console!$B$75:$C$86
Name COB_table_mid: [2]Console!$B$75:$G$86
Name Company: #REF!
Name Company: #REF!
Name Contract_Basis: [3]Assumptions!$L$7
Name Contract_length_table: [2]Console!$B$90:$C$93
Name Contract_length_table_mid: [2]Console!$B$90:$G$93
Name Corr_Factor: [3]Assumptions!$L$13
Name country_table: [2]Console!$K$74:$L$182
Name country_table_mid: [2]Console!$K$74:$P$182
Name csi: [4]Assumptions!$C$28
Name csi_client: #REF!
Name csi_client: #REF!
Name csi_market: #REF!
Name csi_market: #REF!
Name csi_mkt: [4]Aggregation!#REF!
Name csi_mkt: [4]Aggregation!#REF!
Name csi_old: #REF!
Name csi_old: #REF!
Name csi_orig: [4]Aggregation!$D$35
Name csi_std_client: #REF!
Name csi_std_client: #REF!
Name CurrentYear: #REF!
Name CurrentYear: #REF!
Name Data_as_at_date: '2. Claims data'!$D$3
Name Data_Set: '[5]1. IBNR Calculations'!$W$7
Name database1: '[6]2007 vs 2008 (2)'!$A$8:$T$130
Name Database2: '[6]2007 vs 2008'!$A$8:$T$130
Name Dcsi_mkt: [4]Aggregation!#REF!
Name Dcsi_mkt: [4]Aggregation!#REF!
Name Default_Inflation: [3]Assumptions!$L$9
Name disct_rate_cli: #REF!
Name disct_rate_cli: #REF!
Name disct_rate_mkt: #REF!
Name disct_rate_mkt: #REF!
Name dlambda_client: #REF!

Sheet 00. DISCLAIMER
B4: This software is intended for purely educational purposes and as supporting material for the textbook "Pricing in General Insurance" by Pietro Parodi and comes with no guarantee. It should not be relied upon for use in a professional context. If you find errors in the code, you are welcome to notify them (pietro_parodi@yahoo.com) and they will be corrected in a successive version of the software.

Sheet 0. Disclaimer
B2: 这个excel文件将展示如何预测最终索赔次数

Sheet 1. Exposure data
A1: Historic exposure data | E1: Exposure inflation | F1: 0.04
A3: Fiscal year | B3: Turnover (x 1€m) | D3: Policy year | E3: Turnover (x 1€m) - aligned to policy year | F3: Turnover (x 1€m) - revalued @ 4% p.a. | H3: Employee Numbers
A4: 2005 | B4: 311.19 | D4: 2005 | E4: =B4 -> 311.19 | F4: =E4*(1+$F$1)^(2012-D4) -> 409.50481 | H4: 12696
A5: 2006 | B5: 381.975 | D5: 2006 | E5: =B5 -> 381.975 | F5: =E5*(1+$F$1)^(2012-D5) -> 483.32023 | H5: 15964
A6: 2007 | B6: 450.23 | D6: 2007 | E6: =B6 -> 450.23 | F6: =E6*(1+$F$1)^(2012-D6) -> 547.77364 | H6: 16706
A7: 2008 | B7: 514.58 | D7: 2008 | E7: =B7 -> 514.58 | F7: =E7*(1+$F$1)^(2012-D7) -> 601.98582 | H7: 17831
A8: 2009 | B8: 675.84 | D8: 2009 | E8: =B8 -> 675.84 | F8: =E8*(1+$F$1)^(2012-D8) -> 760.22809 | H8: 23301
A9: 2010 | B9: 773.96 | D9: 2010 | E9: =B9 -> 773.96 | F9: =E9*(1+$F$1)^(2012-D9) -> 837.11514 | H9: 26377
A10: 2011 | B10: 837.045 | D10: 2011 | E10: =B10 -> 837.045 | F10: =E10*(1+$F$1)^(2012-D10) -> 870.5268 | H10: 27529
A11: 2012 | B11: 1057.54 | D11: 2012 | E11: =B11 -> 1057.54 | F11: =E11*(1+$F$1)^(2012-D11) -> 1057.54 | H11: 29497
A12: 2013 | B12: 1134.21 | D12: 2013 | E12: =B12 -> 1134.21 | F12: =E12*(1+$F$1)^(2012-D12) -> 1090.5865 | H12: 32373
A13: 2014 | B13: 1164.35 | D13: 2014 | E13: =B13 -> 1164.35 | F13: =E13*(1+$F$1)^(2012-D13) -> 1076.507 | H13: 34375
A14: 2015 | B14: 1265 | D14: 2015 | E14: =B14 -> 1265 | F14: =E14*(1+$F$1)^(2012-D14) -> 1124.5804 | H14: 37290

Sheet 2. Claims data
U1: 案例研究中的样本的延迟信息(以年为单位)具有下面两个特点：(a)同一案件的延迟信息(以天为单位)相同(b)。请注意，我们案例研究中的保单在4月1日生效，因此，损失之间存在明显的保单年度不匹配。 由于没有关于案件赔款量化日期和以前的非零赔案何时被调回零的信息。因此对于这个特定的数据集，我们将假设量化日期与报告日期相同，可以忽略索赔准备金为零的案件。
D2: ASSUMPTIONS
C3: Data as-at date | D3: 41973 | F3: Earliest year | G3: =MIN(Table1[Policy Year]) -> 2005
C4: Policy inception month | D4: 4 | F4: Latest year | G4: =MAX(Table1[Policy Year]) -> 2014
C5: Revalue at | D5: 42278 | F5: Earliest year (shifted) | G5: =MIN(Table1[Policy Year (shifted)]) -> 2004
C6: Claims inflation | D6: 0.05 | F6: Latest year (shifted) | G6: =MAX(Table1[Policy Year (shifted)]) -> 2013
C7: Destination currency | D7: GBP | F7: Earliest month | G7: =Earliest_Year*12+Policy_Inception_Month -> 24064
C8: Exchange rate | D8: 1 | F8: Latest third | G8: =MAX(Table1[Reporting third]) -> 28
C9: Policy inception month (shifted) | D9: 12
AB10: 变换后的保单年 | AC10: 变换后的保单年 | AD10: 变换后的延迟日期
F11: 根据新保单生效月调整保单年 | I11: 已付 | J11: 未付 | K11: 已发生 | L11: 费用 | M11: 追偿 | O11: 非零 | P11: 已发生损失 | Q11: 重估值的已发生损失 | R11: 报告延迟 | T11: 风险暴露
A12: Claim ID | B12: Claimant Name | C12: Class of Business | D12: Loss date | E12: Reporting date | F12: Policy Year | G12: Claim description | H12: Original currency | I12: Paid | J12: Outstanding | K12: Total incurred | L12: Fees | M12: Recoveries | N12: Overall amount | O12: Non-zero? (1=Yes) | P12: Overall (destination currency) | Q12: Overall amount (revalued) | R12: Delay (days) | S12: Claim Status | T12: Exposure | U12: Reporting year | V12: Delay (years) | W12: Delay (days)2 | X12: Policy third | Y12: Reporting third | Z12: Delay (thirds) | AA12: % O/S | AB12: Policy Year (shifted) | AC12: Reporting year (shifted) | AD12: Delay (shifted)
A13: Claim_1 | B13: Name_1 | C13: Public Liability Bodily Injury | D13: 40195 | E13: 40561 | F13: =IF(MONTH(Table1[[#This Row],[Loss date]])<Policy_Inception_Month,YEAR(Table1[[#This Row],[Loss date]])-1,YEAR(Table1[[#This Row],[Loss date]])) -> 2009 | G13: Contact With | H13: GBP | I13: 17056.23 | J13: 0 | K13: 17056.23 | L13: 0 | M13: 0 | N13: 17056.23 | O13: =IF(Table1[[#This Row],[Overall amount]]=0,0,1) -> 1 | P13: =Table1[[#This Row],[Overall amount]]*Exchange_Rate -> 17056.23 | Q13: =Table1[[#This Row],[Overall (destination currency)]]*(1+Claims_Inflation)^((Revalue_at_date-Table1[[#This Row],[Loss date]])/365.25) -> 22528.092 | R13: =INT(Table1[[#This Row],[Reporting date]])-INT(Table1[[#This Row],[Loss date]]) -> 366 | S13: Closed | T13: =VLOOKUP(Table1[[#This Row],[Policy Year]],exposure_table,3,FALSE) -> 760.22809 | U13: =IF(MONTH(Table1[[#This Row],[Reporting date]])<Policy_Inception_Month,YEAR(Table1[[#This Row],[Reporting date]])-1,YEAR(Table1[[#This Row],[Reporting date]])) -> 2010 | V13: =Table1[[#This Row],[Reporting year]]-Table1[[#This Row],[Policy Year]] -> 1 | W13: =INT(Table1[[#This Row],[Reporting date]])-INT(Table1[[#This Row],[Loss date]]) -> 366 | X13: =INT((YEAR(Table1[[#This Row],[Loss date]])*12+MONTH(Table1[[#This Row],[Loss date]])-Earliest_Month)/4) -> 14 | Y13: =INT((YEAR(Table1[[#This Row],[Reporting date]])*12+MONTH(Table1[[#This Row],[Reporting date]])-Earliest_Month)/4) -> 17 | Z13: =Table1[[#This Row],[Reporting third]]-Table1[[#This Row],[Policy third]] -> 3 | AA13: =IF(Table1[[#This Row],[Overall amount]]=0,"N/A",Table1[[#This Row],[Outstanding]]/Table1[[#This Row],[Overall amount]]) -> 0 | AB13: =IF(MONTH(Table1[[#This Row],[Loss date]])<Pol_Inc_Month_Shifted,YEAR(Table1[[#This Row],[Loss date]])-1,YEAR(Table1[[#This Row],[Loss date]])) -> 2009 | AC13: =IF(MONTH(Table1[[#This Row],[Reporting date]])<Pol_Inc_Month_Shifted,YEAR(Table1[[#This Row],[Reporting date]])-1,YEAR(Table1[[#This Row],[Reporting date]])) -> 2010 | AD13: =Table1[[#This Row],[Reporting year (shifted)]]-Table1[[#This Row],[Policy Year (shifted)]] -> 1 | AF13: =COUNTIFS(Table1[Policy Year (shifted)],2010, Table1[Non-zero? (1=Yes)],1) -> 268
A14: Claim_2 | B14: Name_2 | C14: Public Liability Bodily Injury | D14: 39144 | E14: 39195 | F14: =IF(MONTH(Table1[[#This Row],[Loss date]])<Policy_Inception_Month,YEAR(Table1[[#This Row],[Loss date]])-1,YEAR(Table1[[#This Row],[Loss date]])) -> 2006 | G14: Slip,Trip Or Fall-Same Level | H14: GBP | I14: 27297.096 | J14: 0 | K14: 27297.096 | L14: 0 | M14: 0 | N14: 27297.096 | O14: =IF(Table1[[#This Row],[Overall amount]]=0,0,1) -> 1 | P14: =Table1[[#This Row],[Overall amount]]*Exchange_Rate -> 27297.096 | Q14: =Table1[[#This Row],[Overall (destination currency)]]*(1+Claims_Inflation)^((Revalue_at_date-Table1[[#This Row],[Loss date]])/365.25) -> 41488.68 | R14: =INT(Table1[[#This Row],[Reporting date]])-INT(Table1[[#This Row],[Loss date]]) -> 51 | S14: Closed | T14: =VLOOKUP(Table1[[#This Row],[Policy Year]],exposure_table,3,FALSE) -> 483.32023 | U14: =IF(MONTH(Table1[[#This Row],[Reporting date]])<Policy_Inception_Month,YEAR(Table1[[#This Row],[Reporting date]])-1,YEAR(Table1[[#This Row],[Reporting date]])) -> 2007 | V14: =Table1[[#This Row],[Reporting year]]-Table1[[#This Row],[Policy Year]] -> 1 | W14: =INT(Table1[[#This Row],[Reporting date]])-INT(Table1[[#This Row],[Loss date]]) -> 51 | X14: =INT((YEAR(Table1[[#This Row],[Loss date]])*12+MONTH(Table1[[#This Row],[Loss date]])-Earliest_Month)/4) -> 5 | Y14: =INT((YEAR(Table1[[#This Row],[Reporting date]])*12+MONTH(Table1[[#This Row],[Reporting date]])-Earliest_Month)/4) -> 6 | Z14: =Table1[[#This Row],[Reporting third]]-Table1[[#This Row],[Policy third]] -> 1 | AA14: =IF(Table1[[#This Row],[Overall amount]]=0,"N/A",Table1[[#This Row],[Outstanding]]/Table1[[#This Row],[Overall amount]]) -> 0 | AB14: =IF(MONTH(Table1[[#This Row],[Loss date]])<Pol_Inc_Month_Shifted,YEAR(Table1[[#This Row],[Loss date]])-1,YEAR(Table1[[#This Row],[Loss date]])) -> 2006 | AC14: =IF(MONTH(Table1[[#This Row],[Reporting date]])<Pol_Inc_Month_Shifted,YEAR(Table1[[#This Row],[Reporting date]])-1,YEAR(Table1[[#This Row],[Reporting date]])) -> 2006 | AD14: =Table1[[#This Row],[Reporting year (shifted)]]-Table1[[#This Row],[Policy Year (shifted)]] -> 0
A15: Claim_3 | B15: Name_3 | C15: Public Liability Bodily Injury | D15: 39268 | E15: 39622 | F15: =IF(MONTH(Table1[[#This Row],[Loss date]])<Policy_Inception_Month,YEAR(Table1[[#This Row],[Loss date]])-1,YEAR(Table1[[#This Row],[Loss date]])) -> 2007 | G15: Slip,Trip Or Fall-Elevated Surfaces | H15: GBP | I15: 2230.5459 | J15: 0 | K15: 2230.5459 | L15: 0 | M15: 0 | N15: 2230.5459 | O15: =IF(Table1[[#This Row],[Overall amount]]=0,0,1) -> 1 | P15: =Table1[[#This Row],[Overall amount]]*Exchange_Rate -> 2230.5459 | Q15: =Table1[[#This Row],[Overall (destination currency)]]*(1+Claims_Inflation)^((Revalue_at_date-Table1[[#This Row],[Loss date]])/365.25) -> 3334.5 | R15: =INT(Table1[[#This Row],[Reporting date]])-INT(Table1[[#This Row],[Loss date]]) -> 354 | S15: Closed | T15: =VLOOKUP(Table1[[#This Row],[Policy Year]],exposure_table,3,FALSE) -> 547.77364 | U15: =IF(MONTH(Table1[[#This Row],[Reporting date]])<Policy_Inception_Month,YEAR(Table1[[#This Row],[Reporting date]])-1,YEAR(Table1[[#This Row],[Reporting date]])) -> 2008 | V15: =Table1[[#This Row],[Reporting year]]-Table1[[#This Row],[Policy Year]] -> 1 | W15: =INT(Table1[[#This Row],[Reporting date]])-INT(Table1[[#This Row],[Loss date]]) -> 354 | X15: =INT((YEAR(Table1[[#This Row],[Loss date]])*12+MONTH(Table1[[#This Row],[Loss date]])-Earliest_Month)/4) -> 6 | Y15: =INT((YEAR(Table1[[#This Row],[Reporting date]])*12+MONTH(Table1[[#This Row],[Reporting date]])-Earliest_Month)/4) -> 9 | Z15: =Table1[[#This Row],[Reporting third]]-Table1[[#This Row],[Policy third]] -> 3 | AA15: =IF(Table1[[#This Row],[Overall amount]]=0,"N/A",Table1[[#This Row],[Outstanding]]/Table1[[#This Row],[Overall amount]]) -> 0 | AB15: =IF(MONTH(Table1[[#This Row],[Loss date]])<Pol_Inc_Month_Shifted,YEAR(Table1[[#This Row],[Loss date]])-1,YEAR(Table1[[#This Row],[Loss date]])) -> 2006 | AC15: =IF(MONTH(Table1[[#This Row],[Reporting date]])<Pol_Inc_Month_Shifted,YEAR(Table1[[#This Row],[Reporting date]])-1,YEAR(Table1[[#This Row],[Reporting date]])) -> 2007 | AD15: =Table1[[#This Row],[Reporting year (shifted)]]-Table1[[#This Row],[Policy Year (shifted)]] -> 1
A16: Claim_4 | B16: Name_4 | C16: Public Liability Bodily Injury | D16: 39605 | E16: 40201 | F16: =IF(MONTH(Table1[[#This Row],[Loss date]])<Policy_Inception_Month,YEAR(Table1[[#This Row],[Loss date]])-1,YEAR(Table1[[#This Row],[Loss date]])) -> 2008 | G16: Slip,Trip Or Fall-Same Level | H16: GBP | I16: 13516.419 | J16: 0 | K16: 13516.419 | L16: 0 | M16: 1189.4449 | N16: 12326.974 | O16: =IF(Table1[[#This Row],[Overall amount]]=0,0,1) -> 1 | P16: =Table1[[#This Row],[Overall amount]]*Exchange_Rate -> 12326.974 | Q16: =Table1[[#This Row],[Overall (destination currency)]]*(1+Claims_Inflation)^((Revalue_at_date-Table1[[#This Row],[Loss date]])/365.25) -> 17616.743 | R16: =INT(Table1[[#This Row],[Reporting date]])-INT(Table1[[#This Row],[Loss date]]) -> 596 | S16: Closed | T16: =VLOOKUP(Table1[[#This Row],[Policy Year]],exposure_table,3,FALSE) -> 601.98582 | U16: =IF(MONTH(Table1[[#This Row],[Reporting date]])<Policy_Inception_Month,YEAR(Table1[[#This Row],[Reporting date]])-1,YEAR(Table1[[#This Row],[Reporting date]])) -> 2009 | V16: =Table1[[#This Row],[Reporting year]]-Table1[[#This Row],[Policy Year]] -> 1 | W16: =INT(Table1[[#This Row],[Reporting date]])-INT(Table1[[#This Row],[Loss date]]) -> 596 | X16: =INT((YEAR(Table1[[#This Row],[Loss date]])*12+MONTH(Table1[[#This Row],[Loss date]])-Earliest_Month)/4) -> 9 | Y16: =INT((YEAR(Table1[[#This Row],[Reporting date]])*12+MONTH(Table1[[#This Row],[Reporting date]])-Earliest_Month)/4) -> 14 | Z16: =Table1[[#This Row],[Reporting third]]-Table1[[#This Row],[Policy third]] -> 5 | AA16: =IF(Table1[[#This Row],[Overall amount]]=0,"N/A",Table1[[#This Row],[Outstanding]]/Table1[[#This Row],[Overall amount]]) -> 0 | AB16: =IF(MONTH(Table1[[#This Row],[Loss date]])<Pol_Inc_Month_Shifted,YEAR(Table1[[#This Row],[Loss date]])-1,YEAR(Table1[[#This Row],[Loss date]])) -> 2007 | AC16: =IF(MONTH(Table1[[#This Row],[Reporting date]])<Pol_Inc_Month_Shifted,YEAR(Table1[[#This Row],[Reporting date]])-1,YEAR(Table1[[#This Row],[Reporting date]])) -> 2009 | AD16: =Table1[[#This Row],[Reporting year (shifted)]]-Table1[[#This Row],[Policy Year (shifted)]] -> 2
A17: Claim_5 | B17: Name_5 | C17: Public Liability Bodily Injury | D17: 40344 | E17: 40348 | F17: =IF(MONTH(Table1[[#This Row],[Loss date]])<Policy_Inception_Month,YEAR(Table1[[#This Row],[Loss date]])-1,YEAR(Table1[[#This Row],[Loss date]])) -> 2010 | G17: Caught Between Moving Objects | H17: GBP | I17: 873.50459 | J17: 0 | K17: 873.50459 | L17: 0 | M17: 0 | N17: 873.50459 | O17: =IF(Table1[[#This Row],[Overall amount]]=0,0,1) -> 1 | P17: =Table1[[#This Row],[Overall amount]]*Exchange_Rate -> 873.50459 | Q17: =Table1[[#This Row],[Overall (destination currency)]]*(1+Claims_Inflation)^((Revalue_at_date-Table1[[#This Row],[Loss date]])/365.25) -> 1131 | R17: =INT(Table1[[#This Row],[Reporting date]])-INT(Table1[[#This Row],[Loss date]]) -> 4 | S17: Closed | T17: =VLOOKUP(Table1[[#This Row],[Policy Year]],exposure_table,3,FALSE) -> 837.11514 | U17: =IF(MONTH(Table1[[#This Row],[Reporting date]])<Policy_Inception_Month,YEAR(Table1[[#This Row],[Reporting date]])-1,YEAR(Table1[[#This Row],[Reporting date]])) -> 2010 | V17: =Table1[[#This Row],[Reporting year]]-Table1[[#This Row],[Policy Year]] -> 0 | W17: =INT(Table1[[#This Row],[Reporting date]])-INT(Table1[[#This Row],[Loss date]]) -> 4 | X17: =INT((YEAR(Table1[[#This Row],[Loss date]])*12+MONTH(Table1[[#This Row],[Loss date]])-Earliest_Month)/4) -> 15 | Y17: =INT((YEAR(Table1[[#This Row],[Reporting date]])*12+MONTH(Table1[[#This Row],[Reporting date]])-Earliest_Month)/4) -> 15 | Z17: =Table1[[#This Row],[Reporting third]]-Table1[[#This Row],[Policy third]] -> 0 | AA17: =IF(Table1[[#This Row],[Overall amount]]=0,"N/A",Table1[[#This Row],[Outstanding]]/Table1[[#This Row],[Overall amount]]) -> 0 | AB17: =IF(MONTH(Table1[[#This Row],[Loss date]])<Pol_Inc_Month_Shifted,YEAR(Table1[[#This Row],[Loss date]])-1,YEAR(Table1[[#This Row],[Loss date]])) -> 2009 | AC17: =IF(MONTH(Table1[[#This Row],[Reporting date]])<Pol_Inc_Month_Shifted,YEAR(Table1[[#This Row],[Reporting date]])-1,YEAR(Table1[[#This Row],[Reporting date]])) -> 2009 | AD17: =Table1[[#This Row],[Reporting year (shifted)]]-Table1[[#This Row],[Policy Year (shifted)]] -> 0
A18: Claim_6 | B18: Name_6 | C18: Public Liability Bodily Injury | D18: 39284 | E18: 39691 | F18: =IF(MONTH(Table1[[#This Row],[Loss date]])<Policy_Inception_Month,YEAR(Table1[[#This Row],[Loss date]])-1,YEAR(Table1[[#This Row],[Loss date]])) -> 2007 | G18: Slip,Trip Or Fall-Same Level | H18: GBP | I18: 866.10894 | J18: 0 | K18: 866.10894 | L18: 0 | M18: 0 | N18: 866.10894 | O18: =IF(Table1[[#This Row],[Overall amount]]=0,0,1) -> 1 | P18: =Table1[[#This Row],[Overall amount]]*Exchange_Rate -> 866.10894 | Q18: =Table1[[#This Row],[Overall (destination currency)]]*(1+Claims_Inflation)^((Revalue_at_date-Table1[[#This Row],[Loss date]])/365.25) -> 1292.004 | R18: =INT(Table1[[#This Row],[Reporting date]])-INT(Table1[[#This Row],[Loss date]]) -> 407 | S18: Closed | T18: =VLOOKUP(Table1[[#This Row],[Policy Year]],exposure_table,3,FALSE) -> 547.77364 | U18: =IF(MONTH(Table1[[#This Row],[Reporting date]])<Policy_Inception_Month,YEAR(Table1[[#This Row],[Reporting date]])-1,YEAR(Table1[[#This Row],[Reporting date]])) -> 2008 | V18: =Table1[[#This Row],[Reporting year]]-Table1[[#This Row],[Policy Year]] -> 1 | W18: =INT(Table1[[#This Row],[Reporting date]])-INT(Table1[[#This Row],[Loss date]]) -> 407 | X18: =INT((YEAR(Table1[[#This Row],[Loss date]])*12+MONTH(Table1[[#This Row],[Loss date]])-Earliest_Month)/4) -> 6 | Y18: =INT((YEAR(Table1[[#This Row],[Reporting date]])*12+MONTH(Table1[[#This Row],[Reporting date]])-Earliest_Month)/4) -> 10 | Z18: =Table1[[#This Row],[Reporting third]]-Table1[[#This Row],[Policy third]] -> 4 | AA18: =IF(Table1[[#This Row],[Overall amount]]=0,"N/A",Table1[[#This Row],[Outstanding]]/Table1[[#This Row],[Overall amount]]) -> 0 | AB18: =IF(MONTH(Table1[[#This Row],[Loss date]])<Pol_Inc_Month_Shifted,YEAR(Table1[[#This Row],[Loss date]])-1,YEAR(Table1[[#This Row],[Loss date]])) -> 2006 | AC18: =IF(MONTH(Table1[[#This Row],[Reporting date]])<Pol_Inc_Month_Shifted,YEAR(Table1[[#This Row],[Reporting date]])-1,YEAR(Table1[[#This Row],[Reporting date]])) -> 2007 | AD18: =Table1[[#This Row],[Reporting year (shifted)]]-Table1[[#This Row],[Policy Year (shifted)]] -> 1
A19: Claim_7 | B19: Name_7 | C19: Public Liability Bodily Injury | D19: 40055 | E19: 40111 | F19: =IF(MONTH(Table1[[#This Row],[Loss date]])<Policy_Inception_Month,YEAR(Table1[[#This Row],[Loss date]])-1,YEAR(Table1[[#This Row],[Loss date]])) -> 2009 | G19: Slip,Trip Or Fall-Same Level | H19: GBP | I19: 413.74811 | J19: 0 | K19: 413.74811 | L19: 0 | M19: 0 | N19: 413.74811 | O19: =IF(Table1[[#This Row],[Overall amount]]=0,0,1) -> 1 | P19: =Table1[[#This Row],[Overall amount]]*Exchange_Rate -> 413.74811 | Q19: =Table1[[#This Row],[Overall (destination currency)]]*(1+Claims_Inflation)^((Revalue_at_date-Table1[[#This Row],[Loss date]])/365.25) -> 556.8 | R19: =INT(Table1[[#This Row],[Reporting date]])-INT(Table1[[#This Row],[Loss date]]) -> 56 | S19: Closed | T19: =VLOOKUP(Table1[[#This Row],[Policy Year]],exposure_table,3,FALSE) -> 760.22809 | U19: =IF(MONTH(Table1[[#This Row],[Reporting date]])<Policy_Inception_Month,YEAR(Table1[[#This Row],[Reporting date]])-1,YEAR(Table1[[#This Row],[Reporting date]])) -> 2009 | V19: =Table1[[#This Row],[Reporting year]]-Table1[[#This Row],[Policy Year]] -> 0 | W19: =INT(Table1[[#This Row],[Reporting date]])-INT(Table1[[#This Row],[Loss date]]) -> 56 | X19: =INT((YEAR(Table1[[#This Row],[Loss date]])*12+MONTH(Table1[[#This Row],[Loss date]])-Earliest_Month)/4) -> 13 | Y19: =INT((YEAR(Table1[[#This Row],[Reporting date]])*12+MONTH(Table1[[#This Row],[Reporting date]])-Earliest_Month)/4) -> 13 | Z19: =Table1[[#This Row],[Reporting third]]-Table1[[#This Row],[Policy third]] -> 0 | AA19: =IF(Table1[[#This Row],[Overall amount]]=0,"N/A",Table1[[#This Row],[Outstanding]]/Table1[[#This Row],[Overall amount]]) -> 0 | AB19: =IF(MONTH(Table1[[#This Row],[Loss date]])<Pol_Inc_Month_Shifted,YEAR(Table1[[#This Row],[Loss date]])-1,YEAR(Table1[[#This Row],[Loss date]])) -> 2008 | AC19: =IF(MONTH(Table1[[#This Row],[Reporting date]])<Pol_Inc_Month_Shifted,YEAR(Table1[[#This Row],[Reporting date]])-1,YEAR(Table1[[#This Row],[Reporting date]])) -> 2008 | AD19: =Table1[[#This Row],[Reporting year (shifted)]]-Table1[[#This Row],[Policy Year (shifted)]] -> 0
A20: Claim_8 | B20: Name_8 | C20: Public Liability Bodily Injury | D20: 39298 | E20: 39487 | F20: =IF(MONTH(Table1[[#This Row],[Loss date]])<Policy_Inception_Month,YEAR(Table1[[#This Row],[Loss date]])-1,YEAR(Table1[[#This Row],[Loss date]])) -> 2007 | G20: Caught Between Moving Objects | H20: GBP | I20: 38016.942 | J20: 0 | K20: 38016.942 | L20: 0 | M20: 0 | N20: 38016.942 | O20: =IF(Table1[[#This Row],[Overall amount]]=0,0,1) -> 1 | P20: =Table1[[#This Row],[Overall amount]]*Exchange_Rate -> 38016.942 | Q20: =Table1[[#This Row],[Overall (destination currency)]]*(1+Claims_Inflation)^((Revalue_at_date-Table1[[#This Row],[Loss date]])/365.25) -> 56605.2 | R20: =INT(Table1[[#This Row],[Reporting date]])-INT(Table1[[#This Row],[Loss date]]) -> 189 | S20: Closed | T20: =VLOOKUP(Table1[[#This Row],[Policy Year]],exposure_table,3,FALSE) -> 547.77364 | U20: =IF(MONTH(Table1[[#This Row],[Reporting date]])<Policy_Inception_Month,YEAR(Table1[[#This Row],[Reporting date]])-1,YEAR(Table1[[#This Row],[Reporting date]])) -> 2007 | V20: =Table1[[#This Row],[Reporting year]]-Table1[[#This Row],[Policy Year]] -> 0 | W20: =INT(Table1[[#This Row],[Reporting date]])-INT(Table1[[#This Row],[Loss date]]) -> 189 | X20: =INT((YEAR(Table1[[#This Row],[Loss date]])*12+MONTH(Table1[[#This Row],[Loss date]])-Earliest_Month)/4) -> 7 | Y20: =INT((YEAR(Table1[[#This Row],[Reporting date]])*12+MONTH(Table1[[#This Row],[Reporting date]])-Earliest_Month)/4) -> 8 | Z20: =Table1[[#This Row],[Reporting third]]-Table1[[#This Row],[Policy third]] -> 1 | AA20: =IF(Table1[[#This Row],[Overall amount]]=0,"N/A",Table1[[#This Row],[Outstanding]]/Table1[[#This Row],[Overall amount]]) -> 0 | AB20: =IF(MONTH(Table1[[#This Row],[Loss date]])<Pol_Inc_Month_Shifted,YEAR(Table1[[#This Row],[Loss date]])-1,YEAR(Table1[[#This Row],[Loss date]])) -> 2006 | AC20: =IF(MONTH(Table1[[#This Row],[Reporting date]])<Pol_Inc_Month_Shifted,YEAR(Table1[[#This Row],[Reporting date]])-1,YEAR(Table1[[#This Row],[Reporting date]])) -> 2007 | AD20: =Table1[[#This Row],[Reporting year (shifted)]]-Table1[[#This Row],[Policy Year (shifted)]] -> 1
A21: Claim_9 | B21: Name_9 | C21: Public Liability Bodily Injury | D21: 39937 | E21: 39959 | F21: =IF(MONTH(Table1[[#This Row],[Loss date]])<Policy_Inception_Month,YEAR(Table1[[#This Row],[Loss date]])-1,YEAR(Table1[[#This Row],[Loss date]])) -> 2009 | G21: Slip,Trip Or Fall-Same Level | H21: GBP | I21: 674.55344 | J21: 0 | K21: 674.55344 | L21: 0 | M21: 0 | N21: 674.55344 | O21: =IF(Table1[[#This Row],[Overall amount]]=0,0,1) -> 1 | P21: =Table1[[#This Row],[Overall amount]]*Exchange_Rate -> 674.55344 | Q21: =Table1[[#This Row],[Overall (destination currency)]]*(1+Claims_Inflation)^((Revalue_at_date-Table1[[#This Row],[Loss date]])/365.25) -> 922.2 | R21: =INT(Table1[[#This Row],[Reporting date]])-INT(Table1[[#This Row],[Loss date]]) -> 22 | S21: Closed | T21: =VLOOKUP(Table1[[#This Row],[Policy Year]],exposure_table,3,FALSE) -> 760.22809 | U21: =IF(MONTH(Table1[[#This Row],[Reporting date]])<Policy_Inception_Month,YEAR(Table1[[#This Row],[Reporting date]])-1,YEAR(Table1[[#This Row],[Reporting date]])) -> 2009 | V21: =Table1[[#This Row],[Reporting year]]-Table1[[#This Row],[Policy Year]] -> 0 | W21: =INT(Table1[[#This Row],[Reporting date]])-INT(Table1[[#This Row],[Loss date]]) -> 22 | X21: =INT((YEAR(Table1[[#This Row],[Loss date]])*12+MONTH(Table1[[#This Row],[Loss date]])-Earliest_Month)/4) -> 12 | Y21: =INT((YEAR(Table1[[#This Row],[Reporting date]])*12+MONTH(Table1[[#This Row],[Reporting date]])-Earliest_Month)/4) -> 12 | Z21: =Table1[[#This Row],[Reporting third]]-Table1[[#This Row],[Policy third]] -> 0 | AA21: =IF(Table1[[#This Row],[Overall amount]]=0,"N/A",Table1[[#This Row],[Outstanding]]/Table1[[#This Row],[Overall amount]]) -> 0 | AB21: =IF(MONTH(Table1[[#This Row],[Loss date]])<Pol_Inc_Month_Shifted,YEAR(Table1[[#This Row],[Loss date]])-1,YEAR(Table1[[#This Row],[Loss date]])) -> 2008 | AC21: =IF(MONTH(Table1[[#This Row],[Reporting date]])<Pol_Inc_Month_Shifted,YEAR(Table1[[#This Row],[Reporting date]])-1,YEAR(Table1[[#This Row],[Reporting date]])) -> 2008 | AD21: =Table1[[#This Row],[Reporting year (shifted)]]-Table1[[#This Row],[Policy Year (shifted)]] -> 0
A22: Claim_10 | B22: Name_10 | C22: Public Liability Bodily Injury | D22: 40489 | E22: 40517 | F22: =IF(MONTH(Table1[[#This Row],[Loss date]])<Policy_Inception_Month,YEAR(Table1[[#This Row],[Loss date]])-1,YEAR(Table1[[#This Row],[Loss date]])) -> 2010 | G22: Slip,Trip Or Fall-Same Level | H22: GBP | I22: 3572.9845 | J22: 0 | K22: 3572.9845 | L22: 0 | M22: 0 | N22: 3572.9845 | O22: =IF(Table1[[#This Row],[Overall amount]]=0,0,1) -> 1 | P22: =Table1[[#This Row],[Overall amount]]*Exchange_Rate -> 3572.9845 | Q22: =Table1[[#This Row],[Overall (destination currency)]]*(1+Claims_Inflation)^((Revalue_at_date-Table1[[#This Row],[Loss date]])/365.25) -> 4537.5 | R22: =INT(Table1[[#This Row],[Reporting date]])-INT(Table1[[#This Row],[Loss date]]) -> 28 | S22: Closed | T22: =VLOOKUP(Table1[[#This Row],[Policy Year]],exposure_table,3,FALSE) -> 837.11514 | U22: =IF(MONTH(Table1[[#This Row],[Reporting date]])<Policy_Inception_Month,YEAR(Table1[[#This Row],[Reporting date]])-1,YEAR(Table1[[#This Row],[Reporting date]])) -> 2010 | V22: =Table1[[#This Row],[Reporting year]]-Table1[[#This Row],[Policy Year]] -> 0 | W22: =INT(Table1[[#This Row],[Reporting date]])-INT(Table1[[#This Row],[Loss date]]) -> 28 | X22: =INT((YEAR(Table1[[#This Row],[Loss date]])*12+MONTH(Table1[[#This Row],[Loss date]])-Earliest_Month)/4) -> 16 | Y22: =INT((YEAR(Table1[[#This Row],[Reporting date]])*12+MONTH(Table1[[#This Row],[Reporting date]])-Earliest_Month)/4) -> 17 | Z22: =Table1[[#This Row],[Reporting third]]-Table1[[#This Row],[Policy third]] -> 1 | AA22: =IF(Table1[[#This Row],[Overall amount]]=0,"N/A",Table1[[#This Row],[Outstanding]]/Table1[[#This Row],[Overall amount]]) -> 0 | AB22: =IF(MONTH(Table1[[#This Row],[Loss date]])<Pol_Inc_Month_Shifted,YEAR(Table1[[#This Row],[Loss date]])-1,YEAR(Table1[[#This Row],[Loss date]])) -> 2009 | AC22: =IF(MONTH(Table1[[#This Row],[Reporting date]])<Pol_Inc_Month_Shifted,YEAR(Table1[[#This Row],[Reporting date]])-1,YEAR(Table1[[#This Row],[Reporting date]])) -> 2010 | AD22: =Table1[[#This Row],[Reporting year (shifted)]]-Table1[[#This Row],[Policy Year (shifted)]] -> 1
A23: Claim_11 | B23: Name_11 | C23: Public Liability Bodily Injury | D23: 40421 | E23: 40557 | F23: =IF(MONTH(Table1[[#This Row],[Loss date]])<Policy_Inception_Month,YEAR(Table1[[#This Row],[Loss date]])-1,YEAR(Table1[[#This Row],[Loss date]])) -> 2010 | G23: Slip,Trip Or Fall-Same Level | H23: GBP | I23: 6885.4159 | J23: 0 | K23: 6885.4159 | L23: 0 | M23: 0 | N23: 6885.4159 | O23: =IF(Table1[[#This Row],[Overall amount]]=0,0,1) -> 1 | P23: =Table1[[#This Row],[Overall amount]]*Exchange_Rate -> 6885.4159 | Q23: =Table1[[#This Row],[Overall (destination currency)]]*(1+Claims_Inflation)^((Revalue_at_date-Table1[[#This Row],[Loss date]])/365.25) -> 8823.9 | R23: =INT(Table1[[#This Row],[Reporting date]])-INT(Table1[[#This Row],[Loss date]]) -> 136 | S23: Closed | T23: =VLOOKUP(Table1[[#This Row],[Policy Year]],exposure_table,3,FALSE) -> 837.11514 | U23: =IF(MONTH(Table1[[#This Row],[Reporting date]])<Policy_Inception_Month,YEAR(Table1[[#This Row],[Reporting date]])-1,YEAR(Table1[[#This Row],[Reporting date]])) -> 2010 | V23: =Table1[[#This Row],[Reporting year]]-Table1[[#This Row],[Policy Year]] -> 0 | W23: =INT(Table1[[#This Row],[Reporting date]])-INT(Table1[[#This Row],[Loss date]]) -> 136 | X23: =INT((YEAR(Table1[[#This Row],[Loss date]])*12+MONTH(Table1[[#This Row],[Loss date]])-Earliest_Month)/4) -> 16 | Y23: =INT((YEAR(Table1[[#This Row],[Reporting date]])*12+MONTH(Table1[[#This Row],[Reporting date]])-Earliest_Month)/4) -> 17 | Z23: =Table1[[#This Row],[Reporting third]]-Table1[[#This Row],[Policy third]] -> 1 | AA23: =IF(Table1[[#This Row],[Overall amount]]=0,"N/A",Table1[[#This Row],[Outstanding]]/Table1[[#This Row],[Overall amount]]) -> 0 | AB23: =IF(MONTH(Table1[[#This Row],[Loss date]])<Pol_Inc_Month_Shifted,YEAR(Table1[[#This Row],[Loss date]])-1,YEAR(Table1[[#This Row],[Loss date]])) -> 2009 | AC23: =IF(MONTH(Table1[[#This Row],[Reporting date]])<Pol_Inc_Month_Shifted,YEAR(Table1[[#This Row],[Reporting date]])-1,YEAR(Table1[[#This Row],[Reporting date]])) -> 2010 | AD23: =Table1[[#This Row],[Reporting year (shifted)]]-Table1[[#This Row],[Policy Year (shifted)]] -> 1
A24: Claim_12 | B24: Name_12 | C24: Public Liability Property Damage | D24: 39368 | E24: 39451 | F24: =IF(MONTH(Table1[[#This Row],[Loss date]])<Policy_Inception_Month,YEAR(Table1[[#This Row],[Loss date]])-1,YEAR(Table1[[#This Row],[Loss date]])) -> 2007 | G24: Contact With | H24: GBP | I24: 3893.5168 | J24: 0 | K24: 3893.5168 | L24: 0 | M24: 0 | N24: 3893.5168 | O24: =IF(Table1[[#This Row],[Overall amount]]=0,0,1) -> 1 | P24: =Table1[[#This Row],[Overall amount]]*Exchange_Rate -> 3893.5168 | Q24: =Table1[[#This Row],[Overall (destination currency)]]*(1+Claims_Inflation)^((Revalue_at_date-Table1[[#This Row],[Loss date]])/365.25) -> 5743.284 | R24: =INT(Table1[[#This Row],[Reporting date]])-INT(Table1[[#This Row],[Loss date]]) -> 83 | S24: Closed | T24: =VLOOKUP(Table1[[#This Row],[Policy Year]],exposure_table,3,FALSE) -> 547.77364 | U24: =IF(MONTH(Table1[[#This Row],[Reporting date]])<Policy_Inception_Month,YEAR(Table1[[#This Row],[Reporting date]])-1,YEAR(Table1[[#This Row],[Reporting date]])) -> 2007 | V24: =Table1[[#This Row],[Reporting year]]-Table1[[#This Row],[Policy Year]] -> 0 | W24: =INT(Table1[[#This Row],[Reporting date]])-INT(Table1[[#This Row],[Loss date]]) -> 83 | X24: =INT((YEAR(Table1[[#This Row],[Loss date]])*12+MONTH(Table1[[#This Row],[Loss date]])-Earliest_Month)/4) -> 7 | Y24: =INT((YEAR(Table1[[#This Row],[Reporting date]])*12+MONTH(Table1[[#This Row],[Reporting date]])-Earliest_Month)/4) -> 8 | Z24: =Table1[[#This Row],[Reporting third]]-Table1[[#This Row],[Policy third]] -> 1 | AA24: =IF(Table1[[#This Row],[Overall amount]]=0,"N/A",Table1[[#This Row],[Outstanding]]/Table1[[#This Row],[Overall amount]]) -> 0 | AB24: =IF(MONTH(Table1[[#This Row],[Loss date]])<Pol_Inc_Month_Shifted,YEAR(Table1[[#This Row],[Loss date]])-1,YEAR(Table1[[#This Row],[Loss date]])) -> 2006 | AC24: =IF(MONTH(Table1[[#This Row],[Reporting date]])<Pol_Inc_Month_Shifted,YEAR(Table1[[#This Row],[Reporting date]])-1,YEAR(Table1[[#This Row],[Reporting date]])) -> 2007 | AD24: =Table1[[#This Row],[Reporting year (shifted)]]-Table1[[#This Row],[Policy Year (shifted)]] -> 1
A25: Claim_13 | B25: Name_13 | C25: Public Liability Property Damage | D25: 39089 | E25: 39192 | F25: =IF(MONTH(Table1[[#This Row],[Loss date]])<Policy_Inception_Month,YEAR(Table1[[#This Row],[Loss date]])-1,YEAR(Table1[[#This Row],[Loss date]])) -> 2006 | G25: Contact With | H25: GBP | I25: 482.98571 | J25: 0 | K25: 482.98571 | L25: 0 | M25: 7.2447856 | N25: 475.74092 | O25: =IF(Table1[[#This Row],[Overall amount]]=0,0,1) -> 1 | P25: =Table1[[#This Row],[Overall amount]]*Exchange_Rate -> 475.74092 | Q25: =Table1[[#This Row],[Overall (destination currency)]]*(1+Claims_Inflation)^((Revalue_at_date-Table1[[#This Row],[Loss date]])/365.25) -> 728.4075 | R25: =INT(Table1[[#This Row],[Reporting date]])-INT(Table1[[#This Row],[Loss date]]) -> 103 | S25: Closed | T25: =VLOOKUP(Table1[[#This Row],[Policy Year]],exposure_table,3,FALSE) -> 483.32023 | U25: =IF(MONTH(Table1[[#This Row],[Reporting date]])<Policy_Inception_Month,YEAR(Table1[[#This Row],[Reporting date]])-1,YEAR(Table1[[#This Row],[Reporting date]])) -> 2007 | V25: =Table1[[#This Row],[Reporting year]]-Table1[[#This Row],[Policy Year]] -> 1 | W25: =INT(Table1[[#This Row],[Reporting date]])-INT(Table1[[#This Row],[Loss date]]) -> 103 | X25: =INT((YEAR(Table1[[#This Row],[Loss date]])*12+MONTH(Table1[[#This Row],[Loss date]])-Earliest_Month)/4) -> 5 | Y25: =INT((YEAR(Table1[[#This Row],[Reporting date]])*12+MONTH(Table1[[#This Row],[Reporting date]])-Earliest_Month)/4) -> 6 | Z25: =Table1[[#This Row],[Reporting third]]-Table1[[#This Row],[Policy third]] -> 1 | AA25: =IF(Table1[[#This Row],[Overall amount]]=0,"N/A",Table1[[#This Row],[Outstanding]]/Table1[[#This Row],[Overall amount]]) -> 0 | AB25: =IF(MONTH(Table1[[#This Row],[Loss date]])<Pol_Inc_Month_Shifted,YEAR(Table1[[#This Row],[Loss date]])-1,YEAR(Table1[[#This Row],[Loss date]])) -> 2006 | AC25: =IF(MONTH(Table1[[#This Row],[Reporting date]])<Pol_Inc_Month_Shifted,YEAR(Table1[[#This Row],[Reporting date]])-1,YEAR(Table1[[#This Row],[Reporting date]])) -> 2006 | AD25: =Table1[[#This Row],[Reporting year (shifted)]]-Table1[[#This Row],[Policy Year (shifted)]] -> 0
... A1730: Claim_1718 | B1730: Name_1718 | C1730: Public Liability Property Damage | D1730: 41677 | E1730: 41684 | F1730: =IF(MONTH(Table1[[#This Row],[Loss date]])<Policy_Inception_Month,YEAR(Table1[[#This Row],[Loss date]])-1,YEAR(Table1[[#This Row],[Loss date]])) -> 2013 | G1730: Property Damage | H1730: GBP | I1730: 0 | J1730: 0 | K1730: 0 | L1730: 0 | M1730: 0 | N1730: 0 | O1730: =IF(Table1[[#This Row],[Overall amount]]=0,0,1) -> 0 | P1730: =Table1[[#This Row],[Overall amount]]*Exchange_Rate -> 0 | Q1730: =Table1[[#This Row],[Overall (destination currency)]]*(1+Claims_Inflation)^((Revalue_at_date-Table1[[#This Row],[Loss date]])/365.25) -> 0 | R1730: =INT(Table1[[#This Row],[Reporting date]])-INT(Table1[[#This Row],[Loss date]]) -> 7 | S1730: Closed | T1730: =VLOOKUP(Table1[[#This Row],[Policy Year]],exposure_table,3,FALSE) -> 1090.5865 | U1730: =IF(MONTH(Table1[[#This Row],[Reporting date]])<Policy_Inception_Month,YEAR(Table1[[#This Row],[Reporting date]])-1,YEAR(Table1[[#This Row],[Reporting date]])) -> 2013 | V1730: =Table1[[#This Row],[Reporting year]]-Table1[[#This Row],[Policy Year]] -> 0 | W1730: =INT(Table1[[#This Row],[Reporting date]])-INT(Table1[[#This Row],[Loss date]]) -> 7 | X1730: =INT((YEAR(Table1[[#This Row],[Loss date]])*12+MONTH(Table1[[#This Row],[Loss date]])-Earliest_Month)/4) -> 26 | Y1730: =INT((YEAR(Table1[[#This Row],[Reporting date]])*12+MONTH(Table1[[#This Row],[Reporting date]])-Earliest_Month)/4) -> 26 | Z1730: =Table1[[#This Row],[Reporting third]]-Table1[[#This Row],[Policy third]] -> 0 | AA1730: =IF(Table1[[#This Row],[Overall amount]]=0,"N/A",Table1[[#This Row],[Outstanding]]/Table1[[#This Row],[Overall amount]]) -> N/A | AB1730: =IF(MONTH(Table1[[#This Row],[Loss date]])<Pol_Inc_Month_Shifted,YEAR(Table1[[#This Row],[Loss date]])-1,YEAR(Table1[[#This Row],[Loss date]])) -> 2013 | AC1730: =IF(MONTH(Table1[[#This Row],[Reporting date]])<Pol_Inc_Month_Shifted,YEAR(Table1[[#This Row],[Reporting date]])-1,YEAR(Table1[[#This Row],[Reporting date]])) -> 2013 | AD1730: =Table1[[#This Row],[Reporting year (shifted)]]-Table1[[#This Row],[Policy Year (shifted)]] -> 0

Sheet 3. Projection - Methods 1 and 2
A1: 由于存在最后一年的数据不完整情况，这里展示了四种预测IBNR案件数的方法
A4: METHOD 2 - GROSS UP LAST DIAGONAL | N4: METHOD 1 - IGNORE LAST DIAGONAL
A7: 1 - Original table | N7: 1 - Original table
F9: Delay (years)
A10: Policy year | B10: 0 | C10: 1 | D10: 2 | E10: 3 | F10: 4 | G10: 5 | H10: 6 | I10: 7 | J10: 8 | K10: 9 | N10: See table on the left
A11: =Earliest_Year -> 2005 | B11: =IF($A11+B$10>Latest_Year,"",SUMIFS(Table1[Non-zero? (1=Yes)],Table1[Policy Year],"="&'3. Projection - Methods 1 and 2'!$A11,Table1[Delay (years)],"="&'3. Projection - Methods 1 and 2'!B$10)) -> 50 | C11: =IF($A11+C$10>Latest_Year,"",SUMIFS(Table1[Non-zero? (1=Yes)],Table1[Policy Year],"="&'3. Projection - Methods 1 and 2'!$A11,Table1[Delay (years)],"="&'3. Projection - Methods 1 and 2'!C$10)) -> 26 | D11: =IF($A11+D$10>Latest_Year,"",SUMIFS(Table1[Non-zero? (1=Yes)],Table1[Policy Year],"="&'3. Projection - Methods 1 and 2'!$A11,Table1[Delay (years)],"="&'3. Projection - Methods 1 and 2'!D$10)) -> 5 | E11: =IF($A11+E$10>Latest_Year,"",SUMIFS(Table1[Non-zero? (1=Yes)],Table1[Policy Year],"="&'3. Projection - Methods 1 and 2'!$A11,Table1[Delay (years)],"="&'3. Projection - Methods 1 and 2'!E$10)) -> 3 | F11: =IF($A11+F$10>Latest_Year,"",SUMIFS(Table1[Non-zero? (1=Yes)],Table1[Policy Year],"="&'3. Projection - Methods 1 and 2'!$A11,Table1[Delay (years)],"="&'3. Projection - Methods 1 and 2'!F$10)) -> 2 | G11: =IF($A11+G$10>Latest_Year,"",SUMIFS(Table1[Non-zero? (1=Yes)],Table1[Policy Year],"="&'3. Projection - Methods 1 and 2'!$A11,Table1[Delay (years)],"="&'3. Projection - Methods 1 and 2'!G$10)) -> 0 | H11: =IF($A11+H$10>Latest_Year,"",SUMIFS(Table1[Non-zero? (1=Yes)],Table1[Policy Year],"="&'3. Projection - Methods 1 and 2'!$A11,Table1[Delay (years)],"="&'3. Projection - Methods 1 and 2'!H$10)) -> 0 | I11: =IF($A11+I$10>Latest_Year,"",SUMIFS(Table1[Non-zero? (1=Yes)],Table1[Policy Year],"="&'3. Projection - Methods 1 and 2'!$A11,Table1[Delay (years)],"="&'3. Projection - Methods 1 and 2'!I$10)) -> 0 | ... K11: =IF($A11+K$10>Latest_Year,"",SUMIFS(Table1[Non-zero? (1=Yes)],Table1[Policy Year],"="&'3. Projection - Methods 1 and 2'!$A11,Table1[Delay (years)],"="&'3. Projection - Methods 1 and 2'!K$10)) -> 0
A12: =A11+1 -> 2006 | B12: =IF($A12+B$10>Latest_Year,"",SUMIFS(Table1[Non-zero? (1=Yes)],Table1[Policy Year],"="&'3. Projection - Methods 1 and 2'!$A12,Table1[Delay (years)],"="&'3. Projection - Methods 1 and 2'!B$10)) -> 41 | C12: =IF($A12+C$10>Latest_Year,"",SUMIFS(Table1[Non-zero? (1=Yes)],Table1[Policy Year],"="&'3. Projection - Methods 1 and 2'!$A12,Table1[Delay (years)],"="&'3. Projection - Methods 1 and 2'!C$10)) -> 28 | D12: =IF($A12+D$10>Latest_Year,"",SUMIFS(Table1[Non-zero? (1=Yes)],Table1[Policy Year],"="&'3. Projection - Methods 1 and 2'!$A12,Table1[Delay (years)],"="&'3. Projection - Methods 1 and 2'!D$10)) -> 13 | E12: =IF($A12+E$10>Latest_Year,"",SUMIFS(Table1[Non-zero? (1=Yes)],Table1[Policy Year],"="&'3. Projection - Methods 1 and 2'!$A12,Table1[Delay (years)],"="&'3. Projection - Methods 1 and 2'!E$10)) -> 6 | F12: =IF($A12+F$10>Latest_Year,"",SUMIFS(Table1[Non-zero? (1=Yes)],Table1[Policy Year],"="&'3. Projection - Methods 1 and 2'!$A12,Table1[Delay (years)],"="&'3. Projection - Methods 1 and 2'!F$10)) -> 4 | G12: =IF($A12+G$10>Latest_Year,"",SUMIFS(Table1[Non-zero? (1=Yes)],Table1[Policy Year],"="&'3. Projection - Methods 1 and 2'!$A12,Table1[Delay (years)],"="&'3. Projection - Methods 1 and 2'!G$10)) -> 0 | H12: =IF($A12+H$10>Latest_Year,"",SUMIFS(Table1[Non-zero? (1=Yes)],Table1[Policy Year],"="&'3. Projection - Methods 1 and 2'!$A12,Table1[Delay (years)],"="&'3. Projection - Methods 1 and 2'!H$10)) -> 0 | I12: =IF($A12+I$10>Latest_Year,"",SUMIFS(Table1[Non-zero? (1=Yes)],Table1[Policy Year],"="&'3. Projection - Methods 1 and 2'!$A12,Table1[Delay (years)],"="&'3. Projection - Methods 1 and 2'!I$10)) -> 0 | ... K12: =IF($A12+K$10>Latest_Year,"",SUMIFS(Table1[Non-zero? (1=Yes)],Table1[Policy Year],"="&'3. Projection - Methods 1 and 2'!$A12,Table1[Delay (years)],"="&'3. Projection - Methods 1 and 2'!K$10))
A13: =A12+1 -> 2007 | B13: =IF($A13+B$10>Latest_Year,"",SUMIFS(Table1[Non-zero? (1=Yes)],Table1[Policy Year],"="&'3. Projection - Methods 1 and 2'!$A13,Table1[Delay (years)],"="&'3. Projection - Methods 1 and 2'!B$10)) -> 65 | C13: =IF($A13+C$10>Latest_Year,"",SUMIFS(Table1[Non-zero? (1=Yes)],Table1[Policy Year],"="&'3. Projection - Methods 1 and 2'!$A13,Table1[Delay (years)],"="&'3. Projection - Methods 1 and 2'!C$10)) -> 33 | D13: =IF($A13+D$10>Latest_Year,"",SUMIFS(Table1[Non-zero? (1=Yes)],Table1[Policy Year],"="&'3. Projection - Methods 1 and 2'!$A13,Table1[Delay (years)],"="&'3. Projection - Methods 1 and 2'!D$10)) -> 10 | E13: =IF($A13+E$10>Latest_Year,"",SUMIFS(Table1[Non-zero? (1=Yes)],Table1[Policy Year],"="&'3. Projection - Methods 1 and 2'!$A13,Table1[Delay (years)],"="&'3. Projection - Methods 1 and 2'!E$10)) -> 2 | F13: =IF($A13+F$10>Latest_Year,"",SUMIFS(Table1[Non-zero? (1=Yes)],Table1[Policy Year],"="&'3. Projection - Methods 1 and 2'!$A13,Table1[Delay (years)],"="&'3. Projection - Methods 1 and 2'!F$10)) -> 0 | G13: =IF($A13+G$10>Latest_Year,"",SUMIFS(Table1[Non-zero? (1=Yes)],Table1[Policy Year],"="&'3. Projection - Methods 1 and 2'!$A13,Table1[Delay (years)],"="&'3. Projection - Methods 1 and 2'!G$10)) -> 0 | H13: =IF($A13+H$10>Latest_Year,"",SUMIFS(Table1[Non-zero? (1=Yes)],Table1[Policy Year],"="&'3. Projection - Methods 1 and 2'!$A13,Table1[Delay (years)],"="&'3. Projection - Methods 1 and 2'!H$10)) -> 0 | I13: =IF($A13+I$10>Latest_Year,"",SUMIFS(Table1[Non-zero? (1=Yes)],Table1[Policy Year],"="&'3. Projection - Methods 1 and 2'!$A13,Table1[Delay (years)],"="&'3. Projection - Methods 1 and 2'!I$10)) -> 0 | ... K13: =IF($A13+K$10>Latest_Year,"",SUMIFS(Table1[Non-zero? (1=Yes)],Table1[Policy Year],"="&'3. Projection - Methods 1 and 2'!$A13,Table1[Delay (years)],"="&'3. Projection - Methods 1 and 2'!K$10))
A14: =A13+1 -> 2008 | B14: =IF($A14+B$10>Latest_Year,"",SUMIFS(Table1[Non-zero? (1=Yes)],Table1[Policy Year],"="&'3. Projection - Methods 1 and 2'!$A14,Table1[Delay (years)],"="&'3. Projection - Methods 1 and 2'!B$10)) -> 83 | C14: =IF($A14+C$10>Latest_Year,"",SUMIFS(Table1[Non-zero? (1=Yes)],Table1[Policy Year],"="&'3. Projection - Methods 1 and 2'!$A14,Table1[Delay (years)],"="&'3. Projection - Methods 1 and 2'!C$10)) -> 47 | D14: =IF($A14+D$10>Latest_Year,"",SUMIFS(Table1[Non-zero? (1=Yes)],Table1[Policy Year],"="&'3. Projection - Methods 1 and 2'!$A14,Table1[Delay (years)],"="&'3. Projection - Methods 1 and 2'!D$10)) -> 8 | E14: =IF($A14+E$10>Latest_Year,"",SUMIFS(Table1[Non-zero? (1=Yes)],Table1[Policy Year],"="&'3. Projection - Methods 1 and 2'!$A14,Table1[Delay (years)],"="&'3. Projection - Methods 1 and 2'!E$10)) -> 6 | F14: =IF($A14+F$10>Latest_Year,"",SUMIFS(Table1[Non-zero? (1=Yes)],Table1[Policy Year],"="&'3. Projection - Methods 1 and 2'!$A14,Table1[Delay (years)],"="&'3. Projection - Methods 1 and 2'!F$10)) -> 1 | G14: =IF($A14+G$10>Latest_Year,"",SUMIFS(Table1[Non-zero? (1=Yes)],Table1[Policy Year],"="&'3. Projection - Methods 1 and 2'!$A14,Table1[Delay (years)],"="&'3. Projection - Methods 1 and 2'!G$10)) -> 0 | H14: =IF($A14+H$10>Latest_Year,"",SUMIFS(Table1[Non-zero? (1=Yes)],Table1[Policy Year],"="&'3. Projection - Methods 1 and 2'!$A14,Table1[Delay (years)],"="&'3. Projection - Methods 1 and 2'!H$10)) -> 1 | I14: =IF($A14+I$10>Latest_Year,"",SUMIFS(Table1[Non-zero? (1=Yes)],Table1[Policy Year],"="&'3. Projection - Methods 1 and 2'!$A14,Table1[Delay (years)],"="&'3. Projection - Methods 1 and 2'!I$10)) | ... K14: =IF($A14+K$10>Latest_Year,"",SUMIFS(Table1[Non-zero? (1=Yes)],Table1[Policy Year],"="&'3. Projection - Methods 1 and 2'!$A14,Table1[Delay (years)],"="&'3. Projection - Methods 1 and 2'!K$10))
A15: =A14+1 -> 2009 | B15: =IF($A15+B$10>Latest_Year,"",SUMIFS(Table1[Non-zero? (1=Yes)],Table1[Policy Year],"="&'3. Projection - Methods 1 and 2'!$A15,Table1[Delay (years)],"="&'3. Projection - Methods 1 and 2'!B$10)) -> 120 | C15: =IF($A15+C$10>Latest_Year,"",SUMIFS(Table1[Non-zero? (1=Yes)],Table1[Policy Year],"="&'3. Projection - Methods 1 and 2'!$A15,Table1[Delay (years)],"="&'3. Projection - Methods 1 and 2'!C$10)) -> 45 | D15: =IF($A15+D$10>Latest_Year,"",SUMIFS(Table1[Non-zero? (1=Yes)],Table1[Policy Year],"="&'3. Projection - Methods 1 and 2'!$A15,Table1[Delay (years)],"="&'3. Projection - Methods 1 and 2'!D$10)) -> 16 | E15: =IF($A15+E$10>Latest_Year,"",SUMIFS(Table1[Non-zero? (1=Yes)],Table1[Policy Year],"="&'3. Projection - Methods 1 and 2'!$A15,Table1[Delay (years)],"="&'3. Projection - Methods 1 and 2'!E$10)) -> 9 | F15: =IF($A15+F$10>Latest_Year,"",SUMIFS(Table1[Non-zero? (1=Yes)],Table1[Policy Year],"="&'3. Projection - Methods 1 and 2'!$A15,Table1[Delay (years)],"="&'3. Projection - Methods 1 and 2'!F$10)) -> 2 | G15: =IF($A15+G$10>Latest_Year,"",SUMIFS(Table1[Non-zero? (1=Yes)],Table1[Policy Year],"="&'3. Projection - Methods 1 and 2'!$A15,Table1[Delay (years)],"="&'3. Projection - Methods 1 and 2'!G$10)) -> 2 | H15: =IF($A15+H$10>Latest_Year,"",SUMIFS(Table1[Non-zero? (1=Yes)],Table1[Policy Year],"="&'3. Projection - Methods 1 and 2'!$A15,Table1[Delay (years)],"="&'3. Projection - Methods 1 and 2'!H$10)) | I15: =IF($A15+I$10>Latest_Year,"",SUMIFS(Table1[Non-zero? (1=Yes)],Table1[Policy Year],"="&'3. Projection - Methods 1 and 2'!$A15,Table1[Delay (years)],"="&'3. Projection - Methods 1 and 2'!I$10)) | ... K15: =IF($A15+K$10>Latest_Year,"",SUMIFS(Table1[Non-zero? (1=Yes)],Table1[Policy Year],"="&'3. Projection - Methods 1 and 2'!$A15,Table1[Delay (years)],"="&'3. Projection - Methods 1 and 2'!K$10))
A16: =A15+1 -> 2010 | B16: =IF($A16+B$10>Latest_Year,"",SUMIFS(Table1[Non-zero? (1=Yes)],Table1[Policy Year],"="&'3. Projection - Methods 1 and 2'!$A16,Table1[Delay (years)],"="&'3. Projection - Methods 1 and 2'!B$10)) -> 149 | C16: =IF($A16+C$10>Latest_Year,"",SUMIFS(Table1[Non-zero? (1=Yes)],Table1[Policy Year],"="&'3. Projection - Methods 1 and 2'!$A16,Table1[Delay (years)],"="&'3. Projection - Methods 1 and 2'!C$10)) -> 77 | D16: =IF($A16+D$10>Latest_Year,"",SUMIFS(Table1[Non-zero? (1=Yes)],Table1[Policy Year],"="&'3. Projection - Methods 1 and 2'!$A16,Table1[Delay (years)],"="&'3. Projection - Methods 1 and 2'!D$10)) -> 20 | E16: =IF($A16+E$10>Latest_Year,"",SUMIFS(Table1[Non-zero? (1=Yes)],Table1[Policy Year],"="&'3. Projection - Methods 1 and 2'!$A16,Table1[Delay (years)],"="&'3. Projection - Methods 1 and 2'!E$10)) -> 7 | F16: =IF($A16+F$10>Latest_Year,"",SUMIFS(Table1[Non-zero? (1=Yes)],Table1[Policy Year],"="&'3. Projection - Methods 1 and 2'!$A16,Table1[Delay (years)],"="&'3. Projection - Methods 1 and 2'!F$10)) -> 3 | G16: =IF($A16+G$10>Latest_Year,"",SUMIFS(Table1[Non-zero? (1=Yes)],Table1[Policy Year],"="&'3. Projection - Methods 1 and 2'!$A16,Table1[Delay (years)],"="&'3. Projection - Methods 1 and 2'!G$10)) | H16: =IF($A16+H$10>Latest_Year,"",SUMIFS(Table1[Non-zero? (1=Yes)],Table1[Policy Year],"="&'3. Projection - Methods 1 and 2'!$A16,Table1[Delay (years)],"="&'3. Projection - Methods 1 and 2'!H$10)) | I16: =IF($A16+I$10>Latest_Year,"",SUMIFS(Table1[Non-zero? (1=Yes)],Table1[Policy Year],"="&'3. Projection - Methods 1 and 2'!$A16,Table1[Delay (years)],"="&'3. Projection - Methods 1 and 2'!I$10)) | ... K16: =IF($A16+K$10>Latest_Year,"",SUMIFS(Table1[Non-zero? (1=Yes)],Table1[Policy Year],"="&'3. Projection - Methods 1 and 2'!$A16,Table1[Delay (years)],"="&'3. Projection - Methods 1 and 2'!K$10))
A17: =A16+1 -> 2011 | B17: =IF($A17+B$10>Latest_Year,"",SUMIFS(Table1[Non-zero? (1=Yes)],Table1[Policy Year],"="&'3. Projection - Methods 1 and 2'!$A17,Table1[Delay (years)],"="&'3. Projection - Methods 1 and 2'!B$10)) -> 158 | C17: =IF($A17+C$10>Latest_Year,"",SUMIFS(Table1[Non-zero? (1=Yes)],Table1[Policy Year],"="&'3. Projection - Methods 1 and 2'!$A17,Table1[Delay (years)],"="&'3. Projection - Methods 1 and 2'!C$10)) -> 64 | D17: =IF($A17+D$10>Latest_Year,"",SUMIFS(Table1[Non-zero? (1=Yes)],Table1[Policy Year],"="&'3. Projection - Methods 1 and 2'!$A17,Table1[Delay (years)],"="&'3. Projection - Methods 1 and 2'!D$10)) -> 19 | E17: =IF($A17+E$10>Latest_Year,"",SUMIFS(Table1[Non-zero? (1=Yes)],Table1[Policy Year],"="&'3. Projection - Methods 1 and 2'!$A17,Table1[Delay (years)],"="&'3. Projection - Methods 1 and 2'!E$10)) -> 9 | F17: =IF($A17+F$10>Latest_Year,"",SUMIFS(Table1[Non-zero? (1=Yes)],Table1[Policy Year],"="&'3. Projection - Methods 1 and 2'!$A17,Table1[Delay (years)],"="&'3. Projection - Methods 1 and 2'!F$10)) | G17: =IF($A17+G$10>Latest_Year,"",SUMIFS(Table1[Non-zero? (1=Yes)],Table1[Policy Year],"="&'3. Projection - Methods 1 and 2'!$A17,Table1[Delay (years)],"="&'3. Projection - Methods 1 and 2'!G$10)) | H17: =IF($A17+H$10>Latest_Year,"",SUMIFS(Table1[Non-zero? (1=Yes)],Table1[Policy Year],"="&'3. Projection - Methods 1 and 2'!$A17,Table1[Delay (years)],"="&'3. Projection - Methods 1 and 2'!H$10)) | I17: =IF($A17+I$10>Latest_Year,"",SUMIFS(Table1[Non-zero? (1=Yes)],Table1[Policy Year],"="&'3. Projection - Methods 1 and 2'!$A17,Table1[Delay (years)],"="&'3. Projection - Methods 1 and 2'!I$10)) | ... K17: =IF($A17+K$10>Latest_Year,"",SUMIFS(Table1[Non-zero? (1=Yes)],Table1[Policy Year],"="&'3. Projection - Methods 1 and 2'!$A17,Table1[Delay (years)],"="&'3. Projection - Methods 1 and 2'!K$10))
A18: =A17+1 -> 2012 | B18: =IF($A18+B$10>Latest_Year,"",SUMIFS(Table1[Non-zero? (1=Yes)],Table1[Policy Year],"="&'3. Projection - Methods 1 and 2'!$A18,Table1[Delay (years)],"="&'3. Projection - Methods 1 and 2'!B$10)) -> 96 | C18: =IF($A18+C$10>Latest_Year,"",SUMIFS(Table1[Non-zero? (1=Yes)],Table1[Policy Year],"="&'3. Projection - Methods 1 and 2'!$A18,Table1[Delay (years)],"="&'3. Projection - Methods 1 and 2'!C$10)) -> 81 | D18: =IF($A18+D$10>Latest_Year,"",SUMIFS(Table1[Non-zero? (1=Yes)],Table1[Policy Year],"="&'3. Projection - Methods 1 and 2'!$A18,Table1[Delay (years)],"="&'3. Projection - Methods 1 and 2'!D$10)) -> 22 | E18: =IF($A18+E$10>Latest_Year,"",SUMIFS(Table1[Non-zero? (1=Yes)],Table1[Policy Year],"="&'3. Projection - Methods 1 and 2'!$A18,Table1[Delay (years)],"="&'3. Projection - Methods 1 and 2'!E$10)) | F18: =IF($A18+F$10>Latest_Year,"",SUMIFS(Table1[Non-zero? (1=Yes)],Table1[Policy Year],"="&'3. Projection - Methods 1 and 2'!$A18,Table1[Delay (years)],"="&'3. Projection - Methods 1 and 2'!F$10)) | G18: =IF($A18+G$10>Latest_Year,"",SUMIFS(Table1[Non-zero? (1=Yes)],Table1[Policy Year],"="&'3. Projection - Methods 1 and 2'!$A18,Table1[Delay (years)],"="&'3. Projection - Methods 1 and 2'!G$10)) | H18: =IF($A18+H$10>Latest_Year,"",SUMIFS(Table1[Non-zero? (1=Yes)],Table1[Policy Year],"="&'3. Projection - Methods 1 and 2'!$A18,Table1[Delay (years)],"="&'3. Projection - Methods 1 and 2'!H$10)) | I18: =IF($A18+I$10>Latest_Year,"",SUMIFS(Table1[Non-zero? (1=Yes)],Table1[Policy Year],"="&'3. Projection - Methods 1 and 2'!$A18,Table1[Delay (years)],"="&'3. Projection - Methods 1 and 2'!I$10)) | ... K18: =IF($A18+K$10>Latest_Year,"",SUMIFS(Table1[Non-zero? (1=Yes)],Table1[Policy Year],"="&'3. Projection - Methods 1 and 2'!$A18,Table1[Delay (years)],"="&'3. Projection - Methods 1 and 2'!K$10))
A19: =A18+1 -> 2013 | B19: =IF($A19+B$10>Latest_Year,"",SUMIFS(Table1[Non-zero? (1=Yes)],Table1[Policy Year],"="&'3. Projection - Methods 1 and 2'!$A19,Table1[Delay (years)],"="&'3. Projection - Methods 1 and 2'!B$10)) -> 102 | C19: =IF($A19+C$10>Latest_Year,"",SUMIFS(Table1[Non-zero? (1=Yes)],Table1[Policy Year],"="&'3. Projection - Methods 1 and 2'!$A19,Table1[Delay (years)],"="&'3. Projection - Methods 1 and 2'!C$10)) -> 99 | D19: =IF($A19+D$10>Latest_Year,"",SUMIFS(Table1[Non-zero? (1=Yes)],Table1[Policy Year],"="&'3. Projection - Methods 1 and 2'!$A19,Table1[Delay (years)],"="&'3. Projection - Methods 1 and 2'!D$10)) | E19: =IF($A19+E$10>Latest_Year,"",SUMIFS(Table1[Non-zero? (1=Yes)],Table1[Policy Year],"="&'3. Projection - Methods 1 and 2'!$A19,Table1[Delay (years)],"="&'3. Projection - Methods 1 and 2'!E$10)) | F19: =IF($A19+F$10>Latest_Year,"",SUMIFS(Table1[Non-zero? (1=Yes)],Table1[Policy Year],"="&'3. Projection - Methods 1 and 2'!$A19,Table1[Delay (years)],"="&'3. Projection - Methods 1 and 2'!F$10)) | G19: =IF($A19+G$10>Latest_Year,"",SUMIFS(Table1[Non-zero? (1=Yes)],Table1[Policy Year],"="&'3. Projection - Methods 1 and 2'!$A19,Table1[Delay (years)],"="&'3. Projection - Methods 1 and 2'!G$10)) | H19: =IF($A19+H$10>Latest_Year,"",SUMIFS(Table1[Non-zero? (1=Yes)],Table1[Policy Year],"="&'3. Projection - Methods 1 and 2'!$A19,Table1[Delay (years)],"="&'3. Projection - Methods 1 and 2'!H$10)) | I19: =IF($A19+I$10>Latest_Year,"",SUMIFS(Table1[Non-zero? (1=Yes)],Table1[Policy Year],"="&'3. Projection - Methods 1 and 2'!$A19,Table1[Delay (years)],"="&'3. Projection - Methods 1 and 2'!I$10)) | ... K19: =IF($A19+K$10>Latest_Year,"",SUMIFS(Table1[Non-zero? (1=Yes)],Table1[Policy Year],"="&'3. Projection - Methods 1 and 2'!$A19,Table1[Delay (years)],"="&'3. Projection - Methods 1 and 2'!K$10))
A20: =A19+1 -> 2014 | B20: =IF($A20+B$10>Latest_Year,"",SUMIFS(Table1[Non-zero? (1=Yes)],Table1[Policy Year],"="&'3. Projection - Methods 1 and 2'!$A20,Table1[Delay (years)],"="&'3. Projection - Methods 1 and 2'!B$10)) -> 68 | C20: =IF($A20+C$10>Latest_Year,"",SUMIFS(Table1[Non-zero? (1=Yes)],Table1[Policy Year],"="&'3. Projection - Methods 1 and 2'!$A20,Table1[Delay (years)],"="&'3. Projection - Methods 1 and 2'!C$10)) | D20: =IF($A20+D$10>Latest_Year,"",SUMIFS(Table1[Non-zero? (1=Yes)],Table1[Policy Year],"="&'3. Projection - Methods 1 and 2'!$A20,Table1[Delay (years)],"="&'3. Projection - Methods 1 and 2'!D$10)) | E20: =IF($A20+E$10>Latest_Year,"",SUMIFS(Table1[Non-zero? (1=Yes)],Table1[Policy Year],"="&'3. Projection - Methods 1 and 2'!$A20,Table1[Delay (years)],"="&'3. Projection - Methods 1 and 2'!E$10)) | F20: =IF($A20+F$10>Latest_Year,"",SUMIFS(Table1[Non-zero? (1=Yes)],Table1[Policy Year],"="&'3. Projection - Methods 1 and 2'!$A20,Table1[Delay (years)],"="&'3. Projection - Methods 1 and 2'!F$10)) | G20: =IF($A20+G$10>Latest_Year,"",SUMIFS(Table1[Non-zero? (1=Yes)],Table1[Policy Year],"="&'3. Projection - Methods 1 and 2'!$A20,Table1[Delay (years)],"="&'3. Projection - Methods 1 and 2'!G$10)) | H20: =IF($A20+H$10>Latest_Year,"",SUMIFS(Table1[Non-zero? (1=Yes)],Table1[Policy Year],"="&'3. Projection - Methods 1 and 2'!$A20,Table1[Delay (years)],"="&'3. Projection - Methods 1 and 2'!H$10)) | I20: =IF($A20+I$10>Latest_Year,"",SUMIFS(Table1[Non-zero? (1=Yes)],Table1[Policy Year],"="&'3. Projection - Methods 1 and 2'!$A20,Table1[Delay (years)],"="&'3. Projection - Methods 1 and 2'!I$10)) | ... K20: =IF($A20+K$10>Latest_Year,"",SUMIFS(Table1[Non-zero? (1=Yes)],Table1[Policy Year],"="&'3. Projection - Methods 1 and 2'!$A20,Table1[Delay (years)],"="&'3. Projection - Methods 1 and 2'!K$10))
A23: 2 - Cumulative | N23: 2 - Cumulative
F25: Delay (years) | S25: Delay (years)
A26: Policy year | B26: 0 | C26: 1 | D26: 2 | E26: 3 | F26: 4 | G26: 5 | H26: 6 | I26: 7 | J26: 8 | K26: 9 | L26: Ultimate | N26: Policy year | O26: 0 | P26: 1 | Q26: 2 | R26: 3 | S26: 4 | T26: 5 | U26: 6 | V26: 7 | W26: 8 | X26: 9
A27: =A11 -> 2005 | B27: =B11 -> 50 | C27: =IF($A27+C$26>Latest_Year,"",C11+B27) -> 76 | D27: =IF($A27+D$26>Latest_Year,"",D11+C27) -> 81 | E27: =IF($A27+E$26>Latest_Year,"",E11+D27) -> 84 | F27: =IF($A27+F$26>Latest_Year,"",F11+E27) -> 86 | G27: =IF($A27+G$26>Latest_Year,"",G11+F27) -> 86 | H27: =IF($A27+H$26>Latest_Year,"",H11+G27) -> 86 | I27: =IF($A27+I$26>Latest_Year,"",I11+H27) -> 86 | J27: =IF($A27+J$26>Latest_Year,"",J11+I27) -> 86 | K27: =IF($A27+K$26>Latest_Year,"",K11+J27) -> 86 | N27: =A27 -> 2005 | O27: =B11 -> 50 | P27: =IF($A27+P$26>Latest_Year-1,"",C11+O27) -> 76 | Q27: =IF($A27+Q$26>Latest_Year-1,"",D11+P27) -> 81 | R27: =IF($A27+R$26>Latest_Year-1,"",E11+Q27) -> 84 | S27: =IF($A27+S$26>Latest_Year-1,"",F11+R27) -> 86 | T27: =IF($A27+T$26>Latest_Year-1,"",G11+S27) -> 86 | U27: =IF($A27+U$26>Latest_Year-1,"",H11+T27) -> 86 | V27: =IF($A27+V$26>Latest_Year-1,"",I11+U27) -> 86 | W27: =IF($A27+W$26>Latest_Year-1,"",J11+V27) -> 86
A28: =A12 -> 2006 | B28: =B12 -> 41 | C28: =IF($A28+C$26>Latest_Year,"",C12+B28) -> 69 | D28: =IF($A28+D$26>Latest_Year,"",D12+C28) -> 82 | E28: =IF($A28+E$26>Latest_Year,"",E12+D28) -> 88 | F28: =IF($A28+F$26>Latest_Year,"",F12+E28) -> 92 | G28: =IF($A28+G$26>Latest_Year,"",G12+F28) -> 92 | H28: =IF($A28+H$26>Latest_Year,"",H12+G28) -> 92 | I28: =IF($A28+I$26>Latest_Year,"",I12+H28) -> 92 | J28: =IF($A28+J$26>Latest_Year,"",J12+I28) -> 92 | K28: =IF($A28+K$26>Latest_Year,"",K12+J28) | N28: =A28 -> 2006 | O28: =B12 -> 41 | P28: =IF($A28+P$26>Latest_Year-1,"",C12+O28) -> 69 | Q28: =IF($A28+Q$26>Latest_Year-1,"",D12+P28) -> 82 | R28: =IF($A28+R$26>Latest_Year-1,"",E12+Q28) -> 88 | S28: =IF($A28+S$26>Latest_Year-1,"",F12+R28) -> 92 | T28: =IF($A28+T$26>Latest_Year-1,"",G12+S28) -> 92 | U28: =IF($A28+U$26>Latest_Year-1,"",H12+T28) -> 92 | V28: =IF($A28+V$26>Latest_Year-1,"",I12+U28) -> 92 | W28: =IF($A28+W$26>Latest_Year-1,"",J12+V28)
A29: =A13 -> 2007 | B29: =B13 -> 65 | C29: =IF($A29+C$26>Latest_Year,"",C13+B29) -> 98 | D29: =IF($A29+D$26>Latest_Year,"",D13+C29) -> 108 | E29: =IF($A29+E$26>Latest_Year,"",E13+D29) -> 110 | F29: =IF($A29+F$26>Latest_Year,"",F13+E29) -> 110 | G29: =IF($A29+G$26>Latest_Year,"",G13+F29) -> 110 | H29: =IF($A29+H$26>Latest_Year,"",H13+G29) -> 110 | I29: =IF($A29+I$26>Latest_Year,"",I13+H29) -> 110 | J29: =IF($A29+J$26>Latest_Year,"",J13+I29) | K29: =IF($A29+K$26>Latest_Year,"",K13+J29) | N29: =A29 -> 2007 | O29: =B13 -> 65 | P29: =IF($A29+P$26>Latest_Year-1,"",C13+O29) -> 98 | Q29: =IF($A29+Q$26>Latest_Year-1,"",D13+P29) -> 108 | R29: =IF($A29+R$26>Latest_Year-1,"",E13+Q29) -> 110 | S29: =IF($A29+S$26>Latest_Year-1,"",F13+R29) -> 110 | T29: =IF($A29+T$26>Latest_Year-1,"",G13+S29) -> 110 | U29: =IF($A29+U$26>Latest_Year-1,"",H13+T29) -> 110 | V29: =IF($A29+V$26>Latest_Year-1,"",I13+U29) | W29: =IF($A29+W$26>Latest_Year-1,"",J13+V29)
A30: =A14 -> 2008 | B30: =B14 -> 83 | C30: =IF($A30+C$26>Latest_Year,"",C14+B30) -> 130 | D30: =IF($A30+D$26>Latest_Year,"",D14+C30) -> 138 | E30: =IF($A30+E$26>Latest_Year,"",E14+D30) -> 144 | F30: =IF($A30+F$26>Latest_Year,"",F14+E30) -> 145 | G30: =IF($A30+G$26>Latest_Year,"",G14+F30) -> 145 | H30: =IF($A30+H$26>Latest_Year,"",H14+G30) -> 146 | I30: =IF($A30+I$26>Latest_Year,"",I14+H30) | J30: =IF($A30+J$26>Latest_Year,"",J14+I30) | K30: =IF($A30+K$26>Latest_Year,"",K14+J30) | N30: =A30 -> 2008 | O30: =B14 -> 83 | P30: =IF($A30+P$26>Latest_Year-1,"",C14+O30) -> 130 | Q30: =IF($A30+Q$26>Latest_Year-1,"",D14+P30) -> 138 | R30: =IF($A30+R$26>Latest_Year-1,"",E14+Q30) -> 144 | S30: =IF($A30+S$26>Latest_Year-1,"",F14+R30) -> 145 | T30: =IF($A30+T$26>Latest_Year-1,"",G14+S30) -> 145 | U30: =IF($A30+U$26>Latest_Year-1,"",H14+T30) | V30: =IF($A30+V$26>Latest_Year-1,"",I14+U30) | W30: =IF($A30+W$26>Latest_Year-1,"",J14+V30)
A31: =A15 -> 2009 | B31: =B15 -> 120 | C31: =IF($A31+C$26>Latest_Year,"",C15+B31) -> 165 | D31: =IF($A31+D$26>Latest_Year,"",D15+C31) -> 181 | E31: =IF($A31+E$26>Latest_Year,"",E15+D31) -> 190 | F31: =IF($A31+F$26>Latest_Year,"",F15+E31) -> 192 | G31: =IF($A31+G$26>Latest_Year,"",G15+F31) -> 194 | H31: =IF($A31+H$26>Latest_Year,"",H15+G31) | I31: =IF($A31+I$26>Latest_Year,"",I15+H31) | J31: =IF($A31+J$26>Latest_Year,"",J15+I31) | K31: =IF($A31+K$26>Latest_Year,"",K15+J31) | N31: =A31 -> 2009 | O31: =B15 -> 120 | P31: =IF($A31+P$26>Latest_Year-1,"",C15+O31) -> 165 | Q31: =IF($A31+Q$26>Latest_Year-1,"",D15+P31) -> 181 | R31: =IF($A31+R$26>Latest_Year-1,"",E15+Q31) -> 190 | S31: =IF($A31+S$26>Latest_Year-1,"",F15+R31) -> 192 | T31: =IF($A31+T$26>Latest_Year-1,"",G15+S31) | U31: =IF($A31+U$26>Latest_Year-1,"",H15+T31) | V31: =IF($A31+V$26>Latest_Year-1,"",I15+U31) | W31: =IF($A31+W$26>Latest_Year-1,"",J15+V31)
A32: =A16 -> 2010 | B32: =B16 -> 149 | C32: =IF($A32+C$26>Latest_Year,"",C16+B32) -> 226 | D32: =IF($A32+D$26>Latest_Year,"",D16+C32) -> 246 | E32: =IF($A32+E$26>Latest_Year,"",E16+D32) -> 253 | F32: =IF($A32+F$26>Latest_Year,"",F16+E32) -> 256 | G32: =IF($A32+G$26>Latest_Year,"",G16+F32) | H32: =IF($A32+H$26>Latest_Year,"",H16+G32) | I32: =IF($A32+I$26>Latest_Year,"",I16+H32) | J32: =IF($A32+J$26>Latest_Year,"",J16+I32) | K32: =IF($A32+K$26>Latest_Year,"",K16+J32) | N32: =A32 -> 2010 | O32: =B16 -> 149 | P32: =IF($A32+P$26>Latest_Year-1,"",C16+O32) -> 226 | Q32: =IF($A32+Q$26>Latest_Year-1,"",D16+P32) -> 246 | R32: =IF($A32+R$26>Latest_Year-1,"",E16+Q32) -> 253 | S32: =IF($A32+S$26>Latest_Year-1,"",F16+R32) | T32: =IF($A32+T$26>Latest_Year-1,"",G16+S32) | U32: =IF($A32+U$26>Latest_Year-1,"",H16+T32) | V32: =IF($A32+V$26>Latest_Year-1,"",I16+U32) | W32: =IF($A32+W$26>Latest_Year-1,"",J16+V32)
A33: =A17 -> 2011 | B33: =B17 -> 158 | C33: =IF($A33+C$26>Latest_Year,"",C17+B33) -> 222 | D33: =IF($A33+D$26>Latest_Year,"",D17+C33) -> 241 | E33: =IF($A33+E$26>Latest_Year,"",E17+D33) -> 250 | F33: =IF($A33+F$26>Latest_Year,"",F17+E33) | G33: =IF($A33+G$26>Latest_Year,"",G17+F33) | H33: =IF($A33+H$26>Latest_Year,"",H17+G33) | I33: =IF($A33+I$26>Latest_Year,"",I17+H33) | J33: =IF($A33+J$26>Latest_Year,"",J17+I33) | K33: =IF($A33+K$26>Latest_Year,"",K17+J33) | N33: =A33 -> 2011 | O33: =B17 -> 158 | P33: =IF($A33+P$26>Latest_Year-1,"",C17+O33) -> 222 | Q33: =IF($A33+Q$26>Latest_Year-1,"",D17+P33) -> 241 | R33: =IF($A33+R$26>Latest_Year-1,"",E17+Q33) | S33: =IF($A33+S$26>Latest_Year-1,"",F17+R33) | T33: =IF($A33+T$26>Latest_Year-1,"",G17+S33) | U33: =IF($A33+U$26>Latest_Year-1,"",H17+T33) | V33: =IF($A33+V$26>Latest_Year-1,"",I17+U33) | W33: =IF($A33+W$26>Latest_Year-1,"",J17+V33)
A34: =A18 -> 2012 | B34: =B18 -> 96 | C34: =IF($A34+C$26>Latest_Year,"",C18+B34) -> 177 | D34: =IF($A34+D$26>Latest_Year,"",D18+C34) -> 199 | E34: =IF($A34+E$26>Latest_Year,"",E18+D34) | F34: =IF($A34+F$26>Latest_Year,"",F18+E34) | G34: =IF($A34+G$26>Latest_Year,"",G18+F34) | H34: =IF($A34+H$26>Latest_Year,"",H18+G34) | I34: =IF($A34+I$26>Latest_Year,"",I18+H34) | J34: =IF($A34+J$26>Latest_Year,"",J18+I34) | K34: =IF($A34+K$26>Latest_Year,"",K18+J34) | N34: =A34 -> 2012 | O34: =B18 -> 96 | P34: =IF($A34+P$26>Latest_Year-1,"",C18+O34) -> 177 | Q34: =IF($A34+Q$26>Latest_Year-1,"",D18+P34) | R34: =IF($A34+R$26>Latest_Year-1,"",E18+Q34) | S34: =IF($A34+S$26>Latest_Year-1,"",F18+R34) | T34: =IF($A34+T$26>Latest_Year-1,"",G18+S34) | U34: =IF($A34+U$26>Latest_Year-1,"",H18+T34) | V34: =IF($A34+V$26>Latest_Year-1,"",I18+U34) | W34: =IF($A34+W$26>Latest_Year-1,"",J18+V34)
A35: =A19 -> 2013 | B35: =B19 -> 102 | C35: =IF($A35+C$26>Latest_Year,"",C19+B35) -> 201 | D35: =IF($A35+D$26>Latest_Year,"",D19+C35) | E35: =IF($A35+E$26>Latest_Year,"",E19+D35) | F35: =IF($A35+F$26>Latest_Year,"",F19+E35) | G35: =IF($A35+G$26>Latest_Year,"",G19+F35) | H35: =IF($A35+H$26>Latest_Year,"",H19+G35) | I35: =IF($A35+I$26>Latest_Year,"",I19+H35) | J35: =IF($A35+J$26>Latest_Year,"",J19+I35) | K35: =IF($A35+K$26>Latest_Year,"",K19+J35) | N35: =A35 -> 2013 | O35: =B19 -> 102 | P35: =IF($A35+P$26>Latest_Year-1,"",C19+O35) | Q35: =IF($A35+Q$26>Latest_Year-1,"",D19+P35) | R35: =IF($A35+R$26>Latest_Year-1,"",E19+Q35) | S35: =IF($A35+S$26>Latest_Year-1,"",F19+R35) | T35: =IF($A35+T$26>Latest_Year-1,"",G19+S35) | U35: =IF($A35+U$26>Latest_Year-1,"",H19+T35) | V35: =IF($A35+V$26>Latest_Year-1,"",I19+U35) | W35: =IF($A35+W$26>Latest_Year-1,"",J19+V35)
A36: =A20 -> 2014 | B36: =B20 -> 68 | C36: =IF($A36+C$26>Latest_Year,"",C20+B36) | D36: =IF($A36+D$26>Latest_Year,"",D20+C36) | E36: =IF($A36+E$26>Latest_Year,"",E20+D36) | F36: =IF($A36+F$26>Latest_Year,"",F20+E36) | G36: =IF($A36+G$26>Latest_Year,"",G20+F36) | H36: =IF($A36+H$26>Latest_Year,"",H20+G36) | I36: =IF($A36+I$26>Latest_Year,"",I20+H36) | J36: =IF($A36+J$26>Latest_Year,"",J20+I36) | K36: =IF($A36+K$26>Latest_Year,"",K20+J36)
P37: =IF($A36+P$26>2011,"",C20+O37) | Q37: =IF($A36+Q$26>2011,"",D20+P37) | R37: =IF($A36+R$26>2011,"",E20+Q37) | S37: =IF($A36+S$26>2011,"",F20+R37) | T37: =IF($A36+T$26>2011,"",G20+S37) | U37: =IF($A36+U$26>2011,"",H20+T37) | V37: =IF($A36+V$26>2011,"",I20+U37) | W37: Tail
B38: Link ratios | C38: =SUM(C27:C36)/SUMIF(C27:C36,">0",B27:B36) -> 1.5787037 | D38: =SUM(D27:D36)/SUMIF(D27:D36,">0",C27:C36) -> 1.0971625 | E38: =SUM(E27:E36)/SUMIF(E27:E36,">0",D27:D36) -> 1.0389972 | F38: =SUM(F27:F36)/SUMIF(F27:F36,">0",E27:E36) -> 1.013809 | G38: =SUM(G27:G36)/SUMIF(G27:G36,">0",F27:F36) -> 1.0032 | H38: =SUM(H27:H36)/SUMIF(H27:H36,">0",G27:G36) -> 1.0023095 | I38: =SUM(I27:I36)/SUMIF(I27:I36,">0",H27:H36) -> 1 | J38: =SUM(J27:J36)/SUMIF(J27:J36,">0",I27:I36) -> 1 | K38: =SUM(K27:K36)/SUMIF(K27:K36,">0",J27:J36) -> 1 | N38: Link ratios | O38: =SUM(P27:P37)/SUMIF(P27:P37,">0",O27:O37) -> 1.5262467 | P38: =SUM(Q27:Q37)/SUMIF(Q27:Q37,">0",P27:P37) -> 1.0922921 | Q38: =SUM(R27:R37)/SUMIF(R27:R37,">0",Q27:Q37) -> 1.0394737 | R38: =SUM(S27:S37)/SUMIF(S27:S37,">0",R27:R37) -> 1.0146104 | S38: =SUM(T27:T37)/SUMIF(T27:T37,">0",S27:S37) -> 1 | T38: =SUM(U27:U37)/SUMIF(U27:U37,">0",T27:T37) -> 1 | U38: =SUM(V27:V37)/SUMIF(V27:V37,">0",U27:U37) -> 1 | V38: =SUM(W27:W37)/SUMIF(W27:W37,">0",V27:V37) -> 1 | W38: 1
N39: Cumulative | O39: =O38*P39 -> 1.7582326 | P39: =P38*Q39 -> 1.1519976 | Q39: =Q38*R39 -> 1.0546608 | R39: =R38*S39 -> 1.0146104 | S39: =S38*T39 -> 1 | T39: =T38*U39 -> 1 | U39: =U38*V39 -> 1 | V39: =V38 -> 1 | W39: 1
A41: 3 - Grossed-up table | N41: 3 - Projected claims
F42: Delay (years) | S42: Delay (years)
B43: 0 | C43: 1 | D43: 2 | E43: 3 | F43: 4 | G43: 5 | H43: 6 | I43: 7 | J43: 8 | K43: 9 | N43: Policy year | O43: 0 | P43: 1 | Q43: 2 | R43: 3 | S43: 4 | T43: 5 | U43: 6 | V43: 7 | W43: 8 | X43: 9
A44: =A27 -> 2005 | B44: =B11 -> 50 | C44: =C11 -> 26 | D44: =D11 -> 5 | E44: =E11 -> 3 | F44: =F11 -> 2 | G44: =G11 -> 0 | H44: =H11 -> 0 | I44: =I11 -> 0 | J44: =J11 -> 0 | K44: =K11*1.5 -> 0 | N44: =N27 -> 2005 | O44: =IF(ISNUMBER(O27),O27,"") -> 50 | P44: =IF(ISNUMBER(P27),P27,"") -> 76 | Q44: =IF(ISNUMBER(Q27),Q27,"") -> 81 | R44: =IF(ISNUMBER(R27),R27,"") -> 84 | S44: =IF(ISNUMBER(S27),S27,"") -> 86 | T44: =IF(ISNUMBER(T27),T27,"") -> 86 | U44: =IF(ISNUMBER(U27),U27,"") -> 86 | V44: =IF(ISNUMBER(V27),V27,"") -> 86 | W44: =IF(ISNUMBER(W27),W27,"") -> 86 | X44: =W44*W$39 -> 86
A45: =A28 -> 2006 | B45: =B12 -> 41 | C45: =C12 -> 28 | D45: =D12 -> 13 | E45: =E12 -> 6 | F45: =F12 -> 4 | G45: =G12 -> 0 | H45: =H12 -> 0 | I45: =I12 -> 0 | J45: =J12*1.5 -> 0 | K45: =K12 | N45: =N28 -> 2006 | O45: =IF(ISNUMBER(O28),O28,"") -> 41 | P45: =IF(ISNUMBER(P28),P28,"") -> 69 | Q45: =IF(ISNUMBER(Q28),Q28,"") -> 82 | R45: =IF(ISNUMBER(R28),R28,"") -> 88 | S45: =IF(ISNUMBER(S28),S28,"") -> 92 | T45: =IF(ISNUMBER(T28),T28,"") -> 92 | U45: =IF(ISNUMBER(U28),U28,"") -> 92 | V45: =IF(ISNUMBER(V28),V28,"") -> 92 | X45: =V45*V$39 -> 92
A46: =A29 -> 2007 | B46: =B13 -> 65 | C46: =C13 -> 33 | D46: =D13 -> 10 | E46: =E13 -> 2 | F46: =F13 -> 0 | G46: =G13 -> 0 | H46: =H13 -> 0 | I46: =I13*1.5 -> 0 | J46: =J13 | K46: =K13 | N46: =N29 -> 2007 | O46: =IF(ISNUMBER(O29),O29,"") -> 65 | P46: =IF(ISNUMBER(P29),P29,"") -> 98 | Q46: =IF(ISNUMBER(Q29),Q29,"") -> 108 | R46: =IF(ISNUMBER(R29),R29,"") -> 110 | S46: =IF(ISNUMBER(S29),S29,"") -> 110 | T46: =IF(ISNUMBER(T29),T29,"") -> 110 | U46: =IF(ISNUMBER(U29),U29,"") -> 110 | X46: =U46*U$39 -> 110
A47: =A30 -> 2008 | B47: =B14 -> 83 | C47: =C14 -> 47 | D47: =D14 -> 8 | E47: =E14 -> 6 | F47: =F14 -> 1 | G47: =G14 -> 0 | H47: =H14*1.5 -> 1.5 | I47: =I14 | J47: =J14 | K47: =K14 | N47: =N30 -> 2008 | O47: =IF(ISNUMBER(O30),O30,"") -> 83 | P47: =IF(ISNUMBER(P30),P30,"") -> 130 | Q47: =IF(ISNUMBER(Q30),Q30,"") -> 138 | R47: =IF(ISNUMBER(R30),R30,"") -> 144 | S47: =IF(ISNUMBER(S30),S30,"") -> 145 | T47: =IF(ISNUMBER(T30),T30,"") -> 145 | X47: =T47*T$39 -> 145
A48: =A31 -> 2009 | B48: =B15 -> 120 | C48: =C15 -> 45 | D48: =D15 -> 16 | E48: =E15 -> 9 | F48: =F15 -> 2 | G48: =G15*1.5 -> 3 | H48: =H15 | I48: =I15 | J48: =J15 | K48: =K15 | N48: =N31 -> 2009 | O48: =IF(ISNUMBER(O31),O31,"") -> 120 | P48: =IF(ISNUMBER(P31),P31,"") -> 165 | Q48: =IF(ISNUMBER(Q31),Q31,"") -> 181 | R48: =IF(ISNUMBER(R31),R31,"") -> 190 | S48: =IF(ISNUMBER(S31),S31,"") -> 192 | X48: =S48*S$39 -> 192
A49: =A32 -> 2010 | B49: =B16 -> 149 | C49: =C16 -> 77 | D49: =D16 -> 20 | E49: =E16 -> 7 | F49: =F16*1.5 -> 4.5 | G49: =G16 | H49: =H16 | I49: =I16 | J49: =J16 | K49: =K16 | N49: =N32 -> 2010 | O49: =IF(ISNUMBER(O32),O32,"") -> 149 | P49: =IF(ISNUMBER(P32),P32,"") -> 226 | Q49: =IF(ISNUMBER(Q32),Q32,"") -> 246 | R49: =IF(ISNUMBER(R32),R32,"") -> 253 | X49: =R49*R$39 -> 256.69643
A50: =A33 -> 2011 | B50: =B17 -> 158 | C50: =C17 -> 64 | D50: =D17 -> 19 | E50: =E17*1.5 -> 13.5 | F50: =F17 | G50: =G17 | H50: =H17 | I50: =I17 | J50: =J17 | K50: =K17 | N50: =N33 -> 2011 | O50: =IF(ISNUMBER(O33),O33,"") -> 158 | P50: =IF(ISNUMBER(P33),P33,"") -> 222 | Q50: =IF(ISNUMBER(Q33),Q33,"") -> 241 | X50: =Q50*Q$39 -> 254.17325
A51: =A34 -> 2012 | B51: =B18 -> 96 | C51: =C18 -> 81 | D51: =D18*1.5 -> 33 | E51: =E18 | F51: =F18 | G51: 最后一列对角线元素都乘以1.5 | H51: =H18 | I51: =I18 | J51: =J18 | K51: =K18 | N51: =N34 -> 2012 | O51: =IF(ISNUMBER(O34),O34,"") -> 96 | P51: =IF(ISNUMBER(P34),P34,"") -> 177 | X51: =P51*P$39 -> 203.90358
A52: =A35 -> 2013 | B52: =B19 -> 102 | C52: =C19*1.5 -> 148.5 | D52: =D19 | E52: =E19 | F52: =F19 | G52: =G19 | H52: =H19 | I52: =I19 | J52: =J19 | K52: =K19 | N52: =N35 -> 2013 | O52: =IF(ISNUMBER(O35),O35,"") -> 102 | X52: =O52*O$39 -> 179.33973
A53: =A36 -> 2014 | B53: =B20*1.5 -> 102 | C53: =C20 | D53: =D20 | E53: =E20 | F53: =F20 | G53: =G20 | H53: =H20 | I53: =I20 | J53: =J20 | K53: =K20 | O53: =IF(ISNUMBER(O37),O37,"")
A57: 4 - Cumulative grossed-up table
F58: Delay (years)
B59: 0 | C59: 1 | D59: 2 | E59: 3 | F59: 4 | G59: 5 | H59: 6 | I59: 7 | J59: 8 | K59: 9
A60: =A44 -> 2005 | B60: =B44 -> 50 | C60: =IF($A60+C$26>Latest_Year,"",C44+B60) -> 76 | D60: =IF($A60+D$26>Latest_Year,"",D44+C60) -> 81 | E60: =IF($A60+E$26>Latest_Year,"",E44+D60) -> 84 | F60: =IF($A60+F$26>Latest_Year,"",F44+E60) -> 86 | G60: =IF($A60+G$26>Latest_Year,"",G44+F60) -> 86 | H60: =IF($A60+H$26>Latest_Year,"",H44+G60) -> 86 | I60: =IF($A60+I$26>Latest_Year,"",I44+H60) -> 86 | J60: =IF($A60+J$26>Latest_Year,"",J44+I60) -> 86 | K60: =IF($A60+K$26>Latest_Year,"",K44+J60) -> 86
A61: =A45 -> 2006 | B61: =B45 -> 41 | C61: =IF($A61+C$26>Latest_Year,"",C45+B61) -> 69 | D61: =IF($A61+D$26>Latest_Year,"",D45+C61) -> 82 | E61: =IF($A61+E$26>Latest_Year,"",E45+D61) -> 88 | F61: =IF($A61+F$26>Latest_Year,"",F45+E61) -> 92 | G61: =IF($A61+G$26>Latest_Year,"",G45+F61) -> 92 | H61: =IF($A61+H$26>Latest_Year,"",H45+G61) -> 92 | I61: =IF($A61+I$26>Latest_Year,"",I45+H61) -> 92 | J61: =IF($A61+J$26>Latest_Year,"",J45+I61) -> 92 | K61: =IF($A61+K$26>Latest_Year,"",K45+J61)
A62: =A46 -> 2007 | B62: =B46 -> 65 | C62: =IF($A62+C$26>Latest_Year,"",C46+B62) -> 98 | D62: =IF($A62+D$26>Latest_Year,"",D46+C62) -> 108 | E62: =IF($A62+E$26>Latest_Year,"",E46+D62) -> 110 | F62: =IF($A62+F$26>Latest_Year,"",F46+E62) -> 110 | G62: =IF($A62+G$26>Latest_Year,"",G46+F62) -> 110 | H62: =IF($A62+H$26>Latest_Year,"",H46+G62) -> 110 | I62: =IF($A62+I$26>Latest_Year,"",I46+H62) -> 110 | J62: =IF($A62+J$26>Latest_Year,"",J46+I62) | K62: =IF($A62+K$26>Latest_Year,"",K46+J62)
A63: =A47 -> 2008 | B63: =B47 -> 83 | C63: =IF($A63+C$26>Latest_Year,"",C47+B63) -> 130 | D63: =IF($A63+D$26>Latest_Year,"",D47+C63) -> 138 | E63: =IF($A63+E$26>Latest_Year,"",E47+D63) -> 144 | F63: =IF($A63+F$26>Latest_Year,"",F47+E63) -> 145 | G63: =IF($A63+G$26>Latest_Year,"",G47+F63) -> 145 | H63: =IF($A63+H$26>Latest_Year,"",H47+G63) -> 146.5 | I63: =IF($A63+I$26>Latest_Year,"",I47+H63) | J63: =IF($A63+J$26>Latest_Year,"",J47+I63) | K63: =IF($A63+K$26>Latest_Year,"",K47+J63)
A64: =A48 -> 2009 | B64: =B48 -> 120 | C64: =IF($A64+C$26>Latest_Year,"",C48+B64) -> 165 | D64: =IF($A64+D$26>Latest_Year,"",D48+C64) -> 181 | E64: =IF($A64+E$26>Latest_Year,"",E48+D64) -> 190 | F64: =IF($A64+F$26>Latest_Year,"",F48+E64) -> 192 | G64: =IF($A64+G$26>Latest_Year,"",G48+F64) -> 195 | H64: =IF($A64+H$26>Latest_Year,"",H48+G64) | I64: =IF($A64+I$26>Latest_Year,"",I48+H64) | J64: =IF($A64+J$26>Latest_Year,"",J48+I64) | K64: =IF($A64+K$26>Latest_Year,"",K48+J64)
A65: =A49 -> 2010 | B65: =B49 -> 149 | C65: =IF($A65+C$26>Latest_Year,"",C49+B65) -> 226 | D65: =IF($A65+D$26>Latest_Year,"",D49+C65) -> 246 | E65: =IF($A65+E$26>Latest_Year,"",E49+D65) -> 253 | F65: =IF($A65+F$26>Latest_Year,"",F49+E65) -> 257.5 | G65: =IF($A65+G$26>Latest_Year,"",G49+F65) | H65: =IF($A65+H$26>Latest_Year,"",H49+G65) | I65: =IF($A65+I$26>Latest_Year,"",I49+H65) | J65: =IF($A65+J$26>Latest_Year,"",J49+I65) | K65: =IF($A65+K$26>Latest_Year,"",K49+J65)
A66: =A50 -> 2011 | B66: =B50 -> 158 | C66: =IF($A66+C$26>Latest_Year,"",C50+B66) -> 222 | D66: =IF($A66+D$26>Latest_Year,"",D50+C66) -> 241 | E66: =IF($A66+E$26>Latest_Year,"",E50+D66) -> 254.5 | F66: =IF($A66+F$26>Latest_Year,"",F50+E66) | G66: =IF($A66+G$26>Latest_Year,"",G50+F66) | H66: =IF($A66+H$26>Latest_Year,"",H50+G66) | I66: =IF($A66+I$26>Latest_Year,"",I50+H66) | J66: =IF($A66+J$26>Latest_Year,"",J50+I66) | K66: =IF($A66+K$26>Latest_Year,"",K50+J66)
A67: =A51 -> 2012 | B67: =B51 -> 96 | C67: =IF($A67+C$26>Latest_Year,"",C51+B67) -> 177 | D67: =IF($A67+D$26>Latest_Year,"",D51+C67) -> 210 | E67: =IF($A67+E$26>Latest_Year,"",E51+D67) | F67: =IF($A67+F$26>Latest_Year,"",F51+E67) | G67: =IF($A67+G$26>Latest_Year,"",G51+F67) | H67: =IF($A67+H$26>Latest_Year,"",H51+G67) | I67: =IF($A67+I$26>Latest_Year,"",I51+H67) | J67: =IF($A67+J$26>Latest_Year,"",J51+I67) | K67: =IF($A67+K$26>Latest_Year,"",K51+J67)
A68: =A52 -> 2013 | B68: =B52 -> 102 | C68: =IF($A68+C$26>Latest_Year,"",C52+B68) -> 250.5 | D68: =IF($A68+D$26>Latest_Year,"",D52+C68) | E68: =IF($A68+E$26>Latest_Year,"",E52+D68) | F68: =IF($A68+F$26>Latest_Year,"",F52+E68) | G68: =IF($A68+G$26>Latest_Year,"",G52+F68) | H68: =IF($A68+H$26>Latest_Year,"",H52+G68) | I68: =IF($A68+I$26>Latest_Year,"",I52+H68) | J68: =IF($A68+J$26>Latest_Year,"",J52+I68) | K68: =IF($A68+K$26>Latest_Year,"",K52+J68)
A69: =A53 -> 2014 | B69: =B53 -> 102 | C69: =IF($A69+C$26>Latest_Year,"",C53+B69) | D69: =IF($A69+D$26>Latest_Year,"",D53+C69) | E69: =IF($A69+E$26>Latest_Year,"",E53+D69) | F69: =IF($A69+F$26>Latest_Year,"",F53+E69) | G69: =IF($A69+G$26>Latest_Year,"",G53+F69) | H69: =IF($A69+H$26>Latest_Year,"",H53+G69) | I69: =IF($A69+I$26>Latest_Year,"",I53+H69) | J69: =IF($A69+J$26>Latest_Year,"",J53+I69) | K69: =IF($A69+K$26>Latest_Year,"",K53+J69)
K70: Tail factor
A71: Link ratios | B71: =SUM(C60:C69)/SUMIF(C60:C69,">0",B60:B69) -> 1.6359954 | C71: =SUM(D60:D69)/SUMIF(D60:D69,">0",C60:C69) -> 1.1066208 | D71: =SUM(E60:E69)/SUMIF(E60:E69,">0",D60:D69) -> 1.0431755 | E71: =SUM(F60:F69)/SUMIF(F60:F69,">0",E60:E69) -> 1.0155351 | F71: =SUM(G60:G69)/SUMIF(G60:G69,">0",F60:F69) -> 1.0048 | G71: =SUM(H60:H69)/SUMIF(H60:H69,">0",G60:G69) -> 1.0034642 | H71: =SUM(I60:I69)/SUMIF(I60:I69,">0",H60:H69) -> 1 | I71: =SUM(J60:J69)/SUMIF(J60:J69,">0",I60:I69) -> 1 | J71: =SUM(K60:K69)/SUMIF(K60:K69,">0",J60:J69) -> 1 | K71: 1
A72: Cumulative | B72: =B71*C72 -> 1.9338141 | C72: =C71*D72 -> 1.1820413 | D72: =D71*E72 -> 1.0681539 | E72: =E71*F72 -> 1.0239446 | F72: =F71*G72 -> 1.0082808 | G72: =G71*H72 -> 1.0034642 | H72: =H71*I72 -> 1 | I72: =I71*J72 -> 1 | J72: =J71 -> 1 | K72: 1
A74: 5 - Projected claims
F75: Delay (years)
A76: Policy year | B76: 0 | C76: 1 | D76: 2 | E76: 3 | F76: 4 | G76: 5 | H76: 6 | I76: 7 | J76: 8 | K76: 9 | L76: Ultimate
A77: =A60 -> 2005 | B77: =IF(ISNUMBER(B60),B60,"") -> 50 | C77: =IF(ISNUMBER(C60),C60,"") -> 76 | D77: =IF(ISNUMBER(D60),D60,"") -> 81 | E77: =IF(ISNUMBER(E60),E60,"") -> 84 | F77: =IF(ISNUMBER(F60),F60,"") -> 86 | G77: =IF(ISNUMBER(G60),G60,"") -> 86 | H77: =IF(ISNUMBER(H60),H60,"") -> 86 | I77: =IF(ISNUMBER(I60),I60,"") -> 86 | ... K77: =IF(ISNUMBER(K60),K60,"") -> 86 | L77: =K77*K$72 -> 86
A78: =A61 -> 2006 | B78: =IF(ISNUMBER(B61),B61,"") -> 41 | C78: =IF(ISNUMBER(C61),C61,"") -> 69 | D78: =IF(ISNUMBER(D61),D61,"") -> 82 | E78: =IF(ISNUMBER(E61),E61,"") -> 88 | F78: =IF(ISNUMBER(F61),F61,"") -> 92 | G78: =IF(ISNUMBER(G61),G61,"") -> 92 | H78: =IF(ISNUMBER(H61),H61,"") -> 92 | I78: =IF(ISNUMBER(I61),I61,"") -> 92 | J78: =IF(ISNUMBER(J61),J61,"") -> 92 | L78: =J78*J$72 -> 92
A79: =A62 -> 2007 | B79: =IF(ISNUMBER(B62),B62,"") -> 65 | C79: =IF(ISNUMBER(C62),C62,"") -> 98 | D79: =IF(ISNUMBER(D62),D62,"") -> 108 | E79: =IF(ISNUMBER(E62),E62,"") -> 110 | F79: =IF(ISNUMBER(F62),F62,"") -> 110 | G79: =IF(ISNUMBER(G62),G62,"") -> 110 | H79: =IF(ISNUMBER(H62),H62,"") -> 110 | I79: =IF(ISNUMBER(I62),I62,"") -> 110 | L79: =I79*I$72 -> 110
A80: =A63 -> 2008 | B80: =IF(ISNUMBER(B63),B63,"") -> 83 | C80: =IF(ISNUMBER(C63),C63,"") -> 130 | D80: =IF(ISNUMBER(D63),D63,"") -> 138 | E80: =IF(ISNUMBER(E63),E63,"") -> 144 | F80: =IF(ISNUMBER(F63),F63,"") -> 145 | G80: =IF(ISNUMBER(G63),G63,"") -> 145 | H80: =IF(ISNUMBER(H63),H63,"") -> 146.5 | L80: =H80*H$72 -> 146.5
A81: =A64 -> 2009 | B81: =IF(ISNUMBER(B64),B64,"") -> 120 | C81: =IF(ISNUMBER(C64),C64,"") -> 165 | D81: =IF(ISNUMBER(D64),D64,"") -> 181 | E81: =IF(ISNUMBER(E64),E64,"") -> 190 | F81: =IF(ISNUMBER(F64),F64,"") -> 192 | G81: =IF(ISNUMBER(G64),G64,"") -> 195 | L81: =G81*G$72 -> 195.67552
A82: =A65 -> 2010 | B82: =IF(ISNUMBER(B65),B65,"") -> 149 | C82: =IF(ISNUMBER(C65),C65,"") -> 226 | D82: =IF(ISNUMBER(D65),D65,"") -> 246 | E82: =IF(ISNUMBER(E65),E65,"") -> 253 | F82: =IF(ISNUMBER(F65),F65,"") -> 257.5 | L82: =F82*F$72 -> 259.63231
A83: =A66 -> 2011 | B83: =IF(ISNUMBER(B66),B66,"") -> 158 | C83: =IF(ISNUMBER(C66),C66,"") -> 222 | D83: =IF(ISNUMBER(D66),D66,"") -> 241 | E83: =IF(ISNUMBER(E66),E66,"") -> 254.5 | L83: =E83*E$72 -> 260.59389
A84: =A67 -> 2012 | B84: =IF(ISNUMBER(B67),B67,"") -> 96 | C84: =IF(ISNUMBER(C67),C67,"") -> 177 | D84: =IF(ISNUMBER(D67),D67,"") -> 210 | L84: =D84*D$72 -> 224.31231
A85: =A68 -> 2013 | B85: =IF(ISNUMBER(B68),B68,"") -> 102 | C85: =IF(ISNUMBER(C68),C68,"") -> 250.5 | L85: =C85*C$72 -> 296.10135
A86: =A69 -> 2014 | B86: =IF(ISNUMBER(B69),B69,"") -> 102 | L86: =B86*B$72 -> 197.24904

Sheet 4. Projection - Method 3
E1: 我们选择4个月作为单位，而不是1年
A2: METHOD D - USE SHORTER PERIOD
A5: 1 - Original table | G5: =SUMIF('2. Claims data'!$X$14:$X$1730,"="&$C9,'2. Claims data'!$O$13:$O$1730) -> 27
H7: Delay (multiples of 4 months)
A8: Policy year | B8: Third | C8: Period | D8: 0 | E8: 1 | F8: 2 | G8: 3 | H8: 4 | I8: 5 | J8: 6 | K8: 7 | L8: 8 | M8: 9 | N8: 10 | O8: 11 | P8: 12 | Q8: 13 | R8: 14 | S8: 15 | T8: 16 | U8: 17 | V8: 18 | W8: 19 | X8: 20 | Y8: 21 | Z8: 22 | AA8: 23 | AB8: 24 | AC8: 25 | AD8: 26 | AE8: 27 | AF8: 28 | AJ8: Total reported
A9: 2005 | B9: 0 | C9: 0 | D9: =IF($C9+D$8>Latest_Third,"",SUMIFS(Table1[Non-zero? (1=Yes)],Table1[Policy third],"="&$C9,Table1[Delay (thirds)],"="&D$8)) -> 8 | E9: =IF($C9+E$8>Latest_Third,"",SUMIFS(Table1[Non-zero? (1=Yes)],Table1[Policy third],"="&$C9,Table1[Delay (thirds)],"="&E$8)) -> 6 | F9: =IF($C9+F$8>Latest_Third,"",SUMIFS(Table1[Non-zero? (1=Yes)],Table1[Policy third],"="&$C9,Table1[Delay (thirds)],"="&F$8)) -> 4 | G9: =IF($C9+G$8>Latest_Third,"",SUMIFS(Table1[Non-zero? (1=Yes)],Table1[Policy third],"="&$C9,Table1[Delay (thirds)],"="&G$8)) -> 5 | H9: =IF($C9+H$8>Latest_Third,"",SUMIFS(Table1[Non-zero? (1=Yes)],Table1[Policy third],"="&$C9,Table1[Delay (thirds)],"="&H$8)) -> 1 | I9: =IF($C9+I$8>Latest_Third,"",SUMIFS(Table1[Non-zero? (1=Yes)],Table1[Policy third],"="&$C9,Table1[Delay (thirds)],"="&I$8)) -> 1 | J9: =IF($C9+J$8>Latest_Third,"",SUMIFS(Table1[Non-zero? (1=Yes)],Table1[Policy third],"="&$C9,Table1[Delay (thirds)],"="&J$8)) -> 0 | K9: =IF($C9+K$8>Latest_Third,"",SUMIFS(Table1[Non-zero? (1=Yes)],Table1[Policy third],"="&$C9,Table1[Delay (thirds)],"="&K$8)) -> 1 | ... AF9: =IF($C9+AF$8>Latest_Third,"",SUMIFS(Table1[Non-zero? (1=Yes)],Table1[Policy third],"="&$C9,Table1[Delay (thirds)],"="&AF$8)) -> 0 | AJ9: =SUM(D9:W9) -> 28
A10: =A9 -> 2005 | B10: 1 | C10: 1 | D10: =IF($C10+D$8>Latest_Third,"",SUMIFS(Table1[Non-zero? (1=Yes)],Table1[Policy third],"="&$C10,Table1[Delay (thirds)],"="&D$8)) -> 10 | E10: =IF($C10+E$8>Latest_Third,"",SUMIFS(Table1[Non-zero? (1=Yes)],Table1[Policy third],"="&$C10,Table1[Delay (thirds)],"="&E$8)) -> 4 | F10: =IF($C10+F$8>Latest_Third,"",SUMIFS(Table1[Non-zero? (1=Yes)],Table1[Policy third],"="&$C10,Table1[Delay (thirds)],"="&F$8)) -> 3 | G10: =IF($C10+G$8>Latest_Third,"",SUMIFS(Table1[Non-zero? (1=Yes)],Table1[Policy third],"="&$C10,Table1[Delay (thirds)],"="&G$8)) -> 1 | H10: =IF($C10+H$8>Latest_Third,"",SUMIFS(Table1[Non-zero? (1=Yes)],Table1[Policy third],"="&$C10,Table1[Delay (thirds)],"="&H$8)) -> 0 | I10: =IF($C10+I$8>Latest_Third,"",SUMIFS(Table1[Non-zero? (1=Yes)],Table1[Policy third],"="&$C10,Table1[Delay (thirds)],"="&I$8)) -> 1 | J10: =IF($C10+J$8>Latest_Third,"",SUMIFS(Table1[Non-zero? (1=Yes)],Table1[Policy third],"="&$C10,Table1[Delay (thirds)],"="&J$8)) -> 0 | K10: =IF($C10+K$8>Latest_Third,"",SUMIFS(Table1[Non-zero? (1=Yes)],Table1[Policy third],"="&$C10,Table1[Delay (thirds)],"="&K$8)) -> 0 | ... AF10: =IF($C10+AF$8>Latest_Third,"",SUMIFS(Table1[Non-zero? (1=Yes)],Table1[Policy third],"="&$C10,Table1[Delay (thirds)],"="&AF$8)) | AJ10: =SUM(D10:W10) -> 20
A11: =A9 -> 2005 | B11: 2 | C11: 2 | D11: =IF($C11+D$8>Latest_Third,"",SUMIFS(Table1[Non-zero? (1=Yes)],Table1[Policy third],"="&$C11,Table1[Delay (thirds)],"="&D$8)) -> 18 | E11: =IF($C11+E$8>Latest_Third,"",SUMIFS(Table1[Non-zero? (1=Yes)],Table1[Policy third],"="&$C11,Table1[Delay (thirds)],"="&E$8)) -> 8 | F11: =IF($C11+F$8>Latest_Third,"",SUMIFS(Table1[Non-zero? (1=Yes)],Table1[Policy third],"="&$C11,Table1[Delay (thirds)],"="&F$8)) -> 4 | G11: =IF($C11+G$8>Latest_Third,"",SUMIFS(Table1[Non-zero? (1=Yes)],Table1[Policy third],"="&$C11,Table1[Delay (thirds)],"="&G$8)) -> 3 | H11: =IF($C11+H$8>Latest_Third,"",SUMIFS(Table1[Non-zero? (1=Yes)],Table1[Policy third],"="&$C11,Table1[Delay (thirds)],"="&H$8)) -> 1 | I11: =IF($C11+I$8>Latest_Third,"",SUMIFS(Table1[Non-zero? (1=Yes)],Table1[Policy third],"="&$C11,Table1[Delay (thirds)],"="&I$8)) -> 1 | J11: =IF($C11+J$8>Latest_Third,"",SUMIFS(Table1[Non-zero? (1=Yes)],Table1[Policy third],"="&$C11,Table1[Delay (thirds)],"="&J$8)) -> 0 | K11: =IF($C11+K$8>Latest_Third,"",SUMIFS(Table1[Non-zero? (1=Yes)],Table1[Policy third],"="&$C11,Table1[Delay (thirds)],"="&K$8)) -> 2 | ... AF11: =IF($C11+AF$8>Latest_Third,"",SUMIFS(Table1[Non-zero? (1=Yes)],Table1[Policy third],"="&$C11,Table1[Delay (thirds)],"="&AF$8)) | AJ11: =SUM(D11:W11) -> 38
A12: =A9+1 -> 2006 | B12: 0 | C12: 3 | D12: =IF($C12+D$8>Latest_Third,"",SUMIFS(Table1[Non-zero? (1=Yes)],Table1[Policy third],"="&$C12,Table1[Delay (thirds)],"="&D$8)) -> 4 | E12: =IF($C12+E$8>Latest_Third,"",SUMIFS(Table1[Non-zero? (1=Yes)],Table1[Policy third],"="&$C12,Table1[Delay (thirds)],"="&E$8)) -> 4 | F12: =IF($C12+F$8>Latest_Third,"",SUMIFS(Table1[Non-zero? (1=Yes)],Table1[Policy third],"="&$C12,Table1[Delay (thirds)],"="&F$8)) -> 3 | G12: =IF($C12+G$8>Latest_Third,"",SUMIFS(Table1[Non-zero? (1=Yes)],Table1[Policy third],"="&$C12,Table1[Delay (thirds)],"="&G$8)) -> 2 | H12: =IF($C12+H$8>Latest_Third,"",SUMIFS(Table1[Non-zero? (1=Yes)],Table1[Policy third],"="&$C12,Table1[Delay (thirds)],"="&H$8)) -> 0 | I12: =IF($C12+I$8>Latest_Third,"",SUMIFS(Table1[Non-zero? (1=Yes)],Table1[Policy third],"="&$C12,Table1[Delay (thirds)],"="&I$8)) -> 1 | J12: =IF($C12+J$8>Latest_Third,"",SUMIFS(Table1[Non-zero? (1=Yes)],Table1[Policy third],"="&$C12,Table1[Delay (thirds)],"="&J$8)) -> 1 | K12: =IF($C12+K$8>Latest_Third,"",SUMIFS(Table1[Non-zero? (1=Yes)],Table1[Policy third],"="&$C12,Table1[Delay (thirds)],"="&K$8)) -> 0 | ... AF12: =IF($C12+AF$8>Latest_Third,"",SUMIFS(Table1[Non-zero? (1=Yes)],Table1[Policy third],"="&$C12,Table1[Delay (thirds)],"="&AF$8)) | AJ12: =SUM(D12:W12) -> 17
A13: =A10+1 -> 2006 | B13: 1 | C13: 4 | D13: =IF($C13+D$8>Latest_Third,"",SUMIFS(Table1[Non-zero? (1=Yes)],Table1[Policy third],"="&$C13,Table1[Delay (thirds)],"="&D$8)) -> 13 | E13: =IF($C13+E$8>Latest_Third,"",SUMIFS(Table1[Non-zero? (1=Yes)],Table1[Policy third],"="&$C13,Table1[Delay (thirds)],"="&E$8)) -> 8 | F13: =IF($C13+F$8>Latest_Third,"",SUMIFS(Table1[Non-zero? (1=Yes)],Table1[Policy third],"="&$C13,Table1[Delay (thirds)],"="&F$8)) -> 2 | G13: =IF($C13+G$8>Latest_Third,"",SUMIFS(Table1[Non-zero? (1=Yes)],Table1[Policy third],"="&$C13,Table1[Delay (thirds)],"="&G$8)) -> 3 | H13: =IF($C13+H$8>Latest_Third,"",SUMIFS(Table1[Non-zero? (1=Yes)],Table1[Policy third],"="&$C13,Table1[Delay (thirds)],"="&H$8)) -> 1 | I13: =IF($C13+I$8>Latest_Third,"",SUMIFS(Table1[Non-zero? (1=Yes)],Table1[Policy third],"="&$C13,Table1[Delay (thirds)],"="&I$8)) -> 1 | J13: =IF($C13+J$8>Latest_Third,"",SUMIFS(Table1[Non-zero? (1=Yes)],Table1[Policy third],"="&$C13,Table1[Delay (thirds)],"="&J$8)) -> 2 | K13: =IF($C13+K$8>Latest_Third,"",SUMIFS(Table1[Non-zero? (1=Yes)],Table1[Policy third],"="&$C13,Table1[Delay (thirds)],"="&K$8)) -> 0 | ... AF13: =IF($C13+AF$8>Latest_Third,"",SUMIFS(Table1[Non-zero? (1=Yes)],Table1[Policy third],"="&$C13,Table1[Delay (thirds)],"="&AF$8)) | AJ13: =SUM(D13:W13) -> 35
A14: =A11+1 -> 2006 | B14: 2 | C14: 5 | D14: =IF($C14+D$8>Latest_Third,"",SUMIFS(Table1[Non-zero? (1=Yes)],Table1[Policy third],"="&$C14,Table1[Delay (thirds)],"="&D$8)) -> 9 | E14: =IF($C14+E$8>Latest_Third,"",SUMIFS(Table1[Non-zero? (1=Yes)],Table1[Policy third],"="&$C14,Table1[Delay (thirds)],"="&E$8)) -> 10 | F14: =IF($C14+F$8>Latest_Third,"",SUMIFS(Table1[Non-zero? (1=Yes)],Table1[Policy third],"="&$C14,Table1[Delay (thirds)],"="&F$8)) -> 8 | G14: =IF($C14+G$8>Latest_Third,"",SUMIFS(Table1[Non-zero? (1=Yes)],Table1[Policy third],"="&$C14,Table1[Delay (thirds)],"="&G$8)) -> 1 | H14: =IF($C14+H$8>Latest_Third,"",SUMIFS(Table1[Non-zero? (1=Yes)],Table1[Policy third],"="&$C14,Table1[Delay (thirds)],"="&H$8)) -> 4 | I14: =IF($C14+I$8>Latest_Third,"",SUMIFS(Table1[Non-zero? (1=Yes)],Table1[Policy third],"="&$C14,Table1[Delay (thirds)],"="&I$8)) -> 3 | J14: =IF($C14+J$8>Latest_Third,"",SUMIFS(Table1[Non-zero? (1=Yes)],Table1[Policy third],"="&$C14,Table1[Delay (thirds)],"="&J$8)) -> 1 | K14: =IF($C14+K$8>Latest_Third,"",SUMIFS(Table1[Non-zero? (1=Yes)],Table1[Policy third],"="&$C14,Table1[Delay (thirds)],"="&K$8)) -> 0 | ... AF14: =IF($C14+AF$8>Latest_Third,"",SUMIFS(Table1[Non-zero? (1=Yes)],Table1[Policy third],"="&$C14,Table1[Delay (thirds)],"="&AF$8)) | AJ14: =SUM(D14:W14) -> 40
A15: =A12+1 -> 2007 | B15: 0 | C15: 6 | D15: =IF($C15+D$8>Latest_Third,"",SUMIFS(Table1[Non-zero? (1=Yes)],Table1[Policy third],"="&$C15,Table1[Delay (thirds)],"="&D$8)) -> 20 | E15: =IF($C15+E$8>Latest_Third,"",SUMIFS(Table1[Non-zero? (1=Yes)],Table1[Policy third],"="&$C15,Table1[Delay (thirds)],"="&E$8)) -> 7 | F15: =IF($C15+F$8>Latest_Third,"",SUMIFS(Table1[Non-zero? (1=Yes)],Table1[Policy third],"="&$C15,Table1[Delay (thirds)],"="&F$8)) -> 5 | G15: =IF($C15+G$8>Latest_Third,"",SUMIFS(Table1[Non-zero? (1=Yes)],Table1[Policy third],"="&$C15,Table1[Delay (thirds)],"="&G$8)) -> 3 | H15: =IF($C15+H$8>Latest_Third,"",SUMIFS(Table1[Non-zero? (1=Yes)],Table1[Policy third],"="&$C15,Table1[Delay (thirds)],"="&H$8)) -> 4 | I15: =IF($C15+I$8>Latest_Third,"",SUMIFS(Table1[Non-zero? (1=Yes)],Table1[Policy third],"="&$C15,Table1[Delay (thirds)],"="&I$8)) -> 1 | J15: =IF($C15+J$8>Latest_Third,"",SUMIFS(Table1[Non-zero? (1=Yes)],Table1[Policy third],"="&$C15,Table1[Delay (thirds)],"="&J$8)) -> 3 | K15: =IF($C15+K$8>Latest_Third,"",SUMIFS(Table1[Non-zero? (1=Yes)],Table1[Policy third],"="&$C15,Table1[Delay (thirds)],"="&K$8)) -> 1 | ... AF15: =IF($C15+AF$8>Latest_Third,"",SUMIFS(Table1[Non-zero? (1=Yes)],Table1[Policy third],"="&$C15,Table1[Delay (thirds)],"="&AF$8)) | AJ15: =SUM(D15:W15) -> 46
A16: =A13+1 -> 2007 | B16: 1 | C16: 7 | D16: =IF($C16+D$8>Latest_Third,"",SUMIFS(Table1[Non-zero? (1=Yes)],Table1[Policy third],"="&$C16,Table1[Delay (thirds)],"="&D$8)) -> 18 | E16: =IF($C16+E$8>Latest_Third,"",SUMIFS(Table1[Non-zero? (1=Yes)],Table1[Policy third],"="&$C16,Table1[Delay (thirds)],"="&E$8)) -> 8 | F16: =IF($C16+F$8>Latest_Third,"",SUMIFS(Table1[Non-zero? (1=Yes)],Table1[Policy third],"="&$C16,Table1[Delay (thirds)],"="&F$8)) -> 5 | G16: =IF($C16+G$8>Latest_Third,"",SUMIFS(Table1[Non-zero? (1=Yes)],Table1[Policy third],"="&$C16,Table1[Delay (thirds)],"="&G$8)) -> 2 | H16: =IF($C16+H$8>Latest_Third,"",SUMIFS(Table1[Non-zero? (1=Yes)],Table1[Policy third],"="&$C16,Table1[Delay (thirds)],"="&H$8)) -> 3 | I16: =IF($C16+I$8>Latest_Third,"",SUMIFS(Table1[Non-zero? (1=Yes)],Table1[Policy third],"="&$C16,Table1[Delay (thirds)],"="&I$8)) -> 0 | J16: =IF($C16+J$8>Latest_Third,"",SUMIFS(Table1[Non-zero? (1=Yes)],Table1[Policy third],"="&$C16,Table1[Delay (thirds)],"="&J$8)) -> 3 | K16: =IF($C16+K$8>Latest_Third,"",SUMIFS(Table1[Non-zero? (1=Yes)],Table1[Policy third],"="&$C16,Table1[Delay (thirds)],"="&K$8)) -> 0 | ... AF16: =IF($C16+AF$8>Latest_Third,"",SUMIFS(Table1[Non-zero? (1=Yes)],Table1[Policy third],"="&$C16,Table1[Delay (thirds)],"="&AF$8)) | AJ16: =SUM(D16:W16) -> 39
A17: =A14+1 -> 2007 | B17: 2 | C17: 8 | D17: =IF($C17+D$8>Latest_Third,"",SUMIFS(Table1[Non-zero? (1=Yes)],Table1[Policy third],"="&$C17,Table1[Delay (thirds)],"="&D$8)) -> 7 | E17: =IF($C17+E$8>Latest_Third,"",SUMIFS(Table1[Non-zero? (1=Yes)],Table1[Policy third],"="&$C17,Table1[Delay (thirds)],"="&E$8)) -> 8 | F17: =IF($C17+F$8>Latest_Third,"",SUMIFS(Table1[Non-zero? (1=Yes)],Table1[Policy third],"="&$C17,Table1[Delay (thirds)],"="&F$8)) -> 4 | G17: =IF($C17+G$8>Latest_Third,"",SUMIFS(Table1[Non-zero? (1=Yes)],Table1[Policy third],"="&$C17,Table1[Delay (thirds)],"="&G$8)) -> 3 | H17: =IF($C17+H$8>Latest_Third,"",SUMIFS(Table1[Non-zero? (1=Yes)],Table1[Policy third],"="&$C17,Table1[Delay (thirds)],"="&H$8)) -> 2 | I17: =IF($C17+I$8>Latest_Third,"",SUMIFS(Table1[Non-zero? (1=Yes)],Table1[Policy third],"="&$C17,Table1[Delay (thirds)],"="&I$8)) -> 0 | J17: =IF($C17+J$8>Latest_Third,"",SUMIFS(Table1[Non-zero? (1=Yes)],Table1[Policy third],"="&$C17,Table1[Delay (thirds)],"="&J$8)) -> 0 | K17: =IF($C17+K$8>Latest_Third,"",SUMIFS(Table1[Non-zero? (1=Yes)],Table1[Policy third],"="&$C17,Table1[Delay (thirds)],"="&K$8)) -> 0 | ... AF17: =IF($C17+AF$8>Latest_Third,"",SUMIFS(Table1[Non-zero? (1=Yes)],Table1[Policy third],"="&$C17,Table1[Delay (thirds)],"="&AF$8)) | AJ17: =SUM(D17:W17) -> 25
A18: =A15+1 -> 2008 | B18: 0 | C18: 9 | D18: =IF($C18+D$8>Latest_Third,"",SUMIFS(Table1[Non-zero? (1=Yes)],Table1[Policy third],"="&$C18,Table1[Delay (thirds)],"="&D$8)) -> 13 | E18: =IF($C18+E$8>Latest_Third,"",SUMIFS(Table1[Non-zero? (1=Yes)],Table1[Policy third],"="&$C18,Table1[Delay (thirds)],"="&E$8)) -> 11 | F18: =IF($C18+F$8>Latest_Third,"",SUMIFS(Table1[Non-zero? (1=Yes)],Table1[Policy third],"="&$C18,Table1[Delay (thirds)],"="&F$8)) -> 5 | G18: =IF($C18+G$8>Latest_Third,"",SUMIFS(Table1[Non-zero? (1=Yes)],Table1[Policy third],"="&$C18,Table1[Delay (thirds)],"="&G$8)) -> 5 | H18: =IF($C18+H$8>Latest_Third,"",SUMIFS(Table1[Non-zero? (1=Yes)],Table1[Policy third],"="&$C18,Table1[Delay (thirds)],"="&H$8)) -> 1 | I18: =IF($C18+I$8>Latest_Third,"",SUMIFS(Table1[Non-zero? (1=Yes)],Table1[Policy third],"="&$C18,Table1[Delay (thirds)],"="&I$8)) -> 2 | J18: =IF($C18+J$8>Latest_Third,"",SUMIFS(Table1[Non-zero? (1=Yes)],Table1[Policy third],"="&$C18,Table1[Delay (thirds)],"="&J$8)) -> 0 | K18: =IF($C18+K$8>Latest_Third,"",SUMIFS(Table1[Non-zero? (1=Yes)],Table1[Policy third],"="&$C18,Table1[Delay (thirds)],"="&K$8)) -> 0 | ... AF18: =IF($C18+AF$8>Latest_Third,"",SUMIFS(Table1[Non-zero? (1=Yes)],Table1[Policy third],"="&$C18,Table1[Delay (thirds)],"="&AF$8)) | AJ18: =SUM(D18:W18) -> 40
A19: =A16+1 -> 2008 | B19: 1 | C19: 10 | D19: =IF($C19+D$8>Latest_Third,"",SUMIFS(Table1[Non-zero? (1=Yes)],Table1[Policy third],"="&$C19,Table1[Delay (thirds)],"="&D$8)) -> 29 | E19: =IF($C19+E$8>Latest_Third,"",SUMIFS(Table1[Non-zero? (1=Yes)],Table1[Policy third],"="&$C19,Table1[Delay (thirds)],"="&E$8)) -> 8 | F19: =IF($C19+F$8>Latest_Third,"",SUMIFS(Table1[Non-zero? (1=Yes)],Table1[Policy third],"="&$C19,Table1[Delay (thirds)],"="&F$8)) -> 13 | G19: =IF($C19+G$8>Latest_Third,"",SUMIFS(Table1[Non-zero? (1=Yes)],Table1[Policy third],"="&$C19,Table1[Delay (thirds)],"="&G$8)) -> 4 | H19: =IF($C19+H$8>Latest_Third,"",SUMIFS(Table1[Non-zero? (1=Yes)],Table1[Policy third],"="&$C19,Table1[Delay (thirds)],"="&H$8)) -> 3 | I19: =IF($C19+I$8>Latest_Third,"",SUMIFS(Table1[Non-zero? (1=Yes)],Table1[Policy third],"="&$C19,Table1[Delay (thirds)],"="&I$8)) -> 3 | J19: =IF($C19+J$8>Latest_Third,"",SUMIFS(Table1[Non-zero? (1=Yes)],Table1[Policy third],"="&$C19,Table1[Delay (thirds)],"="&J$8)) -> 0 | K19: =IF($C19+K$8>Latest_Third,"",SUMIFS(Table1[Non-zero? (1=Yes)],Table1[Policy third],"="&$C19,Table1[Delay (thirds)],"="&K$8)) -> 0 | ... AF19: =IF($C19+AF$8>Latest_Third,"",SUMIFS(Table1[Non-zero? (1=Yes)],Table1[Policy third],"="&$C19,Table1[Delay (thirds)],"="&AF$8)) | AJ19: =SUM(D19:W19) -> 64
A20: =A17+1 -> 2008 | B20: 2 | C20: 11 | D20: =IF($C20+D$8>Latest_Third,"",SUMIFS(Table1[Non-zero? (1=Yes)],Table1[Policy third],"="&$C20,Table1[Delay (thirds)],"="&D$8)) -> 17 | E20: =IF($C20+E$8>Latest_Third,"",SUMIFS(Table1[Non-zero? (1=Yes)],Table1[Policy third],"="&$C20,Table1[Delay (thirds)],"="&E$8)) -> 8 | F20: =IF($C20+F$8>Latest_Third,"",SUMIFS(Table1[Non-zero? (1=Yes)],Table1[Policy third],"="&$C20,Table1[Delay (thirds)],"="&F$8)) -> 7 | G20: =IF($C20+G$8>Latest_Third,"",SUMIFS(Table1[Non-zero? (1=Yes)],Table1[Policy third],"="&$C20,Table1[Delay (thirds)],"="&G$8)) -> 4 | H20: =IF($C20+H$8>Latest_Third,"",SUMIFS(Table1[Non-zero? (1=Yes)],Table1[Policy third],"="&$C20,Table1[Delay (thirds)],"="&H$8)) -> 4 | I20: =IF($C20+I$8>Latest_Third,"",SUMIFS(Table1[Non-zero? (1=Yes)],Table1[Policy third],"="&$C20,Table1[Delay (thirds)],"="&I$8)) -> 0 | J20: =IF($C20+J$8>Latest_Third,"",SUMIFS(Table1[Non-zero? (1=Yes)],Table1[Policy third],"="&$C20,Table1[Delay (thirds)],"="&J$8)) -> 1 | K20: =IF($C20+K$8>Latest_Third,"",SUMIFS(Table1[Non-zero? (1=Yes)],Table1[Policy third],"="&$C20,Table1[Delay (thirds)],"="&K$8)) -> 1 | ... AF20: =IF($C20+AF$8>Latest_Third,"",SUMIFS(Table1[Non-zero? (1=Yes)],Table1[Policy third],"="&$C20,Table1[Delay (thirds)],"="&AF$8)) | AJ20: =SUM(D20:W20) -> 42
A21: =A18+1 -> 2009 | B21: 0 | C21: 12 | D21: =IF($C21+D$8>Latest_Third,"",SUMIFS(Table1[Non-zero? (1=Yes)],Table1[Policy third],"="&$C21,Table1[Delay (thirds)],"="&D$8)) -> 29 | E21: =IF($C21+E$8>Latest_Third,"",SUMIFS(Table1[Non-zero? (1=Yes)],Table1[Policy third],"="&$C21,Table1[Delay (thirds)],"="&E$8)) -> 11 | F21: =IF($C21+F$8>Latest_Third,"",SUMIFS(Table1[Non-zero? (1=Yes)],Table1[Policy third],"="&$C21,Table1[Delay (thirds)],"="&F$8)) -> 5 | G21: =IF($C21+G$8>Latest_Third,"",SUMIFS(Table1[Non-zero? (1=Yes)],Table1[Policy third],"="&$C21,Table1[Delay (thirds)],"="&G$8)) -> 4 | H21: =IF($C21+H$8>Latest_Third,"",SUMIFS(Table1[Non-zero? (1=Yes)],Table1[Policy third],"="&$C21,Table1[Delay (thirds)],"="&H$8)) -> 2 | I21: =IF($C21+I$8>Latest_Third,"",SUMIFS(Table1[Non-zero? (1=Yes)],Table1[Policy third],"="&$C21,Table1[Delay (thirds)],"="&I$8)) -> 3 | J21: =IF($C21+J$8>Latest_Third,"",SUMIFS(Table1[Non-zero? (1=Yes)],Table1[Policy third],"="&$C21,Table1[Delay (thirds)],"="&J$8)) -> 0 | K21: =IF($C21+K$8>Latest_Third,"",SUMIFS(Table1[Non-zero? (1=Yes)],Table1[Policy third],"="&$C21,Table1[Delay (thirds)],"="&K$8)) -> 0 | ... AF21: =IF($C21+AF$8>Latest_Third,"",SUMIFS(Table1[Non-zero? (1=Yes)],Table1[Policy third],"="&$C21,Table1[Delay (thirds)],"="&AF$8)) | AJ21: =SUM(D21:W21) -> 55
A22: =A19+1 -> 2009 | B22: 1 | C22: 13 | D22: =IF($C22+D$8>Latest_Third,"",SUMIFS(Table1[Non-zero? (1=Yes)],Table1[Policy third],"="&$C22,Table1[Delay (thirds)],"="&D$8)) -> 33 | E22: =IF($C22+E$8>Latest_Third,"",SUMIFS(Table1[Non-zero? (1=Yes)],Table1[Policy third],"="&$C22,Table1[Delay (thirds)],"="&E$8)) -> 16 | F22: =IF($C22+F$8>Latest_Third,"",SUMIFS(Table1[Non-zero? (1=Yes)],Table1[Policy third],"="&$C22,Table1[Delay (thirds)],"="&F$8)) -> 5 | G22: =IF($C22+G$8>Latest_Third,"",SUMIFS(Table1[Non-zero? (1=Yes)],Table1[Policy third],"="&$C22,Table1[Delay (thirds)],"="&G$8)) -> 7 | H22: =IF($C22+H$8>Latest_Third,"",SUMIFS(Table1[Non-zero? (1=Yes)],Table1[Policy third],"="&$C22,Table1[Delay (thirds)],"="&H$8)) -> 2 | I22: =IF($C22+I$8>Latest_Third,"",SUMIFS(Table1[Non-zero? (1=Yes)],Table1[Policy third],"="&$C22,Table1[Delay (thirds)],"="&I$8)) -> 6 | J22: =IF($C22+J$8>Latest_Third,"",SUMIFS(Table1[Non-zero? (1=Yes)],Table1[Policy third],"="&$C22,Table1[Delay (thirds)],"="&J$8)) -> 1 | K22: =IF($C22+K$8>Latest_Third,"",SUMIFS(Table1[Non-zero? (1=Yes)],Table1[Policy third],"="&$C22,Table1[Delay (thirds)],"="&K$8)) -> 1 | ... AF22: =IF($C22+AF$8>Latest_Third,"",SUMIFS(Table1[Non-zero? (1=Yes)],Table1[Policy third],"="&$C22,Table1[Delay (thirds)],"="&AF$8)) | AJ22: =SUM(D22:W22) -> 77
A23: =A20+1 -> 2009 | B23: 2 | C23: 14 | D23: =IF($C23+D$8>Latest_Third,"",SUMIFS(Table1[Non-zero? (1=Yes)],Table1[Policy third],"="&$C23,Table1[Delay (thirds)],"="&D$8)) -> 26 | E23: =IF($C23+E$8>Latest_Third,"",SUMIFS(Table1[Non-zero? (1=Yes)],Table1[Policy third],"="&$C23,Table1[Delay (thirds)],"="&E$8)) -> 11 | F23: =IF($C23+F$8>Latest_Third,"",SUMIFS(Table1[Non-zero? (1=Yes)],Table1[Policy third],"="&$C23,Table1[Delay (thirds)],"="&F$8)) -> 9 | G23: =IF($C23+G$8>Latest_Third,"",SUMIFS(Table1[Non-zero? (1=Yes)],Table1[Policy third],"="&$C23,Table1[Delay (thirds)],"="&G$8)) -> 2 | H23: =IF($C23+H$8>Latest_Third,"",SUMIFS(Table1[Non-zero? (1=Yes)],Table1[Policy third],"="&$C23,Table1[Delay (thirds)],"="&H$8)) -> 3 | I23: =IF($C23+I$8>Latest_Third,"",SUMIFS(Table1[Non-zero? (1=Yes)],Table1[Policy third],"="&$C23,Table1[Delay (thirds)],"="&I$8)) -> 0 | J23: =IF($C23+J$8>Latest_Third,"",SUMIFS(Table1[Non-zero? (1=Yes)],Table1[Policy third],"="&$C23,Table1[Delay (thirds)],"="&J$8)) -> 5 | K23: =IF($C23+K$8>Latest_Third,"",SUMIFS(Table1[Non-zero? (1=Yes)],Table1[Policy third],"="&$C23,Table1[Delay (thirds)],"="&K$8)) -> 1 | ... AF23: =IF($C23+AF$8>Latest_Third,"",SUMIFS(Table1[Non-zero? (1=Yes)],Table1[Policy third],"="&$C23,Table1[Delay (thirds)],"="&AF$8)) | AJ23: =SUM(D23:W23) -> 62
... A37: =A34+1 -> 2014 | B37: 1 | C37: 28 | D37: =IF($C37+D$8>Latest_Third,"",SUMIFS(Table1[Non-zero? (1=Yes)],Table1[Policy third],"="&$C37,Table1[Delay (thirds)],"="&D$8)) -> 19 | E37: =IF($C37+E$8>Latest_Third,"",SUMIFS(Table1[Non-zero? (1=Yes)],Table1[Policy third],"="&$C37,Table1[Delay (thirds)],"="&E$8)) | F37: =IF($C37+F$8>Latest_Third,"",SUMIFS(Table1[Non-zero? (1=Yes)],Table1[Policy third],"="&$C37,Table1[Delay (thirds)],"="&F$8)) | G37: =IF($C37+G$8>Latest_Third,"",SUMIFS(Table1[Non-zero? (1=Yes)],Table1[Policy third],"="&$C37,Table1[Delay (thirds)],"="&G$8)) | H37: =IF($C37+H$8>Latest_Third,"",SUMIFS(Table1[Non-zero? (1=Yes)],Table1[Policy third],"="&$C37,Table1[Delay (thirds)],"="&H$8)) | I37: =IF($C37+I$8>Latest_Third,"",SUMIFS(Table1[Non-zero? (1=Yes)],Table1[Policy third],"="&$C37,Table1[Delay (thirds)],"="&I$8)) | J37: =IF($C37+J$8>Latest_Third,"",SUMIFS(Table1[Non-zero? (1=Yes)],Table1[Policy third],"="&$C37,Table1[Delay (thirds)],"="&J$8)) | K37: =IF($C37+K$8>Latest_Third,"",SUMIFS(Table1[Non-zero? (1=Yes)],Table1[Policy third],"="&$C37,Table1[Delay (thirds)],"="&K$8)) | ... AF37: =IF($C37+AF$8>Latest_Third,"",SUMIFS(Table1[Non-zero? (1=Yes)],Table1[Policy third],"="&$C37,Table1[Delay (thirds)],"="&AF$8)) | AJ37: =SUM(D37:W37) -> 19
A41: 2 - Cumulative
H43: Delay (multiples of 4 months)
A44: Year | B44: Period (in year) | C44: Period | D44: 0 | E44: 1 | F44: 2 | G44: 3 | H44: 4 | I44: 5 | J44: 6 | K44: 7 | L44: 8 | M44: 9 | N44: 10 | O44: 11 | P44: 12 | Q44: 13 | R44: 14 | S44: 15 | T44: 16 | U44: 17 | V44: 18 | W44: 19
A45: =A9 -> 2005 | B45: 0 | C45: 0 | D45: =IF(D$44=0,D9,IF($C45+D$44>Latest_Third,"",D9+C45)) -> 8 | E45: =IF(E$44=0,E9,IF($C45+E$44>Latest_Third,"",E9+D45)) -> 14 | F45: =IF(F$44=0,F9,IF($C45+F$44>Latest_Third,"",F9+E45)) -> 18 | G45: =IF(G$44=0,G9,IF($C45+G$44>Latest_Third,"",G9+F45)) -> 23 | H45: =IF(H$44=0,H9,IF($C45+H$44>Latest_Third,"",H9+G45)) -> 24 | I45: =IF(I$44=0,I9,IF($C45+I$44>Latest_Third,"",I9+H45)) -> 25 | J45: =IF(J$44=0,J9,IF($C45+J$44>Latest_Third,"",J9+I45)) -> 25 | K45: =IF(K$44=0,K9,IF($C45+K$44>Latest_Third,"",K9+J45)) -> 26 | ... W45: =IF(W$44=0,W9,IF($C45+W$44>Latest_Third,"",W9+V45)) -> 28
A46: =A10 -> 2005 | B46: 1 | C46: 1 | D46: =IF(D$44=0,D10,IF($C46+D$44>Latest_Third,"",D10+C46)) -> 10 | E46: =IF(E$44=0,E10,IF($C46+E$44>Latest_Third,"",E10+D46)) -> 14 | F46: =IF(F$44=0,F10,IF($C46+F$44>Latest_Third,"",F10+E46)) -> 17 | G46: =IF(G$44=0,G10,IF($C46+G$44>Latest_Third,"",G10+F46)) -> 18 | H46: =IF(H$44=0,H10,IF($C46+H$44>Latest_Third,"",H10+G46)) -> 18 | I46: =IF(I$44=0,I10,IF($C46+I$44>Latest_Third,"",I10+H46)) -> 19 | J46: =IF(J$44=0,J10,IF($C46+J$44>Latest_Third,"",J10+I46)) -> 19 | K46: =IF(K$44=0,K10,IF($C46+K$44>Latest_Third,"",K10+J46)) -> 19 | ... W46: =IF(W$44=0,W10,IF($C46+W$44>Latest_Third,"",W10+V46)) -> 20
A47: =A11 -> 2005 | B47: 2 | C47: 2 | D47: =IF(D$44=0,D11,IF($C47+D$44>Latest_Third,"",D11+C47)) -> 18 | E47: =IF(E$44=0,E11,IF($C47+E$44>Latest_Third,"",E11+D47)) -> 26 | F47: =IF(F$44=0,F11,IF($C47+F$44>Latest_Third,"",F11+E47)) -> 30 | G47: =IF(G$44=0,G11,IF($C47+G$44>Latest_Third,"",G11+F47)) -> 33 | H47: =IF(H$44=0,H11,IF($C47+H$44>Latest_Third,"",H11+G47)) -> 34 | I47: =IF(I$44=0,I11,IF($C47+I$44>Latest_Third,"",I11+H47)) -> 35 | J47: =IF(J$44=0,J11,IF($C47+J$44>Latest_Third,"",J11+I47)) -> 35 | K47: =IF(K$44=0,K11,IF($C47+K$44>Latest_Third,"",K11+J47)) -> 37 | ... W47: =IF(W$44=0,W11,IF($C47+W$44>Latest_Third,"",W11+V47)) -> 38
A48: =A12 -> 2006 | B48: 0 | C48: 3 | D48: =IF(D$44=0,D12,IF($C48+D$44>Latest_Third,"",D12+C48)) -> 4 | E48: =IF(E$44=0,E12,IF($C48+E$44>Latest_Third,"",E12+D48)) -> 8 | F48: =IF(F$44=0,F12,IF($C48+F$44>Latest_Third,"",F12+E48)) -> 11 | G48: =IF(G$44=0,G12,IF($C48+G$44>Latest_Third,"",G12+F48)) -> 13 | H48: =IF(H$44=0,H12,IF($C48+H$44>Latest_Third,"",H12+G48)) -> 13 | I48: =IF(I$44=0,I12,IF($C48+I$44>Latest_Third,"",I12+H48)) -> 14 | J48: =IF(J$44=0,J12,IF($C48+J$44>Latest_Third,"",J12+I48)) -> 15 | K48: =IF(K$44=0,K12,IF($C48+K$44>Latest_Third,"",K12+J48)) -> 15 | ... W48: =IF(W$44=0,W12,IF($C48+W$44>Latest_Third,"",W12+V48)) -> 17
A49: =A13 -> 2006 | B49: 1 | C49: 4 | D49: =IF(D$44=0,D13,IF($C49+D$44>Latest_Third,"",D13+C49)) -> 13 | E49: =IF(E$44=0,E13,IF($C49+E$44>Latest_Third,"",E13+D49)) -> 21 | F49: =IF(F$44=0,F13,IF($C49+F$44>Latest_Third,"",F13+E49)) -> 23 | G49: =IF(G$44=0,G13,IF($C49+G$44>Latest_Third,"",G13+F49)) -> 26 | H49: =IF(H$44=0,H13,IF($C49+H$44>Latest_Third,"",H13+G49)) -> 27 | I49: =IF(I$44=0,I13,IF($C49+I$44>Latest_Third,"",I13+H49)) -> 28 | J49: =IF(J$44=0,J13,IF($C49+J$44>Latest_Third,"",J13+I49)) -> 30 | K49: =IF(K$44=0,K13,IF($C49+K$44>Latest_Third,"",K13+J49)) -> 30 | ... W49: =IF(W$44=0,W13,IF($C49+W$44>Latest_Third,"",W13+V49)) -> 35
A50: =A14 -> 2006 | B50: 2 | C50: 5 | D50: =IF(D$44=0,D14,IF($C50+D$44>Latest_Third,"",D14+C50)) -> 9 | E50: =IF(E$44=0,E14,IF($C50+E$44>Latest_Third,"",E14+D50)) -> 19 | F50: =IF(F$44=0,F14,IF($C50+F$44>Latest_Third,"",F14+E50)) -> 27 | G50: =IF(G$44=0,G14,IF($C50+G$44>Latest_Third,"",G14+F50)) -> 28 | H50: =IF(H$44=0,H14,IF($C50+H$44>Latest_Third,"",H14+G50)) -> 32 | I50: =IF(I$44=0,I14,IF($C50+I$44>Latest_Third,"",I14+H50)) -> 35 | J50: =IF(J$44=0,J14,IF($C50+J$44>Latest_Third,"",J14+I50)) -> 36 | K50: =IF(K$44=0,K14,IF($C50+K$44>Latest_Third,"",K14+J50)) -> 36 | ... W50: =IF(W$44=0,W14,IF($C50+W$44>Latest_Third,"",W14+V50)) -> 40
A51: =A15 -> 2007 | B51: 0 | C51: 6 | D51: =IF(D$44=0,D15,IF($C51+D$44>Latest_Third,"",D15+C51)) -> 20 | E51: =IF(E$44=0,E15,IF($C51+E$44>Latest_Third,"",E15+D51)) -> 27 | F51: =IF(F$44=0,F15,IF($C51+F$44>Latest_Third,"",F15+E51)) -> 32 | G51: =IF(G$44=0,G15,IF($C51+G$44>Latest_Third,"",G15+F51)) -> 35 | H51: =IF(H$44=0,H15,IF($C51+H$44>Latest_Third,"",H15+G51)) -> 39 | I51: =IF(I$44=0,I15,IF($C51+I$44>Latest_Third,"",I15+H51)) -> 40 | J51: =IF(J$44=0,J15,IF($C51+J$44>Latest_Third,"",J15+I51)) -> 43 | K51: =IF(K$44=0,K15,IF($C51+K$44>Latest_Third,"",K15+J51)) -> 44 | ... W51: =IF(W$44=0,W15,IF($C51+W$44>Latest_Third,"",W15+V51)) -> 46
A52: =A16 -> 2007 | B52: 1 | C52: 7 | D52: =IF(D$44=0,D16,IF($C52+D$44>Latest_Third,"",D16+C52)) -> 18 | E52: =IF(E$44=0,E16,IF($C52+E$44>Latest_Third,"",E16+D52)) -> 26 | F52: =IF(F$44=0,F16,IF($C52+F$44>Latest_Third,"",F16+E52)) -> 31 | G52: =IF(G$44=0,G16,IF($C52+G$44>Latest_Third,"",G16+F52)) -> 33 | H52: =IF(H$44=0,H16,IF($C52+H$44>Latest_Third,"",H16+G52)) -> 36 | I52: =IF(I$44=0,I16,IF($C52+I$44>Latest_Third,"",I16+H52)) -> 36 | J52: =IF(J$44=0,J16,IF($C52+J$44>Latest_Third,"",J16+I52)) -> 39 | K52: =IF(K$44=0,K16,IF($C52+K$44>Latest_Third,"",K16+J52)) -> 39 | ... W52: =IF(W$44=0,W16,IF($C52+W$44>Latest_Third,"",W16+V52)) -> 39
A53: =A17 -> 2007 | B53: 2 | C53: 8 | D53: =IF(D$44=0,D17,IF($C53+D$44>Latest_Third,"",D17+C53)) -> 7 | E53: =IF(E$44=0,E17,IF($C53+E$44>Latest_Third,"",E17+D53)) -> 15 | F53: =IF(F$44=0,F17,IF($C53+F$44>Latest_Third,"",F17+E53)) -> 19 | G53: =IF(G$44=0,G17,IF($C53+G$44>Latest_Third,"",G17+F53)) -> 22 | H53: =IF(H$44=0,H17,IF($C53+H$44>Latest_Third,"",H17+G53)) -> 24 | I53: =IF(I$44=0,I17,IF($C53+I$44>Latest_Third,"",I17+H53)) -> 24 | J53: =IF(J$44=0,J17,IF($C53+J$44>Latest_Third,"",J17+I53)) -> 24 | K53: =IF(K$44=0,K17,IF($C53+K$44>Latest_Third,"",K17+J53)) -> 24 | ... W53: =IF(W$44=0,W17,IF($C53+W$44>Latest_Third,"",W17+V53)) -> 25
A54: =A18 -> 2008 | B54: 0 | C54: 9 | D54: =IF(D$44=0,D18,IF($C54+D$44>Latest_Third,"",D18+C54)) -> 13 | E54: =IF(E$44=0,E18,IF($C54+E$44>Latest_Third,"",E18+D54)) -> 24 | F54: =IF(F$44=0,F18,IF($C54+F$44>Latest_Third,"",F18+E54)) -> 29 | G54: =IF(G$44=0,G18,IF($C54+G$44>Latest_Third,"",G18+F54)) -> 34 | H54: =IF(H$44=0,H18,IF($C54+H$44>Latest_Third,"",H18+G54)) -> 35 | I54: =IF(I$44=0,I18,IF($C54+I$44>Latest_Third,"",I18+H54)) -> 37 | J54: =IF(J$44=0,J18,IF($C54+J$44>Latest_Third,"",J18+I54)) -> 37 | K54: =IF(K$44=0,K18,IF($C54+K$44>Latest_Third,"",K18+J54)) -> 37 | ... W54: =IF(W$44=0,W18,IF($C54+W$44>Latest_Third,"",W18+V54)) -> 40
A55: =A19 -> 2008 | B55: 1 | C55: 10 | D55: =IF(D$44=0,D19,IF($C55+D$44>Latest_Third,"",D19+C55)) -> 29 | E55: =IF(E$44=0,E19,IF($C55+E$44>Latest_Third,"",E19+D55)) -> 37 | F55: =IF(F$44=0,F19,IF($C55+F$44>Latest_Third,"",F19+E55)) -> 50 | G55: =IF(G$44=0,G19,IF($C55+G$44>Latest_Third,"",G19+F55)) -> 54 | H55: =IF(H$44=0,H19,IF($C55+H$44>Latest_Third,"",H19+G55)) -> 57 | I55: =IF(I$44=0,I19,IF($C55+I$44>Latest_Third,"",I19+H55)) -> 60 | J55: =IF(J$44=0,J19,IF($C55+J$44>Latest_Third,"",J19+I55)) -> 60 | K55: =IF(K$44=0,K19,IF($C55+K$44>Latest_Third,"",K19+J55)) -> 60 | ... W55: =IF(W$44=0,W19,IF($C55+W$44>Latest_Third,"",W19+V55))
A56: =A20 -> 2008 | B56: 2 | C56: 11 | D56: =IF(D$44=0,D20,IF($C56+D$44>Latest_Third,"",D20+C56)) -> 17 | E56: =IF(E$44=0,E20,IF($C56+E$44>Latest_Third,"",E20+D56)) -> 25 | F56: =IF(F$44=0,F20,IF($C56+F$44>Latest_Third,"",F20+E56)) -> 32 | G56: =IF(G$44=0,G20,IF($C56+G$44>Latest_Third,"",G20+F56)) -> 36 | H56: =IF(H$44=0,H20,IF($C56+H$44>Latest_Third,"",H20+G56)) -> 40 | I56: =IF(I$44=0,I20,IF($C56+I$44>Latest_Third,"",I20+H56)) -> 40 | J56: =IF(J$44=0,J20,IF($C56+J$44>Latest_Third,"",J20+I56)) -> 41 | K56: =IF(K$44=0,K20,IF($C56+K$44>Latest_Third,"",K20+J56)) -> 42 | ... W56: =IF(W$44=0,W20,IF($C56+W$44>Latest_Third,"",W20+V56))
... A73: =A37 -> 2014 | B73: 1 | C73: 28 | D73: =IF(D$44=0,D37,IF($C73+D$44>Latest_Third,"",D37+C73)) -> 19 | E73: =IF(E$44=0,E37,IF($C73+E$44>Latest_Third,"",E37+D73)) | F73: =IF(F$44=0,F37,IF($C73+F$44>Latest_Third,"",F37+E73)) | G73: =IF(G$44=0,G37,IF($C73+G$44>Latest_Third,"",G37+F73)) | H73: =IF(H$44=0,H37,IF($C73+H$44>Latest_Third,"",H37+G73)) | I73: =IF(I$44=0,I37,IF($C73+I$44>Latest_Third,"",I37+H73)) | J73: =IF(J$44=0,J37,IF($C73+J$44>Latest_Third,"",J37+I73)) | K73: =IF(K$44=0,K37,IF($C73+K$44>Latest_Third,"",K37+J73)) | ... W73: =IF(W$44=0,W37,IF($C73+W$44>Latest_Third,"",W37+V73))
W75: Tail factor
C76: Link ratios | D76: =SUM(E45:E74)/SUMIF(E45:E74,">0",D45:D74) -> 1.707401 | E76: =SUM(F45:F74)/SUMIF(F45:F74,">0",E45:E74) -> 1.2417815 | F76: =SUM(G45:G74)/SUMIF(G45:G74,">0",F45:F74) -> 1.1169538 | G76: =SUM(H45:H74)/SUMIF(H45:H74,">0",G45:G74) -> 1.0732127 | H76: =SUM(I45:I74)/SUMIF(I45:I74,">0",H45:H74) -> 1.0413851 | I76: =SUM(J45:J74)/SUMIF(J45:J74,">0",I45:I74) -> 1.0276339 | J76: =SUM(K45:K74)/SUMIF(K45:K74,">0",J45:J74) -> 1.0106667 | K76: =SUM(L45:L74)/SUMIF(L45:L74,">0",K45:K74) -> 1.0102041 | ... V76: =SUM(W45:W74)/SUMIF(W45:W74,">0",V45:V74) -> 1.0030581 | W76: 1
C77: Cumulative link ratios | D77: =D76*E77 -> 2.9190691 | E77: =E76*F77 -> 1.7096564 | F77: =F76*G77 -> 1.3767771 | G77: =G76*H77 -> 1.2326178 | H77: =H76*I77 -> 1.1485307 | I77: =I76*J77 -> 1.1028876 | J77: =J76*K77 -> 1.0732301 | K77: =K76*L77 -> 1.0619031 | ... U77: =U76*V77 -> 1.0030581 | V77: =V76 -> 1.0030581 | W77: 1
A80: 3 - Projected number of claims
D82: 3 - Projected claims
H83: Delay (number of 4-month periods)
A84: Year | B84: Period (in year) | C84: Period | D84: 0 | E84: 1 | F84: 2 | G84: 3 | H84: 4 | I84: 5 | J84: 6 | K84: 7 | L84: 8 | M84: 9 | N84: 10 | O84: 11 | P84: 12 | Q84: 13 | R84: 14 | S84: 15 | T84: 16 | U84: 17 | V84: 18 | W84: 19 | X84: Ultimate
A85: =A45 -> 2005 | B85: 0 | C85: =A85&"-"&B85 -> 2005-0 | D85: =D45 -> 8 | E85: =E45 -> 14 | F85: =F45 -> 18 | G85: =G45 -> 23 | H85: =H45 -> 24 | I85: =I45 -> 25 | J85: =J45 -> 25 | K85: =K45 -> 26 | ... W85: =W45 -> 28 | X85: =W85 -> 28
A86: =A46 -> 2005 | B86: 1 | C86: =A86&"-"&B86 -> 2005-1 | D86: =D46 -> 10 | E86: =E46 -> 14 | F86: =F46 -> 17 | G86: =G46 -> 18 | H86: =H46 -> 18 | I86: =I46 -> 19 | J86: =J46 -> 19 | K86: =K46 -> 19 | ... W86: =W46 -> 20 | X86: =W86 -> 20
A87: =A47 -> 2005 | B87: 2 | C87: =A87&"-"&B87 -> 2005-2 | D87: =D47 -> 18 | E87: =E47 -> 26 | F87: =F47 -> 30 | G87: =G47 -> 33 | H87: =H47 -> 34 | I87: =I47 -> 35 | J87: =J47 -> 35 | K87: =K47 -> 37 | ... W87: =W47 -> 38 | X87: =W87 -> 38
A88: =A48 -> 2006 | B88: 0 | C88: =A88&"-"&B88 -> 2006-0 | D88: =D48 -> 4 | E88: =E48 -> 8 | F88: =F48 -> 11 | G88: =G48 -> 13 | H88: =H48 -> 13 | I88: =I48 -> 14 | J88: =J48 -> 15 | K88: =K48 -> 15 | ... W88: =W48 -> 17 | X88: =W88 -> 17
A89: =A49 -> 2006 | B89: 1 | C89: =A89&"-"&B89 -> 2006-1 | D89: =D49 -> 13 | E89: =E49 -> 21 | F89: =F49 -> 23 | G89: =G49 -> 26 | H89: =H49 -> 27 | I89: =I49 -> 28 | J89: =J49 -> 30 | K89: =K49 -> 30 | ... W89: =W49 -> 35 | X89: =W89 -> 35
A90: =A50 -> 2006 | B90: 2 | C90: =A90&"-"&B90 -> 2006-2 | D90: =D50 -> 9 | E90: =E50 -> 19 | F90: =F50 -> 27 | G90: =G50 -> 28 | H90: =H50 -> 32 | I90: =I50 -> 35 | J90: =J50 -> 36 | K90: =K50 -> 36 | ... W90: =W50 -> 40 | X90: =W90 -> 40
A91: =A51 -> 2007 | B91: 0 | C91: =A91&"-"&B91 -> 2007-0 | D91: =D51 -> 20 | E91: =E51 -> 27 | F91: =F51 -> 32 | G91: =G51 -> 35 | H91: =H51 -> 39 | I91: =I51 -> 40 | J91: =J51 -> 43 | K91: =K51 -> 44 | ... W91: =W51 -> 46 | X91: =W91 -> 46
A92: =A52 -> 2007 | B92: 1 | C92: =A92&"-"&B92 -> 2007-1 | D92: =D52 -> 18 | E92: =E52 -> 26 | F92: =F52 -> 31 | G92: =G52 -> 33 | H92: =H52 -> 36 | I92: =I52 -> 36 | J92: =J52 -> 39 | K92: =K52 -> 39 | ... W92: =W52 -> 39 | X92: =W92 -> 39
A93: =A53 -> 2007 | B93: 2 | C93: =A93&"-"&B93 -> 2007-2 | D93: =D53 -> 7 | E93: =E53 -> 15 | F93: =F53 -> 19 | G93: =G53 -> 22 | H93: =H53 -> 24 | I93: =I53 -> 24 | J93: =J53 -> 24 | K93: =K53 -> 24 | ... W93: =W53 -> 25 | X93: =W93 -> 25 | AR93: =X93*X$77 -> 0
A94: =A54 -> 2008 | B94: 0 | C94: =A94&"-"&B94 -> 2008-0 | D94: =D54 -> 13 | E94: =E54 -> 24 | F94: =F54 -> 29 | G94: =G54 -> 34 | H94: =H54 -> 35 | I94: =I54 -> 37 | J94: =J54 -> 37 | K94: =K54 -> 37 | ... W94: =W54 -> 40 | X94: =W94 -> 40 | AQ94: =W94*W$77 -> 40
A95: =A55 -> 2008 | B95: 1 | C95: =A95&"-"&B95 -> 2008-1 | D95: =D55 -> 29 | E95: =E55 -> 37 | F95: =F55 -> 50 | G95: =G55 -> 54 | H95: =H55 -> 57 | I95: =I55 -> 60 | J95: =J55 -> 60 | K95: =K55 -> 60 | ... W95: =W55 | X95: =V95*V$77 -> 64.195719 | AP95: =V95*V$77 -> 64.195719
A96: =A56 -> 2008 | B96: 2 | C96: =A96&"-"&B96 -> 2008-2 | D96: =D56 -> 17 | E96: =E56 -> 25 | F96: =F56 -> 32 | G96: =G56 -> 36 | H96: =H56 -> 40 | I96: =I56 -> 40 | J96: =J56 -> 41 | K96: =K56 -> 42 | ... W96: =W56 | X96: =U96*U$77 -> 42.12844
A97: =A57 -> 2009 | B97: 0 | C97: =A97&"-"&B97 -> 2009-0 | D97: =D57 -> 29 | E97: =E57 -> 40 | F97: =F57 -> 45 | G97: =G57 -> 49 | H97: =H57 -> 51 | I97: =I57 -> 54 | J97: =J57 -> 54 | K97: =K57 -> 54 | ... W97: =W57 | X97: =T97*T$77 -> 55.168196
A98: =A58 -> 2009 | B98: 1 | C98: =A98&"-"&B98 -> 2009-1 | D98: =D58 -> 33 | E98: =E58 -> 49 | F98: =F58 -> 54 | G98: =G58 -> 61 | H98: =H58 -> 63 | I98: =I58 -> 69 | J98: =J58 -> 70 | K98: =K58 -> 71 | ... W98: =W58 | X98: =S98*S$77 -> 77.235474
A99: =A59 -> 2009 | B99: 2 | C99: =A99&"-"&B99 -> 2009-2 | D99: =D59 -> 26 | E99: =E59 -> 37 | F99: =F59 -> 46 | G99: =G59 -> 48 | H99: =H59 -> 51 | I99: =I59 -> 51 | J99: =J59 -> 56 | K99: =K59 -> 57 | ... W99: =W59 | X99: =R99*R$77 -> 62.189602
A100: =A60 -> 2010 | B100: 0 | C100: =A100&"-"&B100 -> 2010-0 | D100: =D60 -> 26 | E100: =E60 -> 39 | F100: =F60 -> 48 | G100: =G60 -> 53 | H100: =H60 -> 60 | I100: =I60 -> 63 | J100: =J60 -> 64 | K100: =K60 -> 64 | ... W100: =W60 | X100: =Q100*Q$77 -> 66.307589
A101: =A61 -> 2010 | B101: 1 | C101: =A101&"-"&B101 -> 2010-1 | D101: =D61 -> 34 | E101: =E61 -> 58 | F101: =F61 -> 66 | G101: =G61 -> 73 | H101: =H61 -> 78 | I101: =I61 -> 79 | J101: =J61 -> 81 | K101: =K61 -> 82 | ... W101: =W61 | X101: =P101*P$77 -> 86.651234
A102: =A62 -> 2010 | B102: 2 | C102: =A102&"-"&B102 -> 2010-2 | D102: =D62 -> 43 | E102: =E62 -> 70 | F102: =F62 -> 79 | G102: =G62 -> 85 | H102: =H62 -> 92 | I102: =I62 -> 96 | J102: =J62 -> 98 | K102: =K62 -> 99 | ... W102: =W62 | X102: =O102*O$77 -> 104.92275
A103: =A63 -> 2011 | B103: 0 | C103: =A103&"-"&B103 -> 2011-0 | D103: =D63 -> 36 | E103: =E63 -> 53 | F103: =F63 -> 69 | G103: =G63 -> 75 | H103: =H63 -> 79 | I103: =I63 -> 81 | J103: =J63 -> 82 | K103: =K63 -> 82 | ... W103: =W63 | X103: =N103*N$77 -> 88.173158
A104: =A64 -> 2011 | B104: 1 | C104: =A104&"-"&B104 -> 2011-1 | D104: =D64 -> 37 | E104: =E64 -> 57 | F104: =F64 -> 64 | G104: =G64 -> 69 | H104: =H64 -> 72 | I104: =I64 -> 74 | J104: =J64 -> 76 | K104: =K64 -> 76 | ... W104: =W64 | X104: =M104*M$77 -> 79.358199
A105: =A65 -> 2011 | B105: 2 | C105: =A105&"-"&B105 -> 2011-2 | D105: =D65 -> 32 | E105: =E65 -> 55 | F105: =F65 -> 64 | G105: =G65 -> 69 | H105: =H65 -> 75 | I105: =I65 -> 79 | J105: =J65 -> 81 | K105: =K65 -> 84 | ... W105: =W65 | X105: =L105*L$77 -> 90.401207
A106: =A66 -> 2012 | B106: 0 | C106: =A106&"-"&B106 -> 2012-0 | D106: =D66 -> 18 | E106: =E66 -> 34 | F106: =F66 -> 43 | G106: =G66 -> 50 | H106: =H66 -> 54 | I106: =I66 -> 56 | J106: =J66 -> 59 | K106: =K66 -> 59 | ... W106: =W66 | X106: =K106*K$77 -> 62.652284
A107: =A67 -> 2012 | B107: 1 | C107: =A107&"-"&B107 -> 2012-1 | D107: =D67 -> 18 | E107: =E67 -> 36 | F107: =F67 -> 44 | G107: =G67 -> 51 | H107: =H67 -> 58 | I107: =I67 -> 63 | J107: =J67 -> 65 | K107: =K67 | ... W107: =W67 | X107: =J107*J$77 -> 69.759956
A108: =A68 -> 2012 | B108: 2 | C108: =A108&"-"&B108 -> 2012-2 | D108: =D68 -> 17 | E108: =E68 -> 43 | F108: =F68 -> 54 | G108: =G68 -> 63 | H108: =H68 -> 72 | I108: =I68 -> 75 | J108: =J68 | K108: =K68 | ... W108: =W68 | X108: =I108*I$77 -> 82.716568
A109: =A69 -> 2013 | B109: 0 | C109: =A109&"-"&B109 -> 2013-0 | D109: =D69 -> 16 | E109: =E69 -> 29 | F109: =F69 -> 50 | G109: =G69 -> 60 | H109: =H69 -> 62 | I109: =I69 | J109: =J69 | K109: =K69 | ... W109: =W69 | X109: =H109*H$77 -> 71.208905
A110: =A70 -> 2013 | B110: 1 | C110: =A110&"-"&B110 -> 2013-1 | D110: =D70 -> 12 | E110: =E70 -> 37 | F110: =F70 -> 58 | G110: =G70 -> 71 | H110: =H70 | I110: =I70 | J110: =J70 | K110: =K70 | ... W110: =W70 | X110: =G110*G$77 -> 87.515865
A111: =A71 -> 2013 | B111: 2 | C111: =A111&"-"&B111 -> 2013-2 | D111: =D71 -> 15 | E111: =E71 -> 50 | F111: =F71 -> 68 | G111: =G71 | H111: =H71 | I111: =I71 | J111: =J71 | K111: =K71 | ... W111: =W71 | X111: =F111*F$77 -> 93.620843
A112: =A72 -> 2014 | B112: 0 | C112: =A112&"-"&B112 -> 2014-0 | D112: =D72 -> 23 | E112: =E72 -> 49 | F112: =F72 | G112: =G72 | H112: =H72 | I112: =I72 | J112: =J72 | K112: =K72 | ... W112: =W72 | X112: =E112*E$77 -> 83.773164
A113: =A73 -> 2014 | B113: 1 | C113: =A113&"-"&B113 -> 2014-1 | D113: =D73 -> 19 | E113: =E73 | F113: =F73 | G113: =G73 | H113: =H73 | I113: =I73 | J113: =J73 | K113: =K73 | ... W113: =W73 | X113: =D113*D$77 -> 55.462313
A117: 4 - Annualised ultimates | D117: Months available in latest year | E117: 8
B120: Policy year | C120: Reported | D120: Ultimate | E120: Annualised
B121: 2005 | C121: =SUMIF($A$9:$A$37,"="&$B121,$AJ$9:$AJ$37) -> 86 | D121: =SUMIF($A$9:$A$37,"="&$B121,$X$85:$X$113) -> 86 | E121: =IF(B121=Latest_Year,D121*12/$E$117,D121) -> 86
B122: =B121+1 -> 2006 | C122: =SUMIF($A$9:$A$37,"="&$B122,$AJ$9:$AJ$37) -> 92 | D122: =SUMIF($A$9:$A$37,"="&$B122,$X$85:$X$113) -> 92 | E122: =IF(B122=Latest_Year,D122*12/$E$117,D122) -> 92
B123: =B122+1 -> 2007 | C123: =SUMIF($A$9:$A$37,"="&$B123,$AJ$9:$AJ$37) -> 110 | D123: =SUMIF($A$9:$A$37,"="&$B123,$X$85:$X$113) -> 110 | E123: =IF(B123=Latest_Year,D123*12/$E$117,D123) -> 110
B124: =B123+1 -> 2008 | C124: =SUMIF($A$9:$A$37,"="&$B124,$AJ$9:$AJ$37) -> 146 | D124: =SUMIF($A$9:$A$37,"="&$B124,$X$85:$X$113) -> 146.32416 | E124: =IF(B124=Latest_Year,D124*12/$E$117,D124) -> 146.32416
B125: =B124+1 -> 2009 | C125: =SUMIF($A$9:$A$37,"="&$B125,$AJ$9:$AJ$37) -> 194 | D125: =SUMIF($A$9:$A$37,"="&$B125,$X$85:$X$113) -> 194.59327 | E125: =IF(B125=Latest_Year,D125*12/$E$117,D125) -> 194.59327
B126: =B125+1 -> 2010 | C126: =SUMIF($A$9:$A$37,"="&$B126,$AJ$9:$AJ$37) -> 256 | D126: =SUMIF($A$9:$A$37,"="&$B126,$X$85:$X$113) -> 257.88157 | E126: =IF(B126=Latest_Year,D126*12/$E$117,D126) -> 257.88157
B127: =B126+1 -> 2011 | C127: =SUMIF($A$9:$A$37,"="&$B127,$AJ$9:$AJ$37) -> 250 | D127: =SUMIF($A$9:$A$37,"="&$B127,$X$85:$X$113) -> 257.93256 | E127: =IF(B127=Latest_Year,D127*12/$E$117,D127) -> 257.93256
B128: =B127+1 -> 2012 | C128: =SUMIF($A$9:$A$37,"="&$B128,$AJ$9:$AJ$37) -> 199 | D128: =SUMIF($A$9:$A$37,"="&$B128,$X$85:$X$113) -> 215.12881 | E128: =IF(B128=Latest_Year,D128*12/$E$117,D128) -> 215.12881
B129: =B128+1 -> 2013 | C129: =SUMIF($A$9:$A$37,"="&$B129,$AJ$9:$AJ$37) -> 201 | D129: =SUMIF($A$9:$A$37,"="&$B129,$X$85:$X$113) -> 252.34561 | E129: =IF(B129=Latest_Year,D129*12/$E$117,D129) -> 252.34561
A130: (first 8 months) | B130: =B129+1 -> 2014 | C130: =SUMIF($A$9:$A$37,"="&$B130,$AJ$9:$AJ$37) -> 68 | D130: =SUMIF($A$9:$A$37,"="&$B130,$X$85:$X$113) -> 139.23548 | E130: =IF(B130=Latest_Year,D130*12/$E$117,D130) -> 208.85322

Sheet 5. Projection - Method 4
A2: METHOD 4 - SHIFT POLICY YEARS | E2: 保单年度(移位)”是指从每年12月1日起至次年11月30日止的12个月期间
A4: 1 - Original table
G6: Delay (years)
B7: Shifted policy year | C7: 0 | D7: 1 | E7: 2 | F7: 3 | G7: 4 | H7: 5 | I7: 6 | J7: 7 | K7: 8 | L7: 9
B8: =Earliest_Year_Shifted -> 2004 | C8: =IF($B8+C$7>Latest_Year_Shifted,"",SUMIFS(Table1[Non-zero? (1=Yes)],Table1[Policy Year (shifted)],"="&'5. Projection - Method 4'!$B8,Table1[Delay (shifted)],"="&'5. Projection - Method 4'!C$7)) -> 24 | D8: =IF($B8+D$7>Latest_Year_Shifted,"",SUMIFS(Table1[Non-zero? (1=Yes)],Table1[Policy Year (shifted)],"="&'5. Projection - Method 4'!$B8,Table1[Delay (shifted)],"="&'5. Projection - Method 4'!D$7)) -> 18 | E8: =IF($B8+E$7>Latest_Year_Shifted,"",SUMIFS(Table1[Non-zero? (1=Yes)],Table1[Policy Year (shifted)],"="&'5. Projection - Method 4'!$B8,Table1[Delay (shifted)],"="&'5. Projection - Method 4'!E$7)) -> 3 | F8: =IF($B8+F$7>Latest_Year_Shifted,"",SUMIFS(Table1[Non-zero? (1=Yes)],Table1[Policy Year (shifted)],"="&'5. Projection - Method 4'!$B8,Table1[Delay (shifted)],"="&'5. Projection - Method 4'!F$7)) -> 2 | G8: =IF($B8+G$7>Latest_Year_Shifted,"",SUMIFS(Table1[Non-zero? (1=Yes)],Table1[Policy Year (shifted)],"="&'5. Projection - Method 4'!$B8,Table1[Delay (shifted)],"="&'5. Projection - Method 4'!G$7)) -> 1 | H8: =IF($B8+H$7>Latest_Year_Shifted,"",SUMIFS(Table1[Non-zero? (1=Yes)],Table1[Policy Year (shifted)],"="&'5. Projection - Method 4'!$B8,Table1[Delay (shifted)],"="&'5. Projection - Method 4'!H$7)) -> 0 | I8: =IF($B8+I$7>Latest_Year_Shifted,"",SUMIFS(Table1[Non-zero? (1=Yes)],Table1[Policy Year (shifted)],"="&'5. Projection - Method 4'!$B8,Table1[Delay (shifted)],"="&'5. Projection - Method 4'!I$7)) -> 0 | J8: =IF($B8+J$7>Latest_Year_Shifted,"",SUMIFS(Table1[Non-zero? (1=Yes)],Table1[Policy Year (shifted)],"="&'5. Projection - Method 4'!$B8,Table1[Delay (shifted)],"="&'5. Projection - Method 4'!J$7)) -> 0 | ... L8: =IF($B8+L$7>Latest_Year_Shifted,"",SUMIFS(Table1[Non-zero? (1=Yes)],Table1[Policy Year (shifted)],"="&'5. Projection - Method 4'!$B8,Table1[Delay (shifted)],"="&'5. Projection - Method 4'!L$7)) -> 0
B9: =B8+1 -> 2005 | C9: =IF($B9+C$7>Latest_Year_Shifted,"",SUMIFS(Table1[Non-zero? (1=Yes)],Table1[Policy Year (shifted)],"="&'5. Projection - Method 4'!$B9,Table1[Delay (shifted)],"="&'5. Projection - Method 4'!C$7)) -> 51 | D9: =IF($B9+D$7>Latest_Year_Shifted,"",SUMIFS(Table1[Non-zero? (1=Yes)],Table1[Policy Year (shifted)],"="&'5. Projection - Method 4'!$B9,Table1[Delay (shifted)],"="&'5. Projection - Method 4'!D$7)) -> 23 | E9: =IF($B9+E$7>Latest_Year_Shifted,"",SUMIFS(Table1[Non-zero? (1=Yes)],Table1[Policy Year (shifted)],"="&'5. Projection - Method 4'!$B9,Table1[Delay (shifted)],"="&'5. Projection - Method 4'!E$7)) -> 8 | F9: =IF($B9+F$7>Latest_Year_Shifted,"",SUMIFS(Table1[Non-zero? (1=Yes)],Table1[Policy Year (shifted)],"="&'5. Projection - Method 4'!$B9,Table1[Delay (shifted)],"="&'5. Projection - Method 4'!F$7)) -> 6 | G9: =IF($B9+G$7>Latest_Year_Shifted,"",SUMIFS(Table1[Non-zero? (1=Yes)],Table1[Policy Year (shifted)],"="&'5. Projection - Method 4'!$B9,Table1[Delay (shifted)],"="&'5. Projection - Method 4'!G$7)) -> 2 | H9: =IF($B9+H$7>Latest_Year_Shifted,"",SUMIFS(Table1[Non-zero? (1=Yes)],Table1[Policy Year (shifted)],"="&'5. Projection - Method 4'!$B9,Table1[Delay (shifted)],"="&'5. Projection - Method 4'!H$7)) -> 0 | I9: =IF($B9+I$7>Latest_Year_Shifted,"",SUMIFS(Table1[Non-zero? (1=Yes)],Table1[Policy Year (shifted)],"="&'5. Projection - Method 4'!$B9,Table1[Delay (shifted)],"="&'5. Projection - Method 4'!I$7)) -> 0 | J9: =IF($B9+J$7>Latest_Year_Shifted,"",SUMIFS(Table1[Non-zero? (1=Yes)],Table1[Policy Year (shifted)],"="&'5. Projection - Method 4'!$B9,Table1[Delay (shifted)],"="&'5. Projection - Method 4'!J$7)) -> 0 | ... L9: =IF($B9+L$7>Latest_Year_Shifted,"",SUMIFS(Table1[Non-zero? (1=Yes)],Table1[Policy Year (shifted)],"="&'5. Projection - Method 4'!$B9,Table1[Delay (shifted)],"="&'5. Projection - Method 4'!L$7))
B10: =B9+1 -> 2006 | C10: =IF($B10+C$7>Latest_Year_Shifted,"",SUMIFS(Table1[Non-zero? (1=Yes)],Table1[Policy Year (shifted)],"="&'5. Projection - Method 4'!$B10,Table1[Delay (shifted)],"="&'5. Projection - Method 4'!C$7)) -> 72 | D10: =IF($B10+D$7>Latest_Year_Shifted,"",SUMIFS(Table1[Non-zero? (1=Yes)],Table1[Policy Year (shifted)],"="&'5. Projection - Method 4'!$B10,Table1[Delay (shifted)],"="&'5. Projection - Method 4'!D$7)) -> 35 | E10: =IF($B10+E$7>Latest_Year_Shifted,"",SUMIFS(Table1[Non-zero? (1=Yes)],Table1[Policy Year (shifted)],"="&'5. Projection - Method 4'!$B10,Table1[Delay (shifted)],"="&'5. Projection - Method 4'!E$7)) -> 12 | F10: =IF($B10+F$7>Latest_Year_Shifted,"",SUMIFS(Table1[Non-zero? (1=Yes)],Table1[Policy Year (shifted)],"="&'5. Projection - Method 4'!$B10,Table1[Delay (shifted)],"="&'5. Projection - Method 4'!F$7)) -> 6 | G10: =IF($B10+G$7>Latest_Year_Shifted,"",SUMIFS(Table1[Non-zero? (1=Yes)],Table1[Policy Year (shifted)],"="&'5. Projection - Method 4'!$B10,Table1[Delay (shifted)],"="&'5. Projection - Method 4'!G$7)) -> 0 | H10: =IF($B10+H$7>Latest_Year_Shifted,"",SUMIFS(Table1[Non-zero? (1=Yes)],Table1[Policy Year (shifted)],"="&'5. Projection - Method 4'!$B10,Table1[Delay (shifted)],"="&'5. Projection - Method 4'!H$7)) -> 0 | I10: =IF($B10+I$7>Latest_Year_Shifted,"",SUMIFS(Table1[Non-zero? (1=Yes)],Table1[Policy Year (shifted)],"="&'5. Projection - Method 4'!$B10,Table1[Delay (shifted)],"="&'5. Projection - Method 4'!I$7)) -> 0 | J10: =IF($B10+J$7>Latest_Year_Shifted,"",SUMIFS(Table1[Non-zero? (1=Yes)],Table1[Policy Year (shifted)],"="&'5. Projection - Method 4'!$B10,Table1[Delay (shifted)],"="&'5. Projection - Method 4'!J$7)) -> 0 | ... L10: =IF($B10+L$7>Latest_Year_Shifted,"",SUMIFS(Table1[Non-zero? (1=Yes)],Table1[Policy Year (shifted)],"="&'5. Projection - Method 4'!$B10,Table1[Delay (shifted)],"="&'5. Projection - Method 4'!L$7))
B11: =B10+1 -> 2007 | C11: =IF($B11+C$7>Latest_Year_Shifted,"",SUMIFS(Table1[Non-zero? (1=Yes)],Table1[Policy Year (shifted)],"="&'5. Projection - Method 4'!$B11,Table1[Delay (shifted)],"="&'5. Projection - Method 4'!C$7)) -> 72 | D11: =IF($B11+D$7>Latest_Year_Shifted,"",SUMIFS(Table1[Non-zero? (1=Yes)],Table1[Policy Year (shifted)],"="&'5. Projection - Method 4'!$B11,Table1[Delay (shifted)],"="&'5. Projection - Method 4'!D$7)) -> 41 | E11: =IF($B11+E$7>Latest_Year_Shifted,"",SUMIFS(Table1[Non-zero? (1=Yes)],Table1[Policy Year (shifted)],"="&'5. Projection - Method 4'!$B11,Table1[Delay (shifted)],"="&'5. Projection - Method 4'!E$7)) -> 8 | F11: =IF($B11+F$7>Latest_Year_Shifted,"",SUMIFS(Table1[Non-zero? (1=Yes)],Table1[Policy Year (shifted)],"="&'5. Projection - Method 4'!$B11,Table1[Delay (shifted)],"="&'5. Projection - Method 4'!F$7)) -> 4 | G11: =IF($B11+G$7>Latest_Year_Shifted,"",SUMIFS(Table1[Non-zero? (1=Yes)],Table1[Policy Year (shifted)],"="&'5. Projection - Method 4'!$B11,Table1[Delay (shifted)],"="&'5. Projection - Method 4'!G$7)) -> 3 | H11: =IF($B11+H$7>Latest_Year_Shifted,"",SUMIFS(Table1[Non-zero? (1=Yes)],Table1[Policy Year (shifted)],"="&'5. Projection - Method 4'!$B11,Table1[Delay (shifted)],"="&'5. Projection - Method 4'!H$7)) -> 0 | I11: =IF($B11+I$7>Latest_Year_Shifted,"",SUMIFS(Table1[Non-zero? (1=Yes)],Table1[Policy Year (shifted)],"="&'5. Projection - Method 4'!$B11,Table1[Delay (shifted)],"="&'5. Projection - Method 4'!I$7)) -> 1 | J11: =IF($B11+J$7>Latest_Year_Shifted,"",SUMIFS(Table1[Non-zero? (1=Yes)],Table1[Policy Year (shifted)],"="&'5. Projection - Method 4'!$B11,Table1[Delay (shifted)],"="&'5. Projection - Method 4'!J$7)) | ... L11: =IF($B11+L$7>Latest_Year_Shifted,"",SUMIFS(Table1[Non-zero? (1=Yes)],Table1[Policy Year (shifted)],"="&'5. Projection - Method 4'!$B11,Table1[Delay (shifted)],"="&'5. Projection - Method 4'!L$7))
B12: =B11+1 -> 2008 | C12: =IF($B12+C$7>Latest_Year_Shifted,"",SUMIFS(Table1[Non-zero? (1=Yes)],Table1[Policy Year (shifted)],"="&'5. Projection - Method 4'!$B12,Table1[Delay (shifted)],"="&'5. Projection - Method 4'!C$7)) -> 105 | D12: =IF($B12+D$7>Latest_Year_Shifted,"",SUMIFS(Table1[Non-zero? (1=Yes)],Table1[Policy Year (shifted)],"="&'5. Projection - Method 4'!$B12,Table1[Delay (shifted)],"="&'5. Projection - Method 4'!D$7)) -> 47 | E12: =IF($B12+E$7>Latest_Year_Shifted,"",SUMIFS(Table1[Non-zero? (1=Yes)],Table1[Policy Year (shifted)],"="&'5. Projection - Method 4'!$B12,Table1[Delay (shifted)],"="&'5. Projection - Method 4'!E$7)) -> 14 | F12: =IF($B12+F$7>Latest_Year_Shifted,"",SUMIFS(Table1[Non-zero? (1=Yes)],Table1[Policy Year (shifted)],"="&'5. Projection - Method 4'!$B12,Table1[Delay (shifted)],"="&'5. Projection - Method 4'!F$7)) -> 4 | G12: =IF($B12+G$7>Latest_Year_Shifted,"",SUMIFS(Table1[Non-zero? (1=Yes)],Table1[Policy Year (shifted)],"="&'5. Projection - Method 4'!$B12,Table1[Delay (shifted)],"="&'5. Projection - Method 4'!G$7)) -> 4 | H12: =IF($B12+H$7>Latest_Year_Shifted,"",SUMIFS(Table1[Non-zero? (1=Yes)],Table1[Policy Year (shifted)],"="&'5. Projection - Method 4'!$B12,Table1[Delay (shifted)],"="&'5. Projection - Method 4'!H$7)) -> 0 | I12: =IF($B12+I$7>Latest_Year_Shifted,"",SUMIFS(Table1[Non-zero? (1=Yes)],Table1[Policy Year (shifted)],"="&'5. Projection - Method 4'!$B12,Table1[Delay (shifted)],"="&'5. Projection - Method 4'!I$7)) | J12: =IF($B12+J$7>Latest_Year_Shifted,"",SUMIFS(Table1[Non-zero? (1=Yes)],Table1[Policy Year (shifted)],"="&'5. Projection - Method 4'!$B12,Table1[Delay (shifted)],"="&'5. Projection - Method 4'!J$7)) | ... L12: =IF($B12+L$7>Latest_Year_Shifted,"",SUMIFS(Table1[Non-zero? (1=Yes)],Table1[Policy Year (shifted)],"="&'5. Projection - Method 4'!$B12,Table1[Delay (shifted)],"="&'5. Projection - Method 4'!L$7))
B13: =B12+1 -> 2009 | C13: =IF($B13+C$7>Latest_Year_Shifted,"",SUMIFS(Table1[Non-zero? (1=Yes)],Table1[Policy Year (shifted)],"="&'5. Projection - Method 4'!$B13,Table1[Delay (shifted)],"="&'5. Projection - Method 4'!C$7)) -> 119 | D13: =IF($B13+D$7>Latest_Year_Shifted,"",SUMIFS(Table1[Non-zero? (1=Yes)],Table1[Policy Year (shifted)],"="&'5. Projection - Method 4'!$B13,Table1[Delay (shifted)],"="&'5. Projection - Method 4'!D$7)) -> 65 | E13: =IF($B13+E$7>Latest_Year_Shifted,"",SUMIFS(Table1[Non-zero? (1=Yes)],Table1[Policy Year (shifted)],"="&'5. Projection - Method 4'!$B13,Table1[Delay (shifted)],"="&'5. Projection - Method 4'!E$7)) -> 19 | F13: =IF($B13+F$7>Latest_Year_Shifted,"",SUMIFS(Table1[Non-zero? (1=Yes)],Table1[Policy Year (shifted)],"="&'5. Projection - Method 4'!$B13,Table1[Delay (shifted)],"="&'5. Projection - Method 4'!F$7)) -> 7 | G13: =IF($B13+G$7>Latest_Year_Shifted,"",SUMIFS(Table1[Non-zero? (1=Yes)],Table1[Policy Year (shifted)],"="&'5. Projection - Method 4'!$B13,Table1[Delay (shifted)],"="&'5. Projection - Method 4'!G$7)) -> 4 | H13: =IF($B13+H$7>Latest_Year_Shifted,"",SUMIFS(Table1[Non-zero? (1=Yes)],Table1[Policy Year (shifted)],"="&'5. Projection - Method 4'!$B13,Table1[Delay (shifted)],"="&'5. Projection - Method 4'!H$7)) | I13: =IF($B13+I$7>Latest_Year_Shifted,"",SUMIFS(Table1[Non-zero? (1=Yes)],Table1[Policy Year (shifted)],"="&'5. Projection - Method 4'!$B13,Table1[Delay (shifted)],"="&'5. Projection - Method 4'!I$7)) | J13: =IF($B13+J$7>Latest_Year_Shifted,"",SUMIFS(Table1[Non-zero? (1=Yes)],Table1[Policy Year (shifted)],"="&'5. Projection - Method 4'!$B13,Table1[Delay (shifted)],"="&'5. Projection - Method 4'!J$7)) | ... L13: =IF($B13+L$7>Latest_Year_Shifted,"",SUMIFS(Table1[Non-zero? (1=Yes)],Table1[Policy Year (shifted)],"="&'5. Projection - Method 4'!$B13,Table1[Delay (shifted)],"="&'5. Projection - Method 4'!L$7))
B14: =B13+1 -> 2010 | C14: =IF($B14+C$7>Latest_Year_Shifted,"",SUMIFS(Table1[Non-zero? (1=Yes)],Table1[Policy Year (shifted)],"="&'5. Projection - Method 4'!$B14,Table1[Delay (shifted)],"="&'5. Projection - Method 4'!C$7)) -> 169 | D14: =IF($B14+D$7>Latest_Year_Shifted,"",SUMIFS(Table1[Non-zero? (1=Yes)],Table1[Policy Year (shifted)],"="&'5. Projection - Method 4'!$B14,Table1[Delay (shifted)],"="&'5. Projection - Method 4'!D$7)) -> 75 | E14: =IF($B14+E$7>Latest_Year_Shifted,"",SUMIFS(Table1[Non-zero? (1=Yes)],Table1[Policy Year (shifted)],"="&'5. Projection - Method 4'!$B14,Table1[Delay (shifted)],"="&'5. Projection - Method 4'!E$7)) -> 13 | F14: =IF($B14+F$7>Latest_Year_Shifted,"",SUMIFS(Table1[Non-zero? (1=Yes)],Table1[Policy Year (shifted)],"="&'5. Projection - Method 4'!$B14,Table1[Delay (shifted)],"="&'5. Projection - Method 4'!F$7)) -> 11 | G14: =IF($B14+G$7>Latest_Year_Shifted,"",SUMIFS(Table1[Non-zero? (1=Yes)],Table1[Policy Year (shifted)],"="&'5. Projection - Method 4'!$B14,Table1[Delay (shifted)],"="&'5. Projection - Method 4'!G$7)) | H14: =IF($B14+H$7>Latest_Year_Shifted,"",SUMIFS(Table1[Non-zero? (1=Yes)],Table1[Policy Year (shifted)],"="&'5. Projection - Method 4'!$B14,Table1[Delay (shifted)],"="&'5. Projection - Method 4'!H$7)) | I14: =IF($B14+I$7>Latest_Year_Shifted,"",SUMIFS(Table1[Non-zero? (1=Yes)],Table1[Policy Year (shifted)],"="&'5. Projection - Method 4'!$B14,Table1[Delay (shifted)],"="&'5. Projection - Method 4'!I$7)) | J14: =IF($B14+J$7>Latest_Year_Shifted,"",SUMIFS(Table1[Non-zero? (1=Yes)],Table1[Policy Year (shifted)],"="&'5. Projection - Method 4'!$B14,Table1[Delay (shifted)],"="&'5. Projection - Method 4'!J$7)) | ... L14: =IF($B14+L$7>Latest_Year_Shifted,"",SUMIFS(Table1[Non-zero? (1=Yes)],Table1[Policy Year (shifted)],"="&'5. Projection - Method 4'!$B14,Table1[Delay (shifted)],"="&'5. Projection - Method 4'!L$7))
B15: =B14+1 -> 2011 | C15: =IF($B15+C$7>Latest_Year_Shifted,"",SUMIFS(Table1[Non-zero? (1=Yes)],Table1[Policy Year (shifted)],"="&'5. Projection - Method 4'!$B15,Table1[Delay (shifted)],"="&'5. Projection - Method 4'!C$7)) -> 116 | D15: =IF($B15+D$7>Latest_Year_Shifted,"",SUMIFS(Table1[Non-zero? (1=Yes)],Table1[Policy Year (shifted)],"="&'5. Projection - Method 4'!$B15,Table1[Delay (shifted)],"="&'5. Projection - Method 4'!D$7)) -> 68 | E15: =IF($B15+E$7>Latest_Year_Shifted,"",SUMIFS(Table1[Non-zero? (1=Yes)],Table1[Policy Year (shifted)],"="&'5. Projection - Method 4'!$B15,Table1[Delay (shifted)],"="&'5. Projection - Method 4'!E$7)) -> 26 | F15: =IF($B15+F$7>Latest_Year_Shifted,"",SUMIFS(Table1[Non-zero? (1=Yes)],Table1[Policy Year (shifted)],"="&'5. Projection - Method 4'!$B15,Table1[Delay (shifted)],"="&'5. Projection - Method 4'!F$7)) | G15: =IF($B15+G$7>Latest_Year_Shifted,"",SUMIFS(Table1[Non-zero? (1=Yes)],Table1[Policy Year (shifted)],"="&'5. Projection - Method 4'!$B15,Table1[Delay (shifted)],"="&'5. Projection - Method 4'!G$7)) | H15: =IF($B15+H$7>Latest_Year_Shifted,"",SUMIFS(Table1[Non-zero? (1=Yes)],Table1[Policy Year (shifted)],"="&'5. Projection - Method 4'!$B15,Table1[Delay (shifted)],"="&'5. Projection - Method 4'!H$7)) | I15: =IF($B15+I$7>Latest_Year_Shifted,"",SUMIFS(Table1[Non-zero? (1=Yes)],Table1[Policy Year (shifted)],"="&'5. Projection - Method 4'!$B15,Table1[Delay (shifted)],"="&'5. Projection - Method 4'!I$7)) | J15: =IF($B15+J$7>Latest_Year_Shifted,"",SUMIFS(Table1[Non-zero? (1=Yes)],Table1[Policy Year (shifted)],"="&'5. Projection - Method 4'!$B15,Table1[Delay (shifted)],"="&'5. Projection - Method 4'!J$7)) | ... L15: =IF($B15+L$7>Latest_Year_Shifted,"",SUMIFS(Table1[Non-zero? (1=Yes)],Table1[Policy Year (shifted)],"="&'5. Projection - Method 4'!$B15,Table1[Delay (shifted)],"="&'5. Projection - Method 4'!L$7))
B16: =B15+1 -> 2012 | C16: =IF($B16+C$7>Latest_Year_Shifted,"",SUMIFS(Table1[Non-zero? (1=Yes)],Table1[Policy Year (shifted)],"="&'5. Projection - Method 4'!$B16,Table1[Delay (shifted)],"="&'5. Projection - Method 4'!C$7)) -> 95 | D16: =IF($B16+D$7>Latest_Year_Shifted,"",SUMIFS(Table1[Non-zero? (1=Yes)],Table1[Policy Year (shifted)],"="&'5. Projection - Method 4'!$B16,Table1[Delay (shifted)],"="&'5. Projection - Method 4'!D$7)) -> 113 | E16: =IF($B16+E$7>Latest_Year_Shifted,"",SUMIFS(Table1[Non-zero? (1=Yes)],Table1[Policy Year (shifted)],"="&'5. Projection - Method 4'!$B16,Table1[Delay (shifted)],"="&'5. Projection - Method 4'!E$7)) | F16: =IF($B16+F$7>Latest_Year_Shifted,"",SUMIFS(Table1[Non-zero? (1=Yes)],Table1[Policy Year (shifted)],"="&'5. Projection - Method 4'!$B16,Table1[Delay (shifted)],"="&'5. Projection - Method 4'!F$7)) | G16: =IF($B16+G$7>Latest_Year_Shifted,"",SUMIFS(Table1[Non-zero? (1=Yes)],Table1[Policy Year (shifted)],"="&'5. Projection - Method 4'!$B16,Table1[Delay (shifted)],"="&'5. Projection - Method 4'!G$7)) | H16: =IF($B16+H$7>Latest_Year_Shifted,"",SUMIFS(Table1[Non-zero? (1=Yes)],Table1[Policy Year (shifted)],"="&'5. Projection - Method 4'!$B16,Table1[Delay (shifted)],"="&'5. Projection - Method 4'!H$7)) | I16: =IF($B16+I$7>Latest_Year_Shifted,"",SUMIFS(Table1[Non-zero? (1=Yes)],Table1[Policy Year (shifted)],"="&'5. Projection - Method 4'!$B16,Table1[Delay (shifted)],"="&'5. Projection - Method 4'!I$7)) | J16: =IF($B16+J$7>Latest_Year_Shifted,"",SUMIFS(Table1[Non-zero? (1=Yes)],Table1[Policy Year (shifted)],"="&'5. Projection - Method 4'!$B16,Table1[Delay (shifted)],"="&'5. Projection - Method 4'!J$7)) | ... L16: =IF($B16+L$7>Latest_Year_Shifted,"",SUMIFS(Table1[Non-zero? (1=Yes)],Table1[Policy Year (shifted)],"="&'5. Projection - Method 4'!$B16,Table1[Delay (shifted)],"="&'5. Projection - Method 4'!L$7))
B17: =B16+1 -> 2013 | C17: =IF($B17+C$7>Latest_Year_Shifted,"",SUMIFS(Table1[Non-zero? (1=Yes)],Table1[Policy Year (shifted)],"="&'5. Projection - Method 4'!$B17,Table1[Delay (shifted)],"="&'5. Projection - Method 4'!C$7)) -> 136 | D17: =IF($B17+D$7>Latest_Year_Shifted,"",SUMIFS(Table1[Non-zero? (1=Yes)],Table1[Policy Year (shifted)],"="&'5. Projection - Method 4'!$B17,Table1[Delay (shifted)],"="&'5. Projection - Method 4'!D$7)) | E17: =IF($B17+E$7>Latest_Year_Shifted,"",SUMIFS(Table1[Non-zero? (1=Yes)],Table1[Policy Year (shifted)],"="&'5. Projection - Method 4'!$B17,Table1[Delay (shifted)],"="&'5. Projection - Method 4'!E$7)) | F17: =IF($B17+F$7>Latest_Year_Shifted,"",SUMIFS(Table1[Non-zero? (1=Yes)],Table1[Policy Year (shifted)],"="&'5. Projection - Method 4'!$B17,Table1[Delay (shifted)],"="&'5. Projection - Method 4'!F$7)) | G17: =IF($B17+G$7>Latest_Year_Shifted,"",SUMIFS(Table1[Non-zero? (1=Yes)],Table1[Policy Year (shifted)],"="&'5. Projection - Method 4'!$B17,Table1[Delay (shifted)],"="&'5. Projection - Method 4'!G$7)) | H17: =IF($B17+H$7>Latest_Year_Shifted,"",SUMIFS(Table1[Non-zero? (1=Yes)],Table1[Policy Year (shifted)],"="&'5. Projection - Method 4'!$B17,Table1[Delay (shifted)],"="&'5. Projection - Method 4'!H$7)) | I17: =IF($B17+I$7>Latest_Year_Shifted,"",SUMIFS(Table1[Non-zero? (1=Yes)],Table1[Policy Year (shifted)],"="&'5. Projection - Method 4'!$B17,Table1[Delay (shifted)],"="&'5. Projection - Method 4'!I$7)) | J17: =IF($B17+J$7>Latest_Year_Shifted,"",SUMIFS(Table1[Non-zero? (1=Yes)],Table1[Policy Year (shifted)],"="&'5. Projection - Method 4'!$B17,Table1[Delay (shifted)],"="&'5. Projection - Method 4'!J$7)) | ... L17: =IF($B17+L$7>Latest_Year_Shifted,"",SUMIFS(Table1[Non-zero? (1=Yes)],Table1[Policy Year (shifted)],"="&'5. Projection - Method 4'!$B17,Table1[Delay (shifted)],"="&'5. Projection - Method 4'!L$7))
A20: 2 - Cumulative
G22: Delay (years)
A23: Shifted policy year | C23: 0 | D23: 1 | E23: 2 | F23: 3 | G23: 4 | H23: 5 | I23: 6 | J23: 7 | K23: 8 | L23: 9
A24: =B24 & "/" &B24+1 -> 2004/2005 | B24: =B8 -> 2004 | C24: =C8 -> 24 | D24: =IF($B24+D$23>Latest_Year_Shifted,"",D8+C24) -> 42 | E24: =IF($B24+E$23>Latest_Year_Shifted,"",E8+D24) -> 45 | F24: =IF($B24+F$23>Latest_Year_Shifted,"",F8+E24) -> 47 | G24: =IF($B24+G$23>Latest_Year_Shifted,"",G8+F24) -> 48 | H24: =IF($B24+H$23>Latest_Year_Shifted,"",H8+G24) -> 48 | I24: =IF($B24+I$23>Latest_Year_Shifted,"",I8+H24) -> 48 | J24: =IF($B24+J$23>Latest_Year_Shifted,"",J8+I24) -> 48 | K24: =IF($B24+K$23>Latest_Year_Shifted,"",K8+J24) -> 48 | L24: =IF($B24+L$23>Latest_Year_Shifted,"",L8+K24) -> 48
A25: =B25 & "/" &B25+1 -> 2005/2006 | B25: =B9 -> 2005 | C25: =C9 -> 51 | D25: =IF($B25+D$23>Latest_Year_Shifted,"",D9+C25) -> 74 | E25: =IF($B25+E$23>Latest_Year_Shifted,"",E9+D25) -> 82 | F25: =IF($B25+F$23>Latest_Year_Shifted,"",F9+E25) -> 88 | G25: =IF($B25+G$23>Latest_Year_Shifted,"",G9+F25) -> 90 | H25: =IF($B25+H$23>Latest_Year_Shifted,"",H9+G25) -> 90 | I25: =IF($B25+I$23>Latest_Year_Shifted,"",I9+H25) -> 90 | J25: =IF($B25+J$23>Latest_Year_Shifted,"",J9+I25) -> 90 | K25: =IF($B25+K$23>Latest_Year_Shifted,"",K9+J25) -> 90 | L25: =IF($B25+L$23>Latest_Year_Shifted,"",L9+K25)
A26: =B26 & "/" &B26+1 -> 2006/2007 | B26: =B10 -> 2006 | C26: =C10 -> 72 | D26: =IF($B26+D$23>Latest_Year_Shifted,"",D10+C26) -> 107 | E26: =IF($B26+E$23>Latest_Year_Shifted,"",E10+D26) -> 119 | F26: =IF($B26+F$23>Latest_Year_Shifted,"",F10+E26) -> 125 | G26: =IF($B26+G$23>Latest_Year_Shifted,"",G10+F26) -> 125 | H26: =IF($B26+H$23>Latest_Year_Shifted,"",H10+G26) -> 125 | I26: =IF($B26+I$23>Latest_Year_Shifted,"",I10+H26) -> 125 | J26: =IF($B26+J$23>Latest_Year_Shifted,"",J10+I26) -> 125 | K26: =IF($B26+K$23>Latest_Year_Shifted,"",K10+J26) | L26: =IF($B26+L$23>Latest_Year_Shifted,"",L10+K26)
A27: =B27 & "/" &B27+1 -> 2007/2008 | B27: =B11 -> 2007 | C27: =C11 -> 72 | D27: =IF($B27+D$23>Latest_Year_Shifted,"",D11+C27) -> 113 | E27: =IF($B27+E$23>Latest_Year_Shifted,"",E11+D27) -> 121 | F27: =IF($B27+F$23>Latest_Year_Shifted,"",F11+E27) -> 125 | G27: =IF($B27+G$23>Latest_Year_Shifted,"",G11+F27) -> 128 | H27: =IF($B27+H$23>Latest_Year_Shifted,"",H11+G27) -> 128 | I27: =IF($B27+I$23>Latest_Year_Shifted,"",I11+H27) -> 129 | J27: =IF($B27+J$23>Latest_Year_Shifted,"",J11+I27) | K27: =IF($B27+K$23>Latest_Year_Shifted,"",K11+J27) | L27: =IF($B27+L$23>Latest_Year_Shifted,"",L11+K27)
A28: =B28 & "/" &B28+1 -> 2008/2009 | B28: =B12 -> 2008 | C28: =C12 -> 105 | D28: =IF($B28+D$23>Latest_Year_Shifted,"",D12+C28) -> 152 | E28: =IF($B28+E$23>Latest_Year_Shifted,"",E12+D28) -> 166 | F28: =IF($B28+F$23>Latest_Year_Shifted,"",F12+E28) -> 170 | G28: =IF($B28+G$23>Latest_Year_Shifted,"",G12+F28) -> 174 | H28: =IF($B28+H$23>Latest_Year_Shifted,"",H12+G28) -> 174 | I28: =IF($B28+I$23>Latest_Year_Shifted,"",I12+H28) | J28: =IF($B28+J$23>Latest_Year_Shifted,"",J12+I28) | K28: =IF($B28+K$23>Latest_Year_Shifted,"",K12+J28) | L28: =IF($B28+L$23>Latest_Year_Shifted,"",L12+K28)
A29: =B29 & "/" &B29+1 -> 2009/2010 | B29: =B13 -> 2009 | C29: =C13 -> 119 | D29: =IF($B29+D$23>Latest_Year_Shifted,"",D13+C29) -> 184 | E29: =IF($B29+E$23>Latest_Year_Shifted,"",E13+D29) -> 203 | F29: =IF($B29+F$23>Latest_Year_Shifted,"",F13+E29) -> 210 | G29: =IF($B29+G$23>Latest_Year_Shifted,"",G13+F29) -> 214 | H29: =IF($B29+H$23>Latest_Year_Shifted,"",H13+G29) | I29: =IF($B29+I$23>Latest_Year_Shifted,"",I13+H29) | J29: =IF($B29+J$23>Latest_Year_Shifted,"",J13+I29) | K29: =IF($B29+K$23>Latest_Year_Shifted,"",K13+J29) | L29: =IF($B29+L$23>Latest_Year_Shifted,"",L13+K29)
A30: =B30 & "/" &B30+1 -> 2010/2011 | B30: =B14 -> 2010 | C30: =C14 -> 169 | D30: =IF($B30+D$23>Latest_Year_Shifted,"",D14+C30) -> 244 | E30: =IF($B30+E$23>Latest_Year_Shifted,"",E14+D30) -> 257 | F30: =IF($B30+F$23>Latest_Year_Shifted,"",F14+E30) -> 268 | G30: =IF($B30+G$23>Latest_Year_Shifted,"",G14+F30) | H30: =IF($B30+H$23>Latest_Year_Shifted,"",H14+G30) | I30: =IF($B30+I$23>Latest_Year_Shifted,"",I14+H30) | J30: =IF($B30+J$23>Latest_Year_Shifted,"",J14+I30) | K30: =IF($B30+K$23>Latest_Year_Shifted,"",K14+J30) | L30: =IF($B30+L$23>Latest_Year_Shifted,"",L14+K30)
A31: =B31 & "/" &B31+1 -> 2011/2012 | B31: =B15 -> 2011 | C31: =C15 -> 116 | D31: =IF($B31+D$23>Latest_Year_Shifted,"",D15+C31) -> 184 | E31: =IF($B31+E$23>Latest_Year_Shifted,"",E15+D31) -> 210 | F31: =IF($B31+F$23>Latest_Year_Shifted,"",F15+E31) | G31: =IF($B31+G$23>Latest_Year_Shifted,"",G15+F31) | H31: =IF($B31+H$23>Latest_Year_Shifted,"",H15+G31) | I31: =IF($B31+I$23>Latest_Year_Shifted,"",I15+H31) | J31: =IF($B31+J$23>Latest_Year_Shifted,"",J15+I31) | K31: =IF($B31+K$23>Latest_Year_Shifted,"",K15+J31) | L31: =IF($B31+L$23>Latest_Year_Shifted,"",L15+K31)
A32: =B32 & "/" &B32+1 -> 2012/2013 | B32: =B16 -> 2012 | C32: =C16 -> 95 | D32: =IF($B32+D$23>Latest_Year_Shifted,"",D16+C32) -> 208 | E32: =IF($B32+E$23>Latest_Year_Shifted,"",E16+D32) | F32: =IF($B32+F$23>Latest_Year_Shifted,"",F16+E32) | G32: =IF($B32+G$23>Latest_Year_Shifted,"",G16+F32) | H32: =IF($B32+H$23>Latest_Year_Shifted,"",H16+G32) | I32: =IF($B32+I$23>Latest_Year_Shifted,"",I16+H32) | J32: =IF($B32+J$23>Latest_Year_Shifted,"",J16+I32) | K32: =IF($B32+K$23>Latest_Year_Shifted,"",K16+J32) | L32: =IF($B32+L$23>Latest_Year_Shifted,"",L16+K32)
A33: =B33 & "/" &B33+1 -> 2013/2014 | B33: =B17 -> 2013 | C33: =C17 -> 136 | D33: =IF($B33+D$23>Latest_Year_Shifted,"",D17+C33) | E33: =IF($B33+E$23>Latest_Year_Shifted,"",E17+D33) | F33: =IF($B33+F$23>Latest_Year_Shifted,"",F17+E33) | G33: =IF($B33+G$23>Latest_Year_Shifted,"",G17+F33) | H33: =IF($B33+H$23>Latest_Year_Shifted,"",H17+G33) | I33: =IF($B33+I$23>Latest_Year_Shifted,"",I17+H33) | J33: =IF($B33+J$23>Latest_Year_Shifted,"",J17+I33) | K33: =IF($B33+K$23>Latest_Year_Shifted,"",K17+J33) | L33: =IF($B33+L$23>Latest_Year_Shifted,"",L17+K33)
L34: Tail factor
A35: Link ratios | B35: Link ratios | C35: =SUM(D25:D33)/SUMIF(D25:D33,">0",C25:C33) -> 1.5844806 | D35: =SUM(E25:E33)/SUMIF(E25:E33,">0",D25:D33) -> 1.094518 | E35: =SUM(F25:F33)/SUMIF(F25:F33,">0",E25:E33) -> 1.0400844 | F35: =SUM(G25:G33)/SUMIF(G25:G33,">0",F25:F33) -> 1.0181058 | G35: =SUM(H25:H33)/SUMIF(H25:H33,">0",G25:G33) -> 1 | H35: =SUM(I25:I33)/SUMIF(I25:I33,">0",H25:H33) -> 1.0029155 | I35: =SUM(J25:J33)/SUMIF(J25:J33,">0",I25:I33) -> 1 | J35: =SUM(K24:K33)/SUMIF(K24:K33,">0",J24:J33) -> 1 | K35: =SUM(L24:L33)/SUMIF(L24:L33,">0",K24:K33) -> 1 | L35: 1
A36: Cumulative | B36: Cumulative | C36: =C35*D36 -> 1.8417711 | D36: =D35*E36 -> 1.1623816 | E36: =E35*F36 -> 1.0620032 | F36: =F35*G36 -> 1.0210741 | G36: =G35*H36 -> 1.0029155 | H36: =H35*I36 -> 1.0029155 | I36: =I35*J36 -> 1 | J36: =J35 -> 1 | K36: =K35 -> 1 | L36: 1
A39: 3 - Projected claim counts
H40: Delay (years)
D41: 0 | E41: 1 | F41: 2 | G41: 3 | H41: 4 | I41: 5 | J41: 6 | K41: 7 | L41: 8 | M41: 9 | N41: Ultimate | O41: IBNR
B42: =C42 & "/" &C42+1 -> 2004/2005 | C42: =B8 -> 2004 | D42: =IF(ISNUMBER(C24),C24,"") -> 24 | E42: =IF(ISNUMBER(D24),D24,"") -> 42 | F42: =IF(ISNUMBER(E24),E24,"") -> 45 | G42: =IF(ISNUMBER(F24),F24,"") -> 47 | H42: =IF(ISNUMBER(G24),G24,"") -> 48 | I42: =IF(ISNUMBER(H24),H24,"") -> 48 | J42: =IF(ISNUMBER(I24),I24,"") -> 48 | K42: =IF(ISNUMBER(J24),J24,"") -> 48 | ... M42: =IF(ISNUMBER(L24),L24,"") -> 48 | N42: =M42*L$36 -> 48 | O42: =N42-MAX(D42:M42) -> 0
B43: =C43 & "/" &C43+1 -> 2005/2006 | C43: =B9 -> 2005 | D43: =IF(ISNUMBER(C25),C25,"") -> 51 | E43: =IF(ISNUMBER(D25),D25,"") -> 74 | F43: =IF(ISNUMBER(E25),E25,"") -> 82 | G43: =IF(ISNUMBER(F25),F25,"") -> 88 | H43: =IF(ISNUMBER(G25),G25,"") -> 90 | I43: =IF(ISNUMBER(H25),H25,"") -> 90 | J43: =IF(ISNUMBER(I25),I25,"") -> 90 | K43: =IF(ISNUMBER(J25),J25,"") -> 90 | ... M43: =IF(ISNUMBER(L25),L25,"") | N43: =L43*K$36 -> 90 | O43: =N43-MAX(D43:M43) -> 0
B44: =C44 & "/" &C44+1 -> 2006/2007 | C44: =B10 -> 2006 | D44: =IF(ISNUMBER(C26),C26,"") -> 72 | E44: =IF(ISNUMBER(D26),D26,"") -> 107 | F44: =IF(ISNUMBER(E26),E26,"") -> 119 | G44: =IF(ISNUMBER(F26),F26,"") -> 125 | H44: =IF(ISNUMBER(G26),G26,"") -> 125 | I44: =IF(ISNUMBER(H26),H26,"") -> 125 | J44: =IF(ISNUMBER(I26),I26,"") -> 125 | K44: =IF(ISNUMBER(J26),J26,"") -> 125 | ... M44: =IF(ISNUMBER(L26),L26,"") | N44: =K44*J$36 -> 125 | O44: =N44-MAX(D44:M44) -> 0
B45: =C45 & "/" &C45+1 -> 2007/2008 | C45: =B11 -> 2007 | D45: =IF(ISNUMBER(C27),C27,"") -> 72 | E45: =IF(ISNUMBER(D27),D27,"") -> 113 | F45: =IF(ISNUMBER(E27),E27,"") -> 121 | G45: =IF(ISNUMBER(F27),F27,"") -> 125 | H45: =IF(ISNUMBER(G27),G27,"") -> 128 | I45: =IF(ISNUMBER(H27),H27,"") -> 128 | J45: =IF(ISNUMBER(I27),I27,"") -> 129 | K45: =IF(ISNUMBER(J27),J27,"") | ... M45: =IF(ISNUMBER(L27),L27,"") | N45: =J45*I$36 -> 129 | O45: =N45-MAX(D45:M45) -> 0
B46: =C46 & "/" &C46+1 -> 2008/2009 | C46: =B12 -> 2008 | D46: =IF(ISNUMBER(C28),C28,"") -> 105 | E46: =IF(ISNUMBER(D28),D28,"") -> 152 | F46: =IF(ISNUMBER(E28),E28,"") -> 166 | G46: =IF(ISNUMBER(F28),F28,"") -> 170 | H46: =IF(ISNUMBER(G28),G28,"") -> 174 | I46: =IF(ISNUMBER(H28),H28,"") -> 174 | J46: =IF(ISNUMBER(I28),I28,"") | K46: =IF(ISNUMBER(J28),J28,"") | ... M46: =IF(ISNUMBER(L28),L28,"") | N46: =I46*H$36 -> 174.50729 | O46: =N46-MAX(D46:M46) -> 0.50728863
B47: =C47 & "/" &C47+1 -> 2009/2010 | C47: =B13 -> 2009 | D47: =IF(ISNUMBER(C29),C29,"") -> 119 | E47: =IF(ISNUMBER(D29),D29,"") -> 184 | F47: =IF(ISNUMBER(E29),E29,"") -> 203 | G47: =IF(ISNUMBER(F29),F29,"") -> 210 | H47: =IF(ISNUMBER(G29),G29,"") -> 214 | I47: =IF(ISNUMBER(H29),H29,"") | J47: =IF(ISNUMBER(I29),I29,"") | K47: =IF(ISNUMBER(J29),J29,"") | ... M47: =IF(ISNUMBER(L29),L29,"") | N47: =H47*G$36 -> 214.62391 | O47: =N47-MAX(D47:M47) -> 0.62390671
B48: =C48 & "/" &C48+1 -> 2010/2011 | C48: =B14 -> 2010 | D48: =IF(ISNUMBER(C30),C30,"") -> 169 | E48: =IF(ISNUMBER(D30),D30,"") -> 244 | F48: =IF(ISNUMBER(E30),E30,"") -> 257 | G48: =IF(ISNUMBER(F30),F30,"") -> 268 | H48: =IF(ISNUMBER(G30),G30,"") | I48: =IF(ISNUMBER(H30),H30,"") | J48: =IF(ISNUMBER(I30),I30,"") | K48: =IF(ISNUMBER(J30),J30,"") | ... M48: =IF(ISNUMBER(L30),L30,"") | N48: =G48*F$36 -> 273.64786 | O48: =N48-MAX(D48:M48) -> 5.6478556 | Q48: 177
B49: =C49 & "/" &C49+1 -> 2011/2012 | C49: =B15 -> 2011 | D49: =IF(ISNUMBER(C31),C31,"") -> 116 | E49: =IF(ISNUMBER(D31),D31,"") -> 184 | F49: =IF(ISNUMBER(E31),E31,"") -> 210 | G49: =IF(ISNUMBER(F31),F31,"") | H49: =IF(ISNUMBER(G31),G31,"") | I49: =IF(ISNUMBER(H31),H31,"") | J49: =IF(ISNUMBER(I31),I31,"") | K49: =IF(ISNUMBER(J31),J31,"") | ... M49: =IF(ISNUMBER(L31),L31,"") | N49: =F49*E$36 -> 223.02068 | O49: =N49-MAX(D49:M49) -> 13.020676 | Q49: =O49/3+O50*2/3 -> 26.85714
B50: =C50 & "/" &C50+1 -> 2012/2013 | C50: =B16 -> 2012 | D50: =IF(ISNUMBER(C32),C32,"") -> 95 | E50: =IF(ISNUMBER(D32),D32,"") -> 208 | F50: =IF(ISNUMBER(E32),E32,"") | G50: =IF(ISNUMBER(F32),F32,"") | H50: =IF(ISNUMBER(G32),G32,"") | I50: =IF(ISNUMBER(H32),H32,"") | J50: =IF(ISNUMBER(I32),I32,"") | K50: =IF(ISNUMBER(J32),J32,"") | ... M50: =IF(ISNUMBER(L32),L32,"") | N50: =E50*D$36 -> 241.77537 | O50: =N50-MAX(D50:M50) -> 33.775372 | Q50: =Q48+Q49 -> 203.85714
B51: =C51 & "/" &C51+1 -> 2013/2014 | C51: =B17 -> 2013 | D51: =IF(ISNUMBER(C33),C33,"") -> 136 | E51: =IF(ISNUMBER(D33),D33,"") | F51: =IF(ISNUMBER(E33),E33,"") | G51: =IF(ISNUMBER(F33),F33,"") | H51: =IF(ISNUMBER(G33),G33,"") | I51: =IF(ISNUMBER(H33),H33,"") | J51: =IF(ISNUMBER(I33),I33,"") | K51: =IF(ISNUMBER(J33),J33,"") | ... M51: =IF(ISNUMBER(L33),L33,"") | N51: =D51*C$36 -> 250.48087 | O51: =N51-MAX(D51:M51) -> 114.48087
A54: 4 - Shift back to original policy year basis
A55: SHIFTED-POLICY-YEAR BASIS | F55: ORIGINAL-POLICY-YEAR BASIS
A56: Shifted PY | B56: Reported | C56: Ultimate | D56: IBNR | F56: Original PY | G56: Reported | H56: IBNR (approx.) | I56: Ultimate - Method (iv)
A57: =B42 -> 2004/2005 | B57: =MAX(D42:M42) -> 48 | C57: =N42 -> 48 | D57: =O42 -> 0 | F57: =Earliest_Year -> 2005 | G57: =MAX('3. Projection - Methods 1 and 2'!O44:W44) -> 86 | H57: =4/12*D57+8/12*D58 -> 0 | I57: =SUM(G57:H57) -> 86
A58: =B43 -> 2005/2006 | B58: =MAX(D43:M43) -> 90 | C58: =N43 -> 90 | D58: =O43 -> 0 | F58: =F57+1 -> 2006 | G58: =MAX('3. Projection - Methods 1 and 2'!O45:W45) -> 92 | H58: =4/12*D58+8/12*D59 -> 0 | I58: =SUM(G58:H58) -> 92
A59: =B44 -> 2006/2007 | B59: =MAX(D44:M44) -> 125 | C59: =N44 -> 125 | D59: =O44 -> 0 | F59: =F58+1 -> 2007 | G59: =MAX('3. Projection - Methods 1 and 2'!O46:W46) -> 110 | H59: =4/12*D59+8/12*D60 -> 0 | I59: =SUM(G59:H59) -> 110
A60: =B45 -> 2007/2008 | B60: =MAX(D45:M45) -> 129 | C60: =N45 -> 129 | D60: =O45 -> 0 | F60: =F59+1 -> 2008 | G60: =MAX('3. Projection - Methods 1 and 2'!O47:W47) -> 145 | H60: =4/12*D60+8/12*D61 -> 0.33819242 | I60: =SUM(G60:H60) -> 145.33819 | AB60: =24/55 -> 0.43636364
A61: =B46 -> 2008/2009 | B61: =MAX(D46:M46) -> 174 | C61: =N46 -> 174.50729 | D61: =O46 -> 0.50728863 | F61: =F60+1 -> 2009 | G61: =MAX('3. Projection - Methods 1 and 2'!O48:W48) -> 192 | H61: =4/12*D61+8/12*D62 -> 0.58503401 | I61: =SUM(G61:H61) -> 192.58503 | AB61: =293/568 -> 0.51584507
A62: =B47 -> 2009/2010 | B62: =MAX(D47:M47) -> 214 | C62: =N47 -> 214.62391 | D62: =O47 -> 0.62390671 | F62: =F61+1 -> 2010 | G62: =MAX('3. Projection - Methods 1 and 2'!O49:W49) -> 253 | H62: =4/12*D62+8/12*D63 -> 3.973206 | I62: =SUM(G62:H62) -> 256.97321
A63: =B48 -> 2010/2011 | B63: =MAX(D48:M48) -> 268 | C63: =N48 -> 273.64786 | D63: =O48 -> 5.6478556 | F63: =F62+1 -> 2011 | G63: =MAX('3. Projection - Methods 1 and 2'!O50:W50) -> 241 | H63: =4/12*D63+8/12*D64 -> 10.563069 | I63: =SUM(G63:H63) -> 251.56307
A64: =B49 -> 2011/2012 | B64: =MAX(D49:M49) -> 210 | C64: =N49 -> 223.02068 | D64: =O49 -> 13.020676 | F64: =F63+1 -> 2012 | G64: =MAX('3. Projection - Methods 1 and 2'!O51:W51) -> 177 | H64: =4/12*D64+8/12*D65 -> 26.85714 | I64: =SUM(G64:H64) -> 203.85714
A65: =B50 -> 2012/2013 | B65: =MAX(D50:M50) -> 208 | C65: =N50 -> 241.77537 | D65: =O50 -> 33.775372 | F65: =F64+1 -> 2013 | G65: =MAX('3. Projection - Methods 1 and 2'!O52:W52) -> 102 | H65: =4/12*D65+8/12*D66 -> 87.579036 | I65: =SUM(G65:H65) -> 189.57904
A66: =B51 -> 2013/2014 | B66: =MAX(D51:M51) -> 136 | C66: =N51 -> 250.48087 | D66: =O51 -> 114.48087
Z67: PROJECTED CLAIM COUNTS
Y68: Original PY | Z68: Method (i) - Ignore last diagonal | AA68: Method (ii) - Gross up last diagonal | AB68: Method (iii) - Choose a shorter period | AC68: Method (iv) - Shift policy years
Y69: 2002 | Z69: =G57+H57 -> 86 | AA69: ='3. Projection - Methods 1 and 2'!L77 -> 86 | AB69: ='4. Projection - Method 3'!E121 -> 86 | AC69: =I57 -> 86 | AE69: =MAX(Z69:AC69)-MIN(Z69:AC69) -> 0 | AF69: =AE69/MIN(Z69:AC69) -> 0
Y70: 2003 | Z70: =G58+H58 -> 92 | AA70: ='3. Projection - Methods 1 and 2'!L78 -> 92 | AB70: ='4. Projection - Method 3'!E122 -> 92 | AC70: =I58 -> 92 | AE70: =MAX(Z70:AC70)-MIN(Z70:AC70) -> 0 | AF70: =AE70/MIN(Z70:AC70) -> 0
Y71: 2004 | Z71: =G59+H59 -> 110 | AA71: ='3. Projection - Methods 1 and 2'!L79 -> 110 | AB71: ='4. Projection - Method 3'!E123 -> 110 | AC71: =I59 -> 110 | AE71: =MAX(Z71:AC71)-MIN(Z71:AC71) -> 0 | AF71: =AE71/MIN(Z71:AC71) -> 0
Y72: 2005 | Z72: =G60+H60 -> 145.33819 | AA72: ='3. Projection - Methods 1 and 2'!L80 -> 146.5 | AB72: ='4. Projection - Method 3'!E124 -> 146.32416 | AC72: =I60 -> 145.33819 | AE72: =MAX(Z72:AC72)-MIN(Z72:AC72) -> 1.1618076 | AF72: =AE72/MIN(Z72:AC72) -> 0.0079938216
Y73: 2006 | Z73: =G61+H61 -> 192.58503 | AA73: ='3. Projection - Methods 1 and 2'!L81 -> 195.67552 | AB73: ='4. Projection - Method 3'!E125 -> 194.59327 | AC73: =I61 -> 192.58503 | AE73: =MAX(Z73:AC73)-MIN(Z73:AC73) -> 3.0904856 | AF73: =AE73/MIN(Z73:AC73) -> 0.016047382
Y74: 2007 | Z74: =G62+H62 -> 256.97321 | AA74: ='3. Projection - Methods 1 and 2'!L82 -> 259.63231 | AB74: ='4. Projection - Method 3'!E126 -> 257.88157 | AC74: =I62 -> 256.97321 | AE74: =MAX(Z74:AC74)-MIN(Z74:AC74) -> 2.6591081 | AF74: =AE74/MIN(Z74:AC74) -> 0.010347803
Y75: 2008 | Z75: =G63+H63 -> 251.56307 | AA75: ='3. Projection - Methods 1 and 2'!L83 -> 260.59389 | AB75: ='4. Projection - Method 3'!E127 -> 257.93256 | AC75: =I63 -> 251.56307 | AE75: =MAX(Z75:AC75)-MIN(Z75:AC75) -> 9.0308247 | AF75: =AE75/MIN(Z75:AC75) -> 0.035898849
Y76: 2009 | Z76: =G64+H64 -> 203.85714 | AA76: ='3. Projection - Methods 1 and 2'!L84 -> 224.31231 | AB76: ='4. Projection - Method 3'!E128 -> 215.12881 | AC76: =I64 -> 203.85714 | AE76: =MAX(Z76:AC76)-MIN(Z76:AC76) -> 20.455175 | AF76: =AE76/MIN(Z76:AC76) -> 0.10034073
Y77: 2010 | Z77: =G65+H65 -> 189.57904 | AA77: ='3. Projection - Methods 1 and 2'!L85 -> 296.10135 | AB77: ='4. Projection - Method 3'!E129 -> 252.34561 | AC77: =I65 -> 189.57904 | AE77: =MAX(Z77:AC77)-MIN(Z77:AC77) -> 106.52231 | AF77: =AE77/MIN(Z77:AC77) -> 0.56188867

Sheet 6. Comparison of methods
E4: Projected Claim Counts
C5: Policy year | D5: Reported | E5: Ultimate (Method 1 - ignore last diagonal) | F5: Ultimate Method 2 - Gross up) | G5: Ultimate (Method 3 - Divide into shorter periods) | H5: Ultimate (Method 4 - Shift)
C6: =Earliest_Year -> 2005 | D6: =SUMIFS(Table1[Non-zero? (1=Yes)],Table1[Policy Year],"="&C6) -> 86 | E6: ='3. Projection - Methods 1 and 2'!X44 -> 86 | F6: ='3. Projection - Methods 1 and 2'!L77 -> 86 | G6: ='4. Projection - Method 3'!E121 -> 86 | H6: ='5. Projection - Method 4'!I57 -> 86
C7: =C6+1 -> 2006 | D7: =SUMIFS(Table1[Non-zero? (1=Yes)],Table1[Policy Year],"="&C7) -> 92 | E7: ='3. Projection - Methods 1 and 2'!X45 -> 92 | F7: ='3. Projection - Methods 1 and 2'!L78 -> 92 | G7: ='4. Projection - Method 3'!E122 -> 92 | H7: ='5. Projection - Method 4'!I58 -> 92
C8: =C7+1 -> 2007 | D8: =SUMIFS(Table1[Non-zero? (1=Yes)],Table1[Policy Year],"="&C8) -> 110 | E8: ='3. Projection - Methods 1 and 2'!X46 -> 110 | F8: ='3. Projection - Methods 1 and 2'!L79 -> 110 | G8: ='4. Projection - Method 3'!E123 -> 110 | H8: ='5. Projection - Method 4'!I59 -> 110
C9: =C8+1 -> 2008 | D9: =SUMIFS(Table1[Non-zero? (1=Yes)],Table1[Policy Year],"="&C9) -> 146 | E9: ='3. Projection - Methods 1 and 2'!X47 -> 145 | F9: ='3. Projection - Methods 1 and 2'!L80 -> 146.5 | G9: ='4. Projection - Method 3'!E124 -> 146.32416 | H9: ='5. Projection - Method 4'!I60 -> 145.33819
C10: =C9+1 -> 2009 | D10: =SUMIFS(Table1[Non-zero? (1=Yes)],Table1[Policy Year],"="&C10) -> 194 | E10: ='3. Projection - Methods 1 and 2'!X48 -> 192 | F10: ='3. Projection - Methods 1 and 2'!L81 -> 195.67552 | G10: ='4. Projection - Method 3'!E125 -> 194.59327 | H10: ='5. Projection - Method 4'!I61 -> 192.58503
C11: =C10+1 -> 2010 | D11: =SUMIFS(Table1[Non-zero? (1=Yes)],Table1[Policy Year],"="&C11) -> 256 | E11: ='3. Projection - Methods 1 and 2'!X49 -> 256.69643 | F11: ='3. Projection - Methods 1 and 2'!L82 -> 259.63231 | G11: ='4. Projection - Method 3'!E126 -> 257.88157 | H11: ='5. Projection - Method 4'!I62 -> 256.97321
C12: =C11+1 -> 2011 | D12: =SUMIFS(Table1[Non-zero? (1=Yes)],Table1[Policy Year],"="&C12) -> 250 | E12: ='3. Projection - Methods 1 and 2'!X50 -> 254.17325 | F12: ='3. Projection - Methods 1 and 2'!L83 -> 260.59389 | G12: ='4. Projection - Method 3'!E127 -> 257.93256 | H12: ='5. Projection - Method 4'!I63 -> 251.56307
C13: =C12+1 -> 2012 | D13: =SUMIFS(Table1[Non-zero? (1=Yes)],Table1[Policy Year],"="&C13) -> 199 | E13: ='3. Projection - Methods 1 and 2'!X51 -> 203.90358 | F13: ='3. Projection - Methods 1 and 2'!L84 -> 224.31231 | G13: ='4. Projection - Method 3'!E128 -> 215.12881 | H13: ='5. Projection - Method 4'!I64 -> 203.85714
C14: =C13+1 -> 2013 | D14: =SUMIFS(Table1[Non-zero? (1=Yes)],Table1[Policy Year],"="&C14) -> 201 | E14: ='3. Projection - Methods 1 and 2'!X52 -> 179.33973 | F14: ='3. Projection - Methods 1 and 2'!L85 -> 296.10135 | G14: ='4. Projection - Method 3'!E129 -> 252.34561 | H14: ='5. Projection - Method 4'!I65 -> 189.57904
C15: =C14+1 -> 2014 | D15: =SUMIFS(Table1[Non-zero? (1=Yes)],Table1[Policy Year],"="&C15) -> 68 | E15: ='3. Projection - Methods 1 and 2'!X53 -> 0 | F15: ='3. Projection - Methods 1 and 2'!L86 -> 197.24904 | G15: ='4. Projection - Method 3'!E130 -> 208.85322 | H15: ='5. Projection - Method 4'!I66 -> 0
